Workbook
Name DynDate: OFFSET(NAV!$B$3,0,0,COUNTA(NAV!$B:$B),1)
Name DynITD: OFFSET(NAV!$M$3,0,0,COUNTA(NAV!$M:$M)-1,1)
Name DynMTD: OFFSET(NAV!$N$3,0,0,COUNTA(NAV!$N:$N)-1,1)
Name DynNAV: OFFSET(NAV!$L$3,0,0,COUNTA(NAV!$L:$L)-1,1)

Sheet Blotter
B2: Data | C2: Close | E2: Equity | F2: Futures
B3: AUM | C3: =OFFSET(NAV!B1,MATCH(TODAY(),NAV!B:B,1),8) -> 0 | E3: Commodities | F3: Stocks
B4: P&L $ | C4: =SUM(N18:N1012) -> -516288.43 | E4: FX | F4: Call
B5: Performance ITD % | C5: =OFFSET(NAV!B1,MATCH(TODAY(),NAV!B:B,1),11) -> 0 | E5: Fixed income | F5: Put
B6: Performance MTD % | C6: =OFFSET(NAV!B1,MATCH(TODAY(),NAV!B:B,1),12) -> 0
B7: Risk-free P&L $ | C7: =Cash_Mgmt!H13 -> -3376 | D7: =C7/C3 -> #DIV/0!
B8: Projected P&L $ | C8: =C4+C7 -> -519664.43 | D8: =C5+D7 -> #DIV/0!
B9: Notional Futures $ | C9: {=SUM((F19:F112="Futures")*(M19:M112))} -> 0 | D9: =C9/$C$3 -> #DIV/0!
B10: Notional Call $ | C10: {=SUM((F19:F1012="Call")*(M19:M1012))} -> 0 | D10: =C10/$C$3 -> #DIV/0!
B11: Notional Put $ | C11: {=SUM((F19:F212="Put")*(M19:M212))} -> 0 | D11: =C11/$C$3 -> #DIV/0!
B12: Open Risk $ | C12: {=SUM((PLB!G4:G999="O")*(PLB!E4:E999))} -> 0 | D12: =C12/$C$3 -> #DIV/0!
B13: Open P&L $ | C13: {=SUM((PLB!G4:G999="O")*(PLB!D4:D999))} -> 0 | D13: =C13/$C$3 -> #DIV/0!
B14: PLB Risk $ | C14: =C12+C13 -> 0 | D14: =C14/$C$3 -> #DIV/0!
B17: TICKER | C17: WEEK | D17: UNDERLYING | E17: ASSET CLASS | F17: INSTRUMENT | G17: MAX QUANTITY | H17: INITIAL QUANTITY | I17: QUANTITY | J17: MULTIPLIER | K17: ENTRY PRICE | L17: EXIT PRICE | M17: NOTIONAL $ | N17: P&L $ | O17: ATR | P17: INITIAL RISK | Q17: ROLL | R17: INITIAL RISK $ | S17: VOL SL | T17: VOL/EXIT-1 | U17: TECH SL | V17: TECH/EXIT -1 | X17: <0 | Y17: >0 | Z17: Market Data
B18: CASH MGMT | E18: Fixed income | N18: =Cash_Mgmt!G13 -> 12955.38
B19: SPX 230616P03850000 | C19: 1 | D19: SPX | E19: Equity | F19: Put | G19: =IF(F19="Futures",VLOOKUP(D19,Multiplier!B:I,8,0),0) -> 0 | H19: 6 | I19: {=SUM((Trades!V$2:V$9999)*(Trades!U$2:U$9999=Blotter!B19)*(Trades!$T$2:T$9999=Blotter!C19))} -> 0 | J19: =VLOOKUP(D19,Multiplier!B:D,2,0) -> 100 | K19: =L19-N19/(H19*J19) -> 41.027231 | L19: =IF(I19=0,IF(H19>0,X19,Y19),Z19) -> 27 | M19: =I19*J19*L19 -> 0 | N19: {=-SUM((Trades!T$2:T$9999=Blotter!C19)*(Trades!U$2:U$9999=Blotter!B19)*(Trades!V$2:V$9999)*(Trades!W$2:W$9999))*J19+SUM((Trades!T$2:T$9999=Blotter!C19)*(Trades!U$2:U$9999=Blotter!B19)*(Trades!X$2:X$9999))+(L19*I19)*J19} -> -8416.3386 | O19: =VLOOKUP(D19,Multiplier!B:H,3,0) -> 42 | P19: 41 | R19: =(1-Q19)*P19*J19*H19 -> 24600 | S19: =IF(OR(F19="Futures",F19="Stocks"),IF(I19=0,0,IF(I19>0,L19-O19,L19+O19)),0) -> 0 | T19: =IF(S19>0,IF(ISNUMBER(S19/L19-1),S19/L19-1,0),0) -> 0 | U19: =IF(OR(F19="Futures",F19="Stocks"),IF(I19=0,0,IF(I19>0,K19-P19,K19+P19)),0) -> 0 | V19: =IF(U19>0,IF(ISNUMBER(U19/L19-1),U19/L19-1,0),0) -> 0 | X19: {=IF(ISNUMBER(SUM((Trades!T$2:T$9999=Blotter!C19)*(Trades!U$2:U$9999=Blotter!B19)*(Trades!W$2:W$9999)*(Trades!V$2:V$9999)*(Trades!V$2:V$9999<0))/SUM((Trades!T$2:T$9999=Blotter!C19)*(Trades!U$2:U$9999=Blotter!B19)*(Trades!V$2:V$9999)*(Trades!V$2:V$9999<0))),SUM((Trades!T$2:T$9999=Blotter!C19)*(Trades!U$2:U$9999=Blotter!B19)*(Trades!W$2:W$9999)*(Trades!V$2:V$9999)*(Trades!V$2:V$9999<0))/SUM((Trades!T$2:T$9999=Blotter!C19)*(Trades!U$2:U$9999=Blotter!B19)*(Trades!V$2:V$9999)*(Trades!V$2:V$9999<0)),0)} -> 27 | Y19: {=IF(ISNUMBER(SUM((Trades!T$2:T$9999=Blotter!C19)*(Trades!U$2:U$9999=Blotter!B19)*(Trades!W$2:W$9999)*(Trades!V$2:V$9999)*(Trades!V$2:V$9999>0))/SUM((Trades!T$2:T$9999=Blotter!C19)*(Trades!U$2:U$9999=Blotter!B19)*(Trades!V$2:V$9999)*(Trades!V$2:V$9999>0))),SUM((Trades!T$2:T$9999=Blotter!C19)*(Trades!U$2:U$9999=Blotter!B19)*(Trades!W$2:W$9999)*(Trades!V$2:V$9999)*(Trades!V$2:V$9999>0))/SUM((Trades!T$2:T$9999=Blotter!C19)*(Trades!U$2:U$9999=Blotter!B19)*(Trades!V$2:V$9999)*(Trades!V$2:V$9999>0)),0)} -> 41 | Z19: =IF(C$2="Last",IF(ISNUMBER(VLOOKUP(B19,Data_IB!B:O,14,0)),VLOOKUP(B19,Data_IB!B:O,14,0),0),IF(ISNUMBER(VLOOKUP(B19,Data_IB!B:O,13,0)),VLOOKUP(B19,Data_IB!B:O,13,0),0)) -> 0
B20: SPX 230616P03700000 | C20: 1 | D20: SPX | E20: Equity | F20: Put | G20: =IF(F20="Futures",VLOOKUP(D20,Multiplier!B:I,8,0),0) -> 0 | H20: -6 | I20: {=SUM((Trades!V$2:V$9999)*(Trades!U$2:U$9999=Blotter!B20)*(Trades!$T$2:T$9999=Blotter!C20))} -> 0 | J20: =VLOOKUP(D20,Multiplier!B:D,2,0) -> 100 | K20: =L20-N20/(H20*J20) -> 24.486384 | L20: =IF(I20=0,IF(H20>0,X20,Y20),Z20) -> 0 | M20: =I20*J20*L20 -> 0 | N20: {=-SUM((Trades!T$2:T$9999=Blotter!C20)*(Trades!U$2:U$9999=Blotter!B20)*(Trades!V$2:V$9999)*(Trades!W$2:W$9999))*J20+SUM((Trades!T$2:T$9999=Blotter!C20)*(Trades!U$2:U$9999=Blotter!B20)*(Trades!X$2:X$9999))+(L20*I20)*J20} -> 14691.831 | O20: =VLOOKUP(D20,Multiplier!B:H,3,0) -> 42 | P20: 24.5 | R20: =(1-Q20)*P20*J20*H20 -> -14700 | S20: =IF(OR(F20="Futures",F20="Stocks"),IF(I20=0,0,IF(I20>0,L20-O20,L20+O20)),0) -> 0 | T20: =IF(S20>0,IF(ISNUMBER(S20/L20-1),S20/L20-1,0),0) -> 0 | U20: =IF(OR(F20="Futures",F20="Stocks"),IF(I20=0,0,IF(I20>0,K20-P20,K20+P20)),0) -> 0 | V20: =IF(U20>0,IF(ISNUMBER(U20/L20-1),U20/L20-1,0),0) -> 0 | X20: {=IF(ISNUMBER(SUM((Trades!T$2:T$9999=Blotter!C20)*(Trades!U$2:U$9999=Blotter!B20)*(Trades!W$2:W$9999)*(Trades!V$2:V$9999)*(Trades!V$2:V$9999<0))/SUM((Trades!T$2:T$9999=Blotter!C20)*(Trades!U$2:U$9999=Blotter!B20)*(Trades!V$2:V$9999)*(Trades!V$2:V$9999<0))),SUM((Trades!T$2:T$9999=Blotter!C20)*(Trades!U$2:U$9999=Blotter!B20)*(Trades!W$2:W$9999)*(Trades!V$2:V$9999)*(Trades!V$2:V$9999<0))/SUM((Trades!T$2:T$9999=Blotter!C20)*(Trades!U$2:U$9999=Blotter!B20)*(Trades!V$2:V$9999)*(Trades!V$2:V$9999<0)),0)} -> 24.5 | Y20: {=IF(ISNUMBER(SUM((Trades!T$2:T$9999=Blotter!C20)*(Trades!U$2:U$9999=Blotter!B20)*(Trades!W$2:W$9999)*(Trades!V$2:V$9999)*(Trades!V$2:V$9999>0))/SUM((Trades!T$2:T$9999=Blotter!C20)*(Trades!U$2:U$9999=Blotter!B20)*(Trades!V$2:V$9999)*(Trades!V$2:V$9999>0))),SUM((Trades!T$2:T$9999=Blotter!C20)*(Trades!U$2:U$9999=Blotter!B20)*(Trades!W$2:W$9999)*(Trades!V$2:V$9999)*(Trades!V$2:V$9999>0))/SUM((Trades!T$2:T$9999=Blotter!C20)*(Trades!U$2:U$9999=Blotter!B20)*(Trades!V$2:V$9999)*(Trades!V$2:V$9999>0)),0)} -> 0 | Z20: =IF(C$2="Last",IF(ISNUMBER(VLOOKUP(B20,Data_IB!B:O,14,0)),VLOOKUP(B20,Data_IB!B:O,14,0),0),IF(ISNUMBER(VLOOKUP(B20,Data_IB!B:O,13,0)),VLOOKUP(B20,Data_IB!B:O,13,0),0)) -> 0
B21: NGK3 | C21: 2 | D21: NG | E21: Commodities | F21: Futures | G21: =IF(F21="Futures",VLOOKUP(D21,Multiplier!B:I,8,0),0) -> 8 | H21: 5 | I21: {=SUM((Trades!V$2:V$9999)*(Trades!U$2:U$9999=Blotter!B21)*(Trades!$T$2:T$9999=Blotter!C21))} -> 0 | J21: =VLOOKUP(D21,Multiplier!B:D,2,0) -> 10000 | K21: =L21-N21/(H21*J21) -> 2.208474 | L21: =IF(I21=0,IF(H21>0,X21,Y21),Z21) -> 2.25 | M21: =I21*J21*L21 -> 0 | N21: {=-SUM((Trades!T$2:T$9999=Blotter!C21)*(Trades!U$2:U$9999=Blotter!B21)*(Trades!V$2:V$9999)*(Trades!W$2:W$9999))*J21+SUM((Trades!T$2:T$9999=Blotter!C21)*(Trades!U$2:U$9999=Blotter!B21)*(Trades!X$2:X$9999))+(L21*I21)*J21} -> 2076.3 | O21: =VLOOKUP(D21,Multiplier!B:H,3,0) -> 0.132 | P21: 0.18 | R21: =(1-Q21)*P21*J21*H21 -> 9000 | S21: =IF(OR(F21="Futures",F21="Stocks"),IF(I21=0,0,IF(I21>0,L21-O21,L21+O21)),0) -> 0 | T21: =IF(S21>0,IF(ISNUMBER(S21/L21-1),S21/L21-1,0),0) -> 0 | U21: =IF(OR(F21="Futures",F21="Stocks"),IF(I21=0,0,IF(I21>0,K21-P21,K21+P21)),0) -> 0 | V21: =IF(U21>0,IF(ISNUMBER(U21/L21-1),U21/L21-1,0),0) -> 0 | X21: {=IF(ISNUMBER(SUM((Trades!T$2:T$9999=Blotter!C21)*(Trades!U$2:U$9999=Blotter!B21)*(Trades!W$2:W$9999)*(Trades!V$2:V$9999)*(Trades!V$2:V$9999<0))/SUM((Trades!T$2:T$9999=Blotter!C21)*(Trades!U$2:U$9999=Blotter!B21)*(Trades!V$2:V$9999)*(Trades!V$2:V$9999<0))),SUM((Trades!T$2:T$9999=Blotter!C21)*(Trades!U$2:U$9999=Blotter!B21)*(Trades!W$2:W$9999)*(Trades!V$2:V$9999)*(Trades!V$2:V$9999<0))/SUM((Trades!T$2:T$9999=Blotter!C21)*(Trades!U$2:U$9999=Blotter!B21)*(Trades!V$2:V$9999)*(Trades!V$2:V$9999<0)),0)} -> 2.25 | Y21: {=IF(ISNUMBER(SUM((Trades!T$2:T$9999=Blotter!C21)*(Trades!U$2:U$9999=Blotter!B21)*(Trades!W$2:W$9999)*(Trades!V$2:V$9999)*(Trades!V$2:V$9999>0))/SUM((Trades!T$2:T$9999=Blotter!C21)*(Trades!U$2:U$9999=Blotter!B21)*(Trades!V$2:V$9999)*(Trades!V$2:V$9999>0))),SUM((Trades!T$2:T$9999=Blotter!C21)*(Trades!U$2:U$9999=Blotter!B21)*(Trades!W$2:W$9999)*(Trades!V$2:V$9999)*(Trades!V$2:V$9999>0))/SUM((Trades!T$2:T$9999=Blotter!C21)*(Trades!U$2:U$9999=Blotter!B21)*(Trades!V$2:V$9999)*(Trades!V$2:V$9999>0)),0)} -> 2.208 | Z21: =IF(C$2="Last",IF(ISNUMBER(VLOOKUP(B21,Data_IB!B:O,14,0)),VLOOKUP(B21,Data_IB!B:O,14,0),0),IF(ISNUMBER(VLOOKUP(B21,Data_IB!B:O,13,0)),VLOOKUP(B21,Data_IB!B:O,13,0),0)) -> 0
B22: NGM3 | C22: 2 | D22: NG | E22: Commodities | F22: Futures | G22: =IF(F22="Futures",VLOOKUP(D22,Multiplier!B:I,8,0),0) -> 8 | H22: 5 | I22: {=SUM((Trades!V$2:V$9999)*(Trades!U$2:U$9999=Blotter!B22)*(Trades!$T$2:T$9999=Blotter!C22))} -> 0 | J22: =VLOOKUP(D22,Multiplier!B:D,2,0) -> 10000 | K22: =L22-N22/(H22*J22) -> 2.327448 | L22: =IF(I22=0,IF(H22>0,X22,Y22),Z22) -> 2.3075 | M22: =I22*J22*L22 -> 0 | N22: {=-SUM((Trades!T$2:T$9999=Blotter!C22)*(Trades!U$2:U$9999=Blotter!B22)*(Trades!V$2:V$9999)*(Trades!W$2:W$9999))*J22+SUM((Trades!T$2:T$9999=Blotter!C22)*(Trades!U$2:U$9999=Blotter!B22)*(Trades!X$2:X$9999))+(L22*I22)*J22} -> -997.4 | O22: =VLOOKUP(D22,Multiplier!B:H,3,0) -> 0.132 | P22: 0.18 | Q22: 1 | R22: =(1-Q22)*P22*J22*H22 -> 0 | S22: =IF(OR(F22="Futures",F22="Stocks"),IF(I22=0,0,IF(I22>0,L22-O22,L22+O22)),0) -> 0 | T22: =IF(S22>0,IF(ISNUMBER(S22/L22-1),S22/L22-1,0),0) -> 0 | U22: =IF(OR(F22="Futures",F22="Stocks"),IF(I22=0,0,IF(I22>0,K22-P22,K22+P22)),0) -> 0 | V22: =IF(U22>0,IF(ISNUMBER(U22/L22-1),U22/L22-1,0),0) -> 0 | X22: {=IF(ISNUMBER(SUM((Trades!T$2:T$9999=Blotter!C22)*(Trades!U$2:U$9999=Blotter!B22)*(Trades!W$2:W$9999)*(Trades!V$2:V$9999)*(Trades!V$2:V$9999<0))/SUM((Trades!T$2:T$9999=Blotter!C22)*(Trades!U$2:U$9999=Blotter!B22)*(Trades!V$2:V$9999)*(Trades!V$2:V$9999<0))),SUM((Trades!T$2:T$9999=Blotter!C22)*(Trades!U$2:U$9999=Blotter!B22)*(Trades!W$2:W$9999)*(Trades!V$2:V$9999)*(Trades!V$2:V$9999<0))/SUM((Trades!T$2:T$9999=Blotter!C22)*(Trades!U$2:U$9999=Blotter!B22)*(Trades!V$2:V$9999)*(Trades!V$2:V$9999<0)),0)} -> 2.3075 | Y22: {=IF(ISNUMBER(SUM((Trades!T$2:T$9999=Blotter!C22)*(Trades!U$2:U$9999=Blotter!B22)*(Trades!W$2:W$9999)*(Trades!V$2:V$9999)*(Trades!V$2:V$9999>0))/SUM((Trades!T$2:T$9999=Blotter!C22)*(Trades!U$2:U$9999=Blotter!B22)*(Trades!V$2:V$9999)*(Trades!V$2:V$9999>0))),SUM((Trades!T$2:T$9999=Blotter!C22)*(Trades!U$2:U$9999=Blotter!B22)*(Trades!W$2:W$9999)*(Trades!V$2:V$9999)*(Trades!V$2:V$9999>0))/SUM((Trades!T$2:T$9999=Blotter!C22)*(Trades!U$2:U$9999=Blotter!B22)*(Trades!V$2:V$9999)*(Trades!V$2:V$9999>0)),0)} -> 2.317 | Z22: =IF(C$2="Last",IF(ISNUMBER(VLOOKUP(B22,Data_IB!B:O,14,0)),VLOOKUP(B22,Data_IB!B:O,14,0),0),IF(ISNUMBER(VLOOKUP(B22,Data_IB!B:O,13,0)),VLOOKUP(B22,Data_IB!B:O,13,0),0)) -> 0
B23: NGN3 | C23: 2 | D23: NG | E23: Commodities | F23: Futures | G23: =IF(F23="Futures",VLOOKUP(D23,Multiplier!B:I,8,0),0) -> 8 | H23: 5 | I23: {=SUM((Trades!V$2:V$9999)*(Trades!U$2:U$9999=Blotter!B23)*(Trades!$T$2:T$9999=Blotter!C23))} -> 0 | J23: =VLOOKUP(D23,Multiplier!B:D,2,0) -> 10000 | K23: =L23-N23/(H23*J23) -> 2.3523549 | L23: =IF(I23=0,IF(H23>0,X23,Y23),Z23) -> 2.4208889 | M23: =I23*J23*L23 -> 0 | N23: {=-SUM((Trades!T$2:T$9999=Blotter!C23)*(Trades!U$2:U$9999=Blotter!B23)*(Trades!V$2:V$9999)*(Trades!W$2:W$9999))*J23+SUM((Trades!T$2:T$9999=Blotter!C23)*(Trades!U$2:U$9999=Blotter!B23)*(Trades!X$2:X$9999))+(L23*I23)*J23} -> 3426.7 | O23: =VLOOKUP(D23,Multiplier!B:H,3,0) -> 0.132 | P23: 0.18 | Q23: 1 | R23: =(1-Q23)*P23*J23*H23 -> 0 | S23: =IF(OR(F23="Futures",F23="Stocks"),IF(I23=0,0,IF(I23>0,L23-O23,L23+O23)),0) -> 0 | T23: =IF(S23>0,IF(ISNUMBER(S23/L23-1),S23/L23-1,0),0) -> 0 | U23: =IF(OR(F23="Futures",F23="Stocks"),IF(I23=0,0,IF(I23>0,K23-P23,K23+P23)),0) -> 0 | V23: =IF(U23>0,IF(ISNUMBER(U23/L23-1),U23/L23-1,0),0) -> 0 | X23: {=IF(ISNUMBER(SUM((Trades!T$2:T$9999=Blotter!C23)*(Trades!U$2:U$9999=Blotter!B23)*(Trades!W$2:W$9999)*(Trades!V$2:V$9999)*(Trades!V$2:V$9999<0))/SUM((Trades!T$2:T$9999=Blotter!C23)*(Trades!U$2:U$9999=Blotter!B23)*(Trades!V$2:V$9999)*(Trades!V$2:V$9999<0))),SUM((Trades!T$2:T$9999=Blotter!C23)*(Trades!U$2:U$9999=Blotter!B23)*(Trades!W$2:W$9999)*(Trades!V$2:V$9999)*(Trades!V$2:V$9999<0))/SUM((Trades!T$2:T$9999=Blotter!C23)*(Trades!U$2:U$9999=Blotter!B23)*(Trades!V$2:V$9999)*(Trades!V$2:V$9999<0)),0)} -> 2.4208889 | Y23: {=IF(ISNUMBER(SUM((Trades!T$2:T$9999=Blotter!C23)*(Trades!U$2:U$9999=Blotter!B23)*(Trades!W$2:W$9999)*(Trades!V$2:V$9999)*(Trades!V$2:V$9999>0))/SUM((Trades!T$2:T$9999=Blotter!C23)*(Trades!U$2:U$9999=Blotter!B23)*(Trades!V$2:V$9999)*(Trades!V$2:V$9999>0))),SUM((Trades!T$2:T$9999=Blotter!C23)*(Trades!U$2:U$9999=Blotter!B23)*(Trades!W$2:W$9999)*(Trades!V$2:V$9999)*(Trades!V$2:V$9999>0))/SUM((Trades!T$2:T$9999=Blotter!C23)*(Trades!U$2:U$9999=Blotter!B23)*(Trades!V$2:V$9999)*(Trades!V$2:V$9999>0)),0)} -> 2.4128 | Z23: =IF(C$2="Last",IF(ISNUMBER(VLOOKUP(B23,Data_IB!B:O,14,0)),VLOOKUP(B23,Data_IB!B:O,14,0),0),IF(ISNUMBER(VLOOKUP(B23,Data_IB!B:O,13,0)),VLOOKUP(B23,Data_IB!B:O,13,0),0)) -> 0
B24: RBM3 | C24: 3 | D24: RB | E24: Commodities | F24: Futures | G24: =IF(F24="Futures",VLOOKUP(D24,Multiplier!B:I,8,0),0) -> 3 | H24: 2 | I24: {=SUM((Trades!V$2:V$9999)*(Trades!U$2:U$9999=Blotter!B24)*(Trades!$T$2:T$9999=Blotter!C24))} -> 0 | J24: =VLOOKUP(D24,Multiplier!B:D,2,0) -> 42000 | K24: =L24-N24/(H24*J24) -> 2.5630507 | L24: =IF(I24=0,IF(H24>0,X24,Y24),Z24) -> 2.542175 | M24: =I24*J24*L24 -> 0 | N24: {=-SUM((Trades!T$2:T$9999=Blotter!C24)*(Trades!U$2:U$9999=Blotter!B24)*(Trades!V$2:V$9999)*(Trades!W$2:W$9999))*J24+SUM((Trades!T$2:T$9999=Blotter!C24)*(Trades!U$2:U$9999=Blotter!B24)*(Trades!X$2:X$9999))+(L24*I24)*J24} -> -1753.56 | O24: =VLOOKUP(D24,Multiplier!B:H,3,0) -> 0.0725 | P24: 0.1 | R24: =(1-Q24)*P24*J24*H24 -> 8400 | S24: =IF(OR(F24="Futures",F24="Stocks"),IF(I24=0,0,IF(I24>0,L24-O24,L24+O24)),0) -> 0 | T24: =IF(S24>0,IF(ISNUMBER(S24/L24-1),S24/L24-1,0),0) -> 0 | U24: =IF(OR(F24="Futures",F24="Stocks"),IF(I24=0,0,IF(I24>0,K24-P24,K24+P24)),0) -> 0 | V24: =IF(U24>0,IF(ISNUMBER(U24/L24-1),U24/L24-1,0),0) -> 0 | X24: {=IF(ISNUMBER(SUM((Trades!T$2:T$9999=Blotter!C24)*(Trades!U$2:U$9999=Blotter!B24)*(Trades!W$2:W$9999)*(Trades!V$2:V$9999)*(Trades!V$2:V$9999<0))/SUM((Trades!T$2:T$9999=Blotter!C24)*(Trades!U$2:U$9999=Blotter!B24)*(Trades!V$2:V$9999)*(Trades!V$2:V$9999<0))),SUM((Trades!T$2:T$9999=Blotter!C24)*(Trades!U$2:U$9999=Blotter!B24)*(Trades!W$2:W$9999)*(Trades!V$2:V$9999)*(Trades!V$2:V$9999<0))/SUM((Trades!T$2:T$9999=Blotter!C24)*(Trades!U$2:U$9999=Blotter!B24)*(Trades!V$2:V$9999)*(Trades!V$2:V$9999<0)),0)} -> 2.542175 | Y24: {=IF(ISNUMBER(SUM((Trades!T$2:T$9999=Blotter!C24)*(Trades!U$2:U$9999=Blotter!B24)*(Trades!W$2:W$9999)*(Trades!V$2:V$9999)*(Trades!V$2:V$9999>0))/SUM((Trades!T$2:T$9999=Blotter!C24)*(Trades!U$2:U$9999=Blotter!B24)*(Trades!V$2:V$9999)*(Trades!V$2:V$9999>0))),SUM((Trades!T$2:T$9999=Blotter!C24)*(Trades!U$2:U$9999=Blotter!B24)*(Trades!W$2:W$9999)*(Trades!V$2:V$9999)*(Trades!V$2:V$9999>0))/SUM((Trades!T$2:T$9999=Blotter!C24)*(Trades!U$2:U$9999=Blotter!B24)*(Trades!V$2:V$9999)*(Trades!V$2:V$9999>0)),0)} -> 2.5525 | Z24: =IF(C$2="Last",IF(ISNUMBER(VLOOKUP(B24,Data_IB!B:O,14,0)),VLOOKUP(B24,Data_IB!B:O,14,0),0),IF(ISNUMBER(VLOOKUP(B24,Data_IB!B:O,13,0)),VLOOKUP(B24,Data_IB!B:O,13,0),0)) -> 0
B25: QNEM3 C13800 | C25: 5 | D25: NQ | E25: Equity | F25: Call | G25: =IF(F25="Futures",VLOOKUP(D25,Multiplier!B:I,8,0),0) -> 0 | H25: 1 | I25: {=SUM((Trades!V$2:V$9999)*(Trades!U$2:U$9999=Blotter!B25)*(Trades!$T$2:T$9999=Blotter!C25))} -> 0 | J25: =VLOOKUP(D25,Multiplier!B:D,2,0) -> 20 | K25: =L25-N25/(H25*J25) -> 205.142 | L25: =IF(I25=0,IF(H25>0,X25,Y25),Z25) -> 275 | M25: =I25*J25*L25 -> 0 | N25: {=-SUM((Trades!T$2:T$9999=Blotter!C25)*(Trades!U$2:U$9999=Blotter!B25)*(Trades!V$2:V$9999)*(Trades!W$2:W$9999))*J25+SUM((Trades!T$2:T$9999=Blotter!C25)*(Trades!U$2:U$9999=Blotter!B25)*(Trades!X$2:X$9999))+(L25*I25)*J25} -> 1397.16 | O25: =VLOOKUP(D25,Multiplier!B:H,3,0) -> 248 | P25: 205 | R25: =(1-Q25)*P25*J25*H25 -> 4100 | S25: =IF(OR(F25="Futures",F25="Stocks"),IF(I25=0,0,IF(I25>0,L25-O25,L25+O25)),0) -> 0 | T25: =IF(S25>0,IF(ISNUMBER(S25/L25-1),S25/L25-1,0),0) -> 0 | U25: =IF(OR(F25="Futures",F25="Stocks"),IF(I25=0,0,IF(I25>0,K25-P25,K25+P25)),0) -> 0 | V25: =IF(U25>0,IF(ISNUMBER(U25/L25-1),U25/L25-1,0),0) -> 0 | X25: {=IF(ISNUMBER(SUM((Trades!T$2:T$9999=Blotter!C25)*(Trades!U$2:U$9999=Blotter!B25)*(Trades!W$2:W$9999)*(Trades!V$2:V$9999)*(Trades!V$2:V$9999<0))/SUM((Trades!T$2:T$9999=Blotter!C25)*(Trades!U$2:U$9999=Blotter!B25)*(Trades!V$2:V$9999)*(Trades!V$2:V$9999<0))),SUM((Trades!T$2:T$9999=Blotter!C25)*(Trades!U$2:U$9999=Blotter!B25)*(Trades!W$2:W$9999)*(Trades!V$2:V$9999)*(Trades!V$2:V$9999<0))/SUM((Trades!T$2:T$9999=Blotter!C25)*(Trades!U$2:U$9999=Blotter!B25)*(Trades!V$2:V$9999)*(Trades!V$2:V$9999<0)),0)} -> 275 | Y25: {=IF(ISNUMBER(SUM((Trades!T$2:T$9999=Blotter!C25)*(Trades!U$2:U$9999=Blotter!B25)*(Trades!W$2:W$9999)*(Trades!V$2:V$9999)*(Trades!V$2:V$9999>0))/SUM((Trades!T$2:T$9999=Blotter!C25)*(Trades!U$2:U$9999=Blotter!B25)*(Trades!V$2:V$9999)*(Trades!V$2:V$9999>0))),SUM((Trades!T$2:T$9999=Blotter!C25)*(Trades!U$2:U$9999=Blotter!B25)*(Trades!W$2:W$9999)*(Trades!V$2:V$9999)*(Trades!V$2:V$9999>0))/SUM((Trades!T$2:T$9999=Blotter!C25)*(Trades!U$2:U$9999=Blotter!B25)*(Trades!V$2:V$9999)*(Trades!V$2:V$9999>0)),0)} -> 205 | Z25: =IF(C$2="Last",IF(ISNUMBER(VLOOKUP(B25,Data_IB!B:O,14,0)),VLOOKUP(B25,Data_IB!B:O,14,0),0),IF(ISNUMBER(VLOOKUP(B25,Data_IB!B:O,13,0)),VLOOKUP(B25,Data_IB!B:O,13,0),0)) -> 0
B26: NQM3 | C26: 5 | D26: NQ | E26: Equity | F26: Futures | G26: =IF(F26="Futures",VLOOKUP(D26,Multiplier!B:I,8,0),0) -> 2 | H26: 1 | I26: {=SUM((Trades!V$2:V$9999)*(Trades!U$2:U$9999=Blotter!B26)*(Trades!$T$2:T$9999=Blotter!C26))} -> 0 | J26: =VLOOKUP(D26,Multiplier!B:D,2,0) -> 20 | K26: =L26-N26/(H26*J26) -> 13290.22 | L26: =IF(I26=0,IF(H26>0,X26,Y26),Z26) -> 13800 | M26: =I26*J26*L26 -> 0 | N26: {=-SUM((Trades!T$2:T$9999=Blotter!C26)*(Trades!U$2:U$9999=Blotter!B26)*(Trades!V$2:V$9999)*(Trades!W$2:W$9999))*J26+SUM((Trades!T$2:T$9999=Blotter!C26)*(Trades!U$2:U$9999=Blotter!B26)*(Trades!X$2:X$9999))+(L26*I26)*J26} -> 10195.6 | O26: =VLOOKUP(D26,Multiplier!B:H,3,0) -> 248 | P26: 250 | R26: =(1-Q26)*P26*J26*H26 -> 5000 | S26: =IF(OR(F26="Futures",F26="Stocks"),IF(I26=0,0,IF(I26>0,L26-O26,L26+O26)),0) -> 0 | T26: =IF(S26>0,IF(ISNUMBER(S26/L26-1),S26/L26-1,0),0) -> 0 | U26: =IF(OR(F26="Futures",F26="Stocks"),IF(I26=0,0,IF(I26>0,K26-P26,K26+P26)),0) -> 0 | V26: =IF(U26>0,IF(ISNUMBER(U26/L26-1),U26/L26-1,0),0) -> 0 | X26: {=IF(ISNUMBER(SUM((Trades!T$2:T$9999=Blotter!C26)*(Trades!U$2:U$9999=Blotter!B26)*(Trades!W$2:W$9999)*(Trades!V$2:V$9999)*(Trades!V$2:V$9999<0))/SUM((Trades!T$2:T$9999=Blotter!C26)*(Trades!U$2:U$9999=Blotter!B26)*(Trades!V$2:V$9999)*(Trades!V$2:V$9999<0))),SUM((Trades!T$2:T$9999=Blotter!C26)*(Trades!U$2:U$9999=Blotter!B26)*(Trades!W$2:W$9999)*(Trades!V$2:V$9999)*(Trades!V$2:V$9999<0))/SUM((Trades!T$2:T$9999=Blotter!C26)*(Trades!U$2:U$9999=Blotter!B26)*(Trades!V$2:V$9999)*(Trades!V$2:V$9999<0)),0)} -> 13800 | Y26: {=IF(ISNUMBER(SUM((Trades!T$2:T$9999=Blotter!C26)*(Trades!U$2:U$9999=Blotter!B26)*(Trades!W$2:W$9999)*(Trades!V$2:V$9999)*(Trades!V$2:V$9999>0))/SUM((Trades!T$2:T$9999=Blotter!C26)*(Trades!U$2:U$9999=Blotter!B26)*(Trades!V$2:V$9999)*(Trades!V$2:V$9999>0))),SUM((Trades!T$2:T$9999=Blotter!C26)*(Trades!U$2:U$9999=Blotter!B26)*(Trades!W$2:W$9999)*(Trades!V$2:V$9999)*(Trades!V$2:V$9999>0))/SUM((Trades!T$2:T$9999=Blotter!C26)*(Trades!U$2:U$9999=Blotter!B26)*(Trades!V$2:V$9999)*(Trades!V$2:V$9999>0)),0)} -> 13290 | Z26: =IF(C$2="Last",IF(ISNUMBER(VLOOKUP(B26,Data_IB!B:O,14,0)),VLOOKUP(B26,Data_IB!B:O,14,0),0),IF(ISNUMBER(VLOOKUP(B26,Data_IB!B:O,13,0)),VLOOKUP(B26,Data_IB!B:O,13,0),0)) -> 0
B27: SIN3 | C27: 6 | D27: SI | E27: Commodities | F27: Futures | G27: =IF(F27="Futures",VLOOKUP(D27,Multiplier!B:I,8,0),0) -> 2 | H27: 3 | I27: {=SUM((Trades!V$2:V$9999)*(Trades!U$2:U$9999=Blotter!B27)*(Trades!$T$2:T$9999=Blotter!C27))} -> 0 | J27: =VLOOKUP(D27,Multiplier!B:D,2,0) -> 5000 | K27: =L27-N27/(H27*J27) -> 24.662613 | L27: =IF(I27=0,IF(H27>0,X27,Y27),Z27) -> 23.151429 | M27: =I27*J27*L27 -> 0 | N27: {=-SUM((Trades!T$2:T$9999=Blotter!C27)*(Trades!U$2:U$9999=Blotter!B27)*(Trades!V$2:V$9999)*(Trades!W$2:W$9999))*J27+SUM((Trades!T$2:T$9999=Blotter!C27)*(Trades!U$2:U$9999=Blotter!B27)*(Trades!X$2:X$9999))+(L27*I27)*J27} -> -22667.76 | O27: =VLOOKUP(D27,Multiplier!B:H,3,0) -> 0.825 | P27: 0.64 | Q27: 1 | R27: =(1-Q27)*P27*J27*H27 -> 0 | S27: =IF(OR(F27="Futures",F27="Stocks"),IF(I27=0,0,IF(I27>0,L27-O27,L27+O27)),0) -> 0 | T27: =IF(S27>0,IF(ISNUMBER(S27/L27-1),S27/L27-1,0),0) -> 0 | U27: =IF(OR(F27="Futures",F27="Stocks"),IF(I27=0,0,IF(I27>0,K27-P27,K27+P27)),0) -> 0 | V27: =IF(U27>0,IF(ISNUMBER(U27/L27-1),U27/L27-1,0),0) -> 0 | X27: {=IF(ISNUMBER(SUM((Trades!T$2:T$9999=Blotter!C27)*(Trades!U$2:U$9999=Blotter!B27)*(Trades!W$2:W$9999)*(Trades!V$2:V$9999)*(Trades!V$2:V$9999<0))/SUM((Trades!T$2:T$9999=Blotter!C27)*(Trades!U$2:U$9999=Blotter!B27)*(Trades!V$2:V$9999)*(Trades!V$2:V$9999<0))),SUM((Trades!T$2:T$9999=Blotter!C27)*(Trades!U$2:U$9999=Blotter!B27)*(Trades!W$2:W$9999)*(Trades!V$2:V$9999)*(Trades!V$2:V$9999<0))/SUM((Trades!T$2:T$9999=Blotter!C27)*(Trades!U$2:U$9999=Blotter!B27)*(Trades!V$2:V$9999)*(Trades!V$2:V$9999<0)),0)} -> 23.151429 | Y27: {=IF(ISNUMBER(SUM((Trades!T$2:T$9999=Blotter!C27)*(Trades!U$2:U$9999=Blotter!B27)*(Trades!W$2:W$9999)*(Trades!V$2:V$9999)*(Trades!V$2:V$9999>0))/SUM((Trades!T$2:T$9999=Blotter!C27)*(Trades!U$2:U$9999=Blotter!B27)*(Trades!V$2:V$9999)*(Trades!V$2:V$9999>0))),SUM((Trades!T$2:T$9999=Blotter!C27)*(Trades!U$2:U$9999=Blotter!B27)*(Trades!W$2:W$9999)*(Trades!V$2:V$9999)*(Trades!V$2:V$9999>0))/SUM((Trades!T$2:T$9999=Blotter!C27)*(Trades!U$2:U$9999=Blotter!B27)*(Trades!V$2:V$9999)*(Trades!V$2:V$9999>0)),0)} -> 23.474286 | Z27: =IF(C$2="Last",IF(ISNUMBER(VLOOKUP(B27,Data_IB!B:O,14,0)),VLOOKUP(B27,Data_IB!B:O,14,0),0),IF(ISNUMBER(VLOOKUP(B27,Data_IB!B:O,13,0)),VLOOKUP(B27,Data_IB!B:O,13,0),0)) -> 0
B28: SIU3 | C28: 6 | D28: SI | E28: Commodities | F28: Futures | G28: =IF(F28="Futures",VLOOKUP(D28,Multiplier!B:I,8,0),0) -> 2 | H28: 3 | I28: {=SUM((Trades!V$2:V$9999)*(Trades!U$2:U$9999=Blotter!B28)*(Trades!$T$2:T$9999=Blotter!C28))} -> 0 | J28: =VLOOKUP(D28,Multiplier!B:D,2,0) -> 5000 | K28: =L28-N28/(H28*J28) -> 25.006949 | L28: =IF(I28=0,IF(H28>0,X28,Y28),Z28) -> 23.765128 | M28: =I28*J28*L28 -> 0 | N28: {=-SUM((Trades!T$2:T$9999=Blotter!C28)*(Trades!U$2:U$9999=Blotter!B28)*(Trades!V$2:V$9999)*(Trades!W$2:W$9999))*J28+SUM((Trades!T$2:T$9999=Blotter!C28)*(Trades!U$2:U$9999=Blotter!B28)*(Trades!X$2:X$9999))+(L28*I28)*J28} -> -18627.32 | O28: =VLOOKUP(D28,Multiplier!B:H,3,0) -> 0.825 | P28: 0.64 | Q28: 1 | R28: =(1-Q28)*P28*J28*H28 -> 0 | S28: =IF(OR(F28="Futures",F28="Stocks"),IF(I28=0,0,IF(I28>0,L28-O28,L28+O28)),0) -> 0 | T28: =IF(S28>0,IF(ISNUMBER(S28/L28-1),S28/L28-1,0),0) -> 0 | U28: =IF(OR(F28="Futures",F28="Stocks"),IF(I28=0,0,IF(I28>0,K28-P28,K28+P28)),0) -> 0 | V28: =IF(U28>0,IF(ISNUMBER(U28/L28-1),U28/L28-1,0),0) -> 0 | X28: {=IF(ISNUMBER(SUM((Trades!T$2:T$9999=Blotter!C28)*(Trades!U$2:U$9999=Blotter!B28)*(Trades!W$2:W$9999)*(Trades!V$2:V$9999)*(Trades!V$2:V$9999<0))/SUM((Trades!T$2:T$9999=Blotter!C28)*(Trades!U$2:U$9999=Blotter!B28)*(Trades!V$2:V$9999)*(Trades!V$2:V$9999<0))),SUM((Trades!T$2:T$9999=Blotter!C28)*(Trades!U$2:U$9999=Blotter!B28)*(Trades!W$2:W$9999)*(Trades!V$2:V$9999)*(Trades!V$2:V$9999<0))/SUM((Trades!T$2:T$9999=Blotter!C28)*(Trades!U$2:U$9999=Blotter!B28)*(Trades!V$2:V$9999)*(Trades!V$2:V$9999<0)),0)} -> 23.765128 | Y28: {=IF(ISNUMBER(SUM((Trades!T$2:T$9999=Blotter!C28)*(Trades!U$2:U$9999=Blotter!B28)*(Trades!W$2:W$9999)*(Trades!V$2:V$9999)*(Trades!V$2:V$9999>0))/SUM((Trades!T$2:T$9999=Blotter!C28)*(Trades!U$2:U$9999=Blotter!B28)*(Trades!V$2:V$9999)*(Trades!V$2:V$9999>0))),SUM((Trades!T$2:T$9999=Blotter!C28)*(Trades!U$2:U$9999=Blotter!B28)*(Trades!W$2:W$9999)*(Trades!V$2:V$9999)*(Trades!V$2:V$9999>0))/SUM((Trades!T$2:T$9999=Blotter!C28)*(Trades!U$2:U$9999=Blotter!B28)*(Trades!V$2:V$9999)*(Trades!V$2:V$9999>0)),0)} -> 23.770958 | Z28: =IF(C$2="Last",IF(ISNUMBER(VLOOKUP(B28,Data_IB!B:O,14,0)),VLOOKUP(B28,Data_IB!B:O,14,0),0),IF(ISNUMBER(VLOOKUP(B28,Data_IB!B:O,13,0)),VLOOKUP(B28,Data_IB!B:O,13,0),0)) -> 0
B29: SIZ3 | C29: 6 | D29: SI | E29: Commodities | F29: Futures | G29: =IF(F29="Futures",VLOOKUP(D29,Multiplier!B:I,8,0),0) -> 2 | H29: 3 | I29: {=SUM((Trades!V$2:V$9999)*(Trades!U$2:U$9999=Blotter!B29)*(Trades!$T$2:T$9999=Blotter!C29))} -> 0 | J29: =VLOOKUP(D29,Multiplier!B:D,2,0) -> 5000 | K29: =L29-N29/(H29*J29) -> 28.300641 | L29: =IF(I29=0,IF(H29>0,X29,Y29),Z29) -> 23.567577 | M29: =I29*J29*L29 -> 0 | N29: {=-SUM((Trades!T$2:T$9999=Blotter!C29)*(Trades!U$2:U$9999=Blotter!B29)*(Trades!V$2:V$9999)*(Trades!W$2:W$9999))*J29+SUM((Trades!T$2:T$9999=Blotter!C29)*(Trades!U$2:U$9999=Blotter!B29)*(Trades!X$2:X$9999))+(L29*I29)*J29} -> -70995.96 | O29: =VLOOKUP(D29,Multiplier!B:H,3,0) -> 0.825 | P29: 0.64 | Q29: 1 | R29: =(1-Q29)*P29*J29*H29 -> 0 | S29: =IF(OR(F29="Futures",F29="Stocks"),IF(I29=0,0,IF(I29>0,L29-O29,L29+O29)),0) -> 0 | T29: =IF(S29>0,IF(ISNUMBER(S29/L29-1),S29/L29-1,0),0) -> 0 | U29: =IF(OR(F29="Futures",F29="Stocks"),IF(I29=0,0,IF(I29>0,K29-P29,K29+P29)),0) -> 0 | V29: =IF(U29>0,IF(ISNUMBER(U29/L29-1),U29/L29-1,0),0) -> 0 | X29: {=IF(ISNUMBER(SUM((Trades!T$2:T$9999=Blotter!C29)*(Trades!U$2:U$9999=Blotter!B29)*(Trades!W$2:W$9999)*(Trades!V$2:V$9999)*(Trades!V$2:V$9999<0))/SUM((Trades!T$2:T$9999=Blotter!C29)*(Trades!U$2:U$9999=Blotter!B29)*(Trades!V$2:V$9999)*(Trades!V$2:V$9999<0))),SUM((Trades!T$2:T$9999=Blotter!C29)*(Trades!U$2:U$9999=Blotter!B29)*(Trades!W$2:W$9999)*(Trades!V$2:V$9999)*(Trades!V$2:V$9999<0))/SUM((Trades!T$2:T$9999=Blotter!C29)*(Trades!U$2:U$9999=Blotter!B29)*(Trades!V$2:V$9999)*(Trades!V$2:V$9999<0)),0)} -> 23.567577 | Y29: {=IF(ISNUMBER(SUM((Trades!T$2:T$9999=Blotter!C29)*(Trades!U$2:U$9999=Blotter!B29)*(Trades!W$2:W$9999)*(Trades!V$2:V$9999)*(Trades!V$2:V$9999>0))/SUM((Trades!T$2:T$9999=Blotter!C29)*(Trades!U$2:U$9999=Blotter!B29)*(Trades!V$2:V$9999)*(Trades!V$2:V$9999>0))),SUM((Trades!T$2:T$9999=Blotter!C29)*(Trades!U$2:U$9999=Blotter!B29)*(Trades!W$2:W$9999)*(Trades!V$2:V$9999)*(Trades!V$2:V$9999>0))/SUM((Trades!T$2:T$9999=Blotter!C29)*(Trades!U$2:U$9999=Blotter!B29)*(Trades!V$2:V$9999)*(Trades!V$2:V$9999>0)),0)} -> 23.589548 | Z29: =IF(C$2="Last",IF(ISNUMBER(VLOOKUP(B29,Data_IB!B:O,14,0)),VLOOKUP(B29,Data_IB!B:O,14,0),0),IF(ISNUMBER(VLOOKUP(B29,Data_IB!B:O,13,0)),VLOOKUP(B29,Data_IB!B:O,13,0),0)) -> 0
B30: SOZ3 P2000 | C30: 6 | D30: SI | E30: Commodities | F30: Put | G30: =IF(F30="Futures",VLOOKUP(D30,Multiplier!B:I,8,0),0) -> 0 | H30: -15 | I30: {=SUM((Trades!V$2:V$9999)*(Trades!U$2:U$9999=Blotter!B30)*(Trades!$T$2:T$9999=Blotter!C30))} -> 0 | J30: =VLOOKUP(D30,Multiplier!B:D,2,0) -> 5000 | K30: =L30-N30/(H30*J30) -> 0.359052 | L30: =IF(I30=0,IF(H30>0,X30,Y30),Z30) -> 0.13 | M30: =I30*J30*L30 -> 0 | N30: {=-SUM((Trades!T$2:T$9999=Blotter!C30)*(Trades!U$2:U$9999=Blotter!B30)*(Trades!V$2:V$9999)*(Trades!W$2:W$9999))*J30+SUM((Trades!T$2:T$9999=Blotter!C30)*(Trades!U$2:U$9999=Blotter!B30)*(Trades!X$2:X$9999))+(L30*I30)*J30} -> 17178.9 | O30: =VLOOKUP(D30,Multiplier!B:H,3,0) -> 0.825 | P30: 0.36 | Q30: 1 | R30: =(1-Q30)*P30*J30*H30 -> 0 | S30: =IF(OR(F30="Futures",F30="Stocks"),IF(I30=0,0,IF(I30>0,L30-O30,L30+O30)),0) -> 0 | T30: =IF(S30>0,IF(ISNUMBER(S30/L30-1),S30/L30-1,0),0) -> 0 | U30: =IF(OR(F30="Futures",F30="Stocks"),IF(I30=0,0,IF(I30>0,K30-P30,K30+P30)),0) -> 0 | V30: =IF(U30>0,IF(ISNUMBER(U30/L30-1),U30/L30-1,0),0) -> 0 | X30: {=IF(ISNUMBER(SUM((Trades!T$2:T$9999=Blotter!C30)*(Trades!U$2:U$9999=Blotter!B30)*(Trades!W$2:W$9999)*(Trades!V$2:V$9999)*(Trades!V$2:V$9999<0))/SUM((Trades!T$2:T$9999=Blotter!C30)*(Trades!U$2:U$9999=Blotter!B30)*(Trades!V$2:V$9999)*(Trades!V$2:V$9999<0))),SUM((Trades!T$2:T$9999=Blotter!C30)*(Trades!U$2:U$9999=Blotter!B30)*(Trades!W$2:W$9999)*(Trades!V$2:V$9999)*(Trades!V$2:V$9999<0))/SUM((Trades!T$2:T$9999=Blotter!C30)*(Trades!U$2:U$9999=Blotter!B30)*(Trades!V$2:V$9999)*(Trades!V$2:V$9999<0)),0)} -> 0.36 | Y30: {=IF(ISNUMBER(SUM((Trades!T$2:T$9999=Blotter!C30)*(Trades!U$2:U$9999=Blotter!B30)*(Trades!W$2:W$9999)*(Trades!V$2:V$9999)*(Trades!V$2:V$9999>0))/SUM((Trades!T$2:T$9999=Blotter!C30)*(Trades!U$2:U$9999=Blotter!B30)*(Trades!V$2:V$9999)*(Trades!V$2:V$9999>0))),SUM((Trades!T$2:T$9999=Blotter!C30)*(Trades!U$2:U$9999=Blotter!B30)*(Trades!W$2:W$9999)*(Trades!V$2:V$9999)*(Trades!V$2:V$9999>0))/SUM((Trades!T$2:T$9999=Blotter!C30)*(Trades!U$2:U$9999=Blotter!B30)*(Trades!V$2:V$9999)*(Trades!V$2:V$9999>0)),0)} -> 0.13 | Z30: =IF(C$2="Last",IF(ISNUMBER(VLOOKUP(B30,Data_IB!B:O,14,0)),VLOOKUP(B30,Data_IB!B:O,14,0),0),IF(ISNUMBER(VLOOKUP(B30,Data_IB!B:O,13,0)),VLOOKUP(B30,Data_IB!B:O,13,0),0)) -> 0
B31: SOZ3 C2220 | C31: 6 | D31: SI | E31: Commodities | F31: Call | G31: =IF(F31="Futures",VLOOKUP(D31,Multiplier!B:I,8,0),0) -> 0 | H31: 15 | I31: {=SUM((Trades!V$2:V$9999)*(Trades!U$2:U$9999=Blotter!B31)*(Trades!$T$2:T$9999=Blotter!C31))} -> 0 | J31: =VLOOKUP(D31,Multiplier!B:D,2,0) -> 5000 | K31: =L31-N31/(H31*J31) -> 0.34959733 | L31: =IF(I31=0,IF(H31>0,X31,Y31),Z31) -> 1.685 | M31: =I31*J31*L31 -> 0 | N31: {=-SUM((Trades!T$2:T$9999=Blotter!C31)*(Trades!U$2:U$9999=Blotter!B31)*(Trades!V$2:V$9999)*(Trades!W$2:W$9999))*J31+SUM((Trades!T$2:T$9999=Blotter!C31)*(Trades!U$2:U$9999=Blotter!B31)*(Trades!X$2:X$9999))+(L31*I31)*J31} -> 100155.2 | O31: =VLOOKUP(D31,Multiplier!B:H,3,0) -> 0.825 | P31: =0.52-0.23 -> 0.29 | Q31: 1 | R31: =(1-Q31)*P31*J31*H31 -> 0 | S31: =IF(OR(F31="Futures",F31="Stocks"),IF(I31=0,0,IF(I31>0,L31-O31,L31+O31)),0) -> 0 | T31: =IF(S31>0,IF(ISNUMBER(S31/L31-1),S31/L31-1,0),0) -> 0 | U31: =IF(OR(F31="Futures",F31="Stocks"),IF(I31=0,0,IF(I31>0,K31-P31,K31+P31)),0) -> 0 | V31: =IF(U31>0,IF(ISNUMBER(U31/L31-1),U31/L31-1,0),0) -> 0 | X31: {=IF(ISNUMBER(SUM((Trades!T$2:T$9999=Blotter!C31)*(Trades!U$2:U$9999=Blotter!B31)*(Trades!W$2:W$9999)*(Trades!V$2:V$9999)*(Trades!V$2:V$9999<0))/SUM((Trades!T$2:T$9999=Blotter!C31)*(Trades!U$2:U$9999=Blotter!B31)*(Trades!V$2:V$9999)*(Trades!V$2:V$9999<0))),SUM((Trades!T$2:T$9999=Blotter!C31)*(Trades!U$2:U$9999=Blotter!B31)*(Trades!W$2:W$9999)*(Trades!V$2:V$9999)*(Trades!V$2:V$9999<0))/SUM((Trades!T$2:T$9999=Blotter!C31)*(Trades!U$2:U$9999=Blotter!B31)*(Trades!V$2:V$9999)*(Trades!V$2:V$9999<0)),0)} -> 1.685 | Y31: {=IF(ISNUMBER(SUM((Trades!T$2:T$9999=Blotter!C31)*(Trades!U$2:U$9999=Blotter!B31)*(Trades!W$2:W$9999)*(Trades!V$2:V$9999)*(Trades!V$2:V$9999>0))/SUM((Trades!T$2:T$9999=Blotter!C31)*(Trades!U$2:U$9999=Blotter!B31)*(Trades!V$2:V$9999)*(Trades!V$2:V$9999>0))),SUM((Trades!T$2:T$9999=Blotter!C31)*(Trades!U$2:U$9999=Blotter!B31)*(Trades!W$2:W$9999)*(Trades!V$2:V$9999)*(Trades!V$2:V$9999>0))/SUM((Trades!T$2:T$9999=Blotter!C31)*(Trades!U$2:U$9999=Blotter!B31)*(Trades!V$2:V$9999)*(Trades!V$2:V$9999>0)),0)} -> 0.6825 | Z31: =IF(C$2="Last",IF(ISNUMBER(VLOOKUP(B31,Data_IB!B:O,14,0)),VLOOKUP(B31,Data_IB!B:O,14,0),0),IF(ISNUMBER(VLOOKUP(B31,Data_IB!B:O,13,0)),VLOOKUP(B31,Data_IB!B:O,13,0),0)) -> 0
B32: SOZ3 C2470 | C32: 6 | D32: SI | E32: Commodities | F32: Call | G32: =IF(F32="Futures",VLOOKUP(D32,Multiplier!B:I,8,0),0) -> 0 | H32: -15 | I32: {=SUM((Trades!V$2:V$9999)*(Trades!U$2:U$9999=Blotter!B32)*(Trades!$T$2:T$9999=Blotter!C32))} -> 0 | J32: =VLOOKUP(D32,Multiplier!B:D,2,0) -> 5000 | K32: =L32-N32/(H32*J32) -> 0.181052 | L32: =IF(I32=0,IF(H32>0,X32,Y32),Z32) -> 0.246 | M32: =I32*J32*L32 -> 0 | N32: {=-SUM((Trades!T$2:T$9999=Blotter!C32)*(Trades!U$2:U$9999=Blotter!B32)*(Trades!V$2:V$9999)*(Trades!W$2:W$9999))*J32+SUM((Trades!T$2:T$9999=Blotter!C32)*(Trades!U$2:U$9999=Blotter!B32)*(Trades!X$2:X$9999))+(L32*I32)*J32} -> -4871.1 | O32: =VLOOKUP(D32,Multiplier!B:H,3,0) -> 0.825 | P32: 0.182 | Q32: 1 | R32: =(1-Q32)*P32*J32*H32 -> 0 | S32: =IF(OR(F32="Futures",F32="Stocks"),IF(I32=0,0,IF(I32>0,L32-O32,L32+O32)),0) -> 0 | T32: =IF(S32>0,IF(ISNUMBER(S32/L32-1),S32/L32-1,0),0) -> 0 | U32: =IF(OR(F32="Futures",F32="Stocks"),IF(I32=0,0,IF(I32>0,K32-P32,K32+P32)),0) -> 0 | V32: =IF(U32>0,IF(ISNUMBER(U32/L32-1),U32/L32-1,0),0) -> 0 | X32: {=IF(ISNUMBER(SUM((Trades!T$2:T$9999=Blotter!C32)*(Trades!U$2:U$9999=Blotter!B32)*(Trades!W$2:W$9999)*(Trades!V$2:V$9999)*(Trades!V$2:V$9999<0))/SUM((Trades!T$2:T$9999=Blotter!C32)*(Trades!U$2:U$9999=Blotter!B32)*(Trades!V$2:V$9999)*(Trades!V$2:V$9999<0))),SUM((Trades!T$2:T$9999=Blotter!C32)*(Trades!U$2:U$9999=Blotter!B32)*(Trades!W$2:W$9999)*(Trades!V$2:V$9999)*(Trades!V$2:V$9999<0))/SUM((Trades!T$2:T$9999=Blotter!C32)*(Trades!U$2:U$9999=Blotter!B32)*(Trades!V$2:V$9999)*(Trades!V$2:V$9999<0)),0)} -> 0.182 | Y32: {=IF(ISNUMBER(SUM((Trades!T$2:T$9999=Blotter!C32)*(Trades!U$2:U$9999=Blotter!B32)*(Trades!W$2:W$9999)*(Trades!V$2:V$9999)*(Trades!V$2:V$9999>0))/SUM((Trades!T$2:T$9999=Blotter!C32)*(Trades!U$2:U$9999=Blotter!B32)*(Trades!V$2:V$9999)*(Trades!V$2:V$9999>0))),SUM((Trades!T$2:T$9999=Blotter!C32)*(Trades!U$2:U$9999=Blotter!B32)*(Trades!W$2:W$9999)*(Trades!V$2:V$9999)*(Trades!V$2:V$9999>0))/SUM((Trades!T$2:T$9999=Blotter!C32)*(Trades!U$2:U$9999=Blotter!B32)*(Trades!V$2:V$9999)*(Trades!V$2:V$9999>0)),0)} -> 0.246 | Z32: =IF(C$2="Last",IF(ISNUMBER(VLOOKUP(B32,Data_IB!B:O,14,0)),VLOOKUP(B32,Data_IB!B:O,14,0),0),IF(ISNUMBER(VLOOKUP(B32,Data_IB!B:O,13,0)),VLOOKUP(B32,Data_IB!B:O,13,0),0)) -> 0
B33: SOJ4 C2650 | C33: 6 | D33: SI | E33: Commodities | F33: Call | G33: =IF(F33="Futures",VLOOKUP(D33,Multiplier!B:I,8,0),0) -> 0 | H33: 7 | I33: {=SUM((Trades!V$2:V$9999)*(Trades!U$2:U$9999=Blotter!B33)*(Trades!$T$2:T$9999=Blotter!C33))} -> 0 | J33: =VLOOKUP(D33,Multiplier!B:D,2,0) -> 5000 | K33: =L33-N33/(H33*J33) -> 0.950968 | L33: =IF(I33=0,IF(H33>0,X33,Y33),Z33) -> 0.1 | M33: =I33*J33*L33 -> 0 | N33: {=-SUM((Trades!T$2:T$9999=Blotter!C33)*(Trades!U$2:U$9999=Blotter!B33)*(Trades!V$2:V$9999)*(Trades!W$2:W$9999))*J33+SUM((Trades!T$2:T$9999=Blotter!C33)*(Trades!U$2:U$9999=Blotter!B33)*(Trades!X$2:X$9999))+(L33*I33)*J33} -> -29783.88 | O33: =VLOOKUP(D33,Multiplier!B:H,3,0) -> 0.825 | P33: 0.95 | R33: =(1-Q33)*P33*J33*H33 -> 33250 | S33: =IF(OR(F33="Futures",F33="Stocks"),IF(I33=0,0,IF(I33>0,L33-O33,L33+O33)),0) -> 0 | T33: =IF(S33>0,IF(ISNUMBER(S33/L33-1),S33/L33-1,0),0) -> 0 | U33: =IF(OR(F33="Futures",F33="Stocks"),IF(I33=0,0,IF(I33>0,K33-P33,K33+P33)),0) -> 0 | V33: =IF(U33>0,IF(ISNUMBER(U33/L33-1),U33/L33-1,0),0) -> 0 | X33: {=IF(ISNUMBER(SUM((Trades!T$2:T$9999=Blotter!C33)*(Trades!U$2:U$9999=Blotter!B33)*(Trades!W$2:W$9999)*(Trades!V$2:V$9999)*(Trades!V$2:V$9999<0))/SUM((Trades!T$2:T$9999=Blotter!C33)*(Trades!U$2:U$9999=Blotter!B33)*(Trades!V$2:V$9999)*(Trades!V$2:V$9999<0))),SUM((Trades!T$2:T$9999=Blotter!C33)*(Trades!U$2:U$9999=Blotter!B33)*(Trades!W$2:W$9999)*(Trades!V$2:V$9999)*(Trades!V$2:V$9999<0))/SUM((Trades!T$2:T$9999=Blotter!C33)*(Trades!U$2:U$9999=Blotter!B33)*(Trades!V$2:V$9999)*(Trades!V$2:V$9999<0)),0)} -> 0.1 | Y33: {=IF(ISNUMBER(SUM((Trades!T$2:T$9999=Blotter!C33)*(Trades!U$2:U$9999=Blotter!B33)*(Trades!W$2:W$9999)*(Trades!V$2:V$9999)*(Trades!V$2:V$9999>0))/SUM((Trades!T$2:T$9999=Blotter!C33)*(Trades!U$2:U$9999=Blotter!B33)*(Trades!V$2:V$9999)*(Trades!V$2:V$9999>0))),SUM((Trades!T$2:T$9999=Blotter!C33)*(Trades!U$2:U$9999=Blotter!B33)*(Trades!W$2:W$9999)*(Trades!V$2:V$9999)*(Trades!V$2:V$9999>0))/SUM((Trades!T$2:T$9999=Blotter!C33)*(Trades!U$2:U$9999=Blotter!B33)*(Trades!V$2:V$9999)*(Trades!V$2:V$9999>0)),0)} -> 0.95 | Z33: =IF(C$2="Last",IF(ISNUMBER(VLOOKUP(B33,Data_IB!B:O,14,0)),VLOOKUP(B33,Data_IB!B:O,14,0),0),IF(ISNUMBER(VLOOKUP(B33,Data_IB!B:O,13,0)),VLOOKUP(B33,Data_IB!B:O,13,0),0)) -> 0
B34: SOJ4 C3000 | C34: 6 | D34: SI | E34: Commodities | F34: Call | G34: =IF(F34="Futures",VLOOKUP(D34,Multiplier!B:I,8,0),0) -> 0 | H34: -7 | I34: {=SUM((Trades!V$2:V$9999)*(Trades!U$2:U$9999=Blotter!B34)*(Trades!$T$2:T$9999=Blotter!C34))} -> 0 | J34: =VLOOKUP(D34,Multiplier!B:D,2,0) -> 5000 | K34: =L34-N34/(H34*J34) -> 0.379526 | L34: =IF(I34=0,IF(H34>0,X34,Y34),Z34) -> 0 | M34: =I34*J34*L34 -> 0 | N34: {=-SUM((Trades!T$2:T$9999=Blotter!C34)*(Trades!U$2:U$9999=Blotter!B34)*(Trades!V$2:V$9999)*(Trades!W$2:W$9999))*J34+SUM((Trades!T$2:T$9999=Blotter!C34)*(Trades!U$2:U$9999=Blotter!B34)*(Trades!X$2:X$9999))+(L34*I34)*J34} -> 13283.41 | O34: =VLOOKUP(D34,Multiplier!B:H,3,0) -> 0.825 | P34: 0.38 | R34: =(1-Q34)*P34*J34*H34 -> -13300 | S34: =IF(OR(F34="Futures",F34="Stocks"),IF(I34=0,0,IF(I34>0,L34-O34,L34+O34)),0) -> 0 | T34: =IF(S34>0,IF(ISNUMBER(S34/L34-1),S34/L34-1,0),0) -> 0 | U34: =IF(OR(F34="Futures",F34="Stocks"),IF(I34=0,0,IF(I34>0,K34-P34,K34+P34)),0) -> 0 | V34: =IF(U34>0,IF(ISNUMBER(U34/L34-1),U34/L34-1,0),0) -> 0 | X34: {=IF(ISNUMBER(SUM((Trades!T$2:T$9999=Blotter!C34)*(Trades!U$2:U$9999=Blotter!B34)*(Trades!W$2:W$9999)*(Trades!V$2:V$9999)*(Trades!V$2:V$9999<0))/SUM((Trades!T$2:T$9999=Blotter!C34)*(Trades!U$2:U$9999=Blotter!B34)*(Trades!V$2:V$9999)*(Trades!V$2:V$9999<0))),SUM((Trades!T$2:T$9999=Blotter!C34)*(Trades!U$2:U$9999=Blotter!B34)*(Trades!W$2:W$9999)*(Trades!V$2:V$9999)*(Trades!V$2:V$9999<0))/SUM((Trades!T$2:T$9999=Blotter!C34)*(Trades!U$2:U$9999=Blotter!B34)*(Trades!V$2:V$9999)*(Trades!V$2:V$9999<0)),0)} -> 0.38 | Y34: {=IF(ISNUMBER(SUM((Trades!T$2:T$9999=Blotter!C34)*(Trades!U$2:U$9999=Blotter!B34)*(Trades!W$2:W$9999)*(Trades!V$2:V$9999)*(Trades!V$2:V$9999>0))/SUM((Trades!T$2:T$9999=Blotter!C34)*(Trades!U$2:U$9999=Blotter!B34)*(Trades!V$2:V$9999)*(Trades!V$2:V$9999>0))),SUM((Trades!T$2:T$9999=Blotter!C34)*(Trades!U$2:U$9999=Blotter!B34)*(Trades!W$2:W$9999)*(Trades!V$2:V$9999)*(Trades!V$2:V$9999>0))/SUM((Trades!T$2:T$9999=Blotter!C34)*(Trades!U$2:U$9999=Blotter!B34)*(Trades!V$2:V$9999)*(Trades!V$2:V$9999>0)),0)} -> 0 | Z34: =IF(C$2="Last",IF(ISNUMBER(VLOOKUP(B34,Data_IB!B:O,14,0)),VLOOKUP(B34,Data_IB!B:O,14,0),0),IF(ISNUMBER(VLOOKUP(B34,Data_IB!B:O,13,0)),VLOOKUP(B34,Data_IB!B:O,13,0),0)) -> 0
B35: HGN3 | C35: 8 | D35: HG | E35: Commodities | F35: Futures | G35: =IF(F35="Futures",VLOOKUP(D35,Multiplier!B:I,8,0),0) -> 6 | H35: 4 | I35: {=SUM((Trades!V$2:V$9999)*(Trades!U$2:U$9999=Blotter!B35)*(Trades!$T$2:T$9999=Blotter!C35))} -> 0 | J35: =VLOOKUP(D35,Multiplier!B:D,2,0) -> 25000 | K35: =L35-N35/(H35*J35) -> 3.7413737 | L35: =IF(I35=0,IF(H35>0,X35,Y35),Z35) -> 3.7753333 | M35: =I35*J35*L35 -> 0 | N35: {=-SUM((Trades!T$2:T$9999=Blotter!C35)*(Trades!U$2:U$9999=Blotter!B35)*(Trades!V$2:V$9999)*(Trades!W$2:W$9999))*J35+SUM((Trades!T$2:T$9999=Blotter!C35)*(Trades!U$2:U$9999=Blotter!B35)*(Trades!X$2:X$9999))+(L35*I35)*J35} -> 3395.96 | O35: =VLOOKUP(D35,Multiplier!B:H,3,0) -> 0.0708 | P35: 0.09 | Q35: 1 | R35: =(1-Q35)*P35*J35*H35 -> 0 | S35: =IF(OR(F35="Futures",F35="Stocks"),IF(I35=0,0,IF(I35>0,L35-O35,L35+O35)),0) -> 0 | T35: =IF(S35>0,IF(ISNUMBER(S35/L35-1),S35/L35-1,0),0) -> 0 | U35: =IF(OR(F35="Futures",F35="Stocks"),IF(I35=0,0,IF(I35>0,K35-P35,K35+P35)),0) -> 0 | V35: =IF(U35>0,IF(ISNUMBER(U35/L35-1),U35/L35-1,0),0) -> 0 | X35: {=IF(ISNUMBER(SUM((Trades!T$2:T$9999=Blotter!C35)*(Trades!U$2:U$9999=Blotter!B35)*(Trades!W$2:W$9999)*(Trades!V$2:V$9999)*(Trades!V$2:V$9999<0))/SUM((Trades!T$2:T$9999=Blotter!C35)*(Trades!U$2:U$9999=Blotter!B35)*(Trades!V$2:V$9999)*(Trades!V$2:V$9999<0))),SUM((Trades!T$2:T$9999=Blotter!C35)*(Trades!U$2:U$9999=Blotter!B35)*(Trades!W$2:W$9999)*(Trades!V$2:V$9999)*(Trades!V$2:V$9999<0))/SUM((Trades!T$2:T$9999=Blotter!C35)*(Trades!U$2:U$9999=Blotter!B35)*(Trades!V$2:V$9999)*(Trades!V$2:V$9999<0)),0)} -> 3.7753333 | Y35: {=IF(ISNUMBER(SUM((Trades!T$2:T$9999=Blotter!C35)*(Trades!U$2:U$9999=Blotter!B35)*(Trades!W$2:W$9999)*(Trades!V$2:V$9999)*(Trades!V$2:V$9999>0))/SUM((Trades!T$2:T$9999=Blotter!C35)*(Trades!U$2:U$9999=Blotter!B35)*(Trades!V$2:V$9999)*(Trades!V$2:V$9999>0))),SUM((Trades!T$2:T$9999=Blotter!C35)*(Trades!U$2:U$9999=Blotter!B35)*(Trades!W$2:W$9999)*(Trades!V$2:V$9999)*(Trades!V$2:V$9999>0))/SUM((Trades!T$2:T$9999=Blotter!C35)*(Trades!U$2:U$9999=Blotter!B35)*(Trades!V$2:V$9999)*(Trades!V$2:V$9999>0)),0)} -> 3.7525 | Z35: =IF(C$2="Last",IF(ISNUMBER(VLOOKUP(B35,Data_IB!B:O,14,0)),VLOOKUP(B35,Data_IB!B:O,14,0),0),IF(ISNUMBER(VLOOKUP(B35,Data_IB!B:O,13,0)),VLOOKUP(B35,Data_IB!B:O,13,0),0)) -> 0
B36: HGU3 | C36: 8 | D36: HG | E36: Commodities | F36: Futures | G36: =IF(F36="Futures",VLOOKUP(D36,Multiplier!B:I,8,0),0) -> 6 | H36: 4 | I36: {=SUM((Trades!V$2:V$9999)*(Trades!U$2:U$9999=Blotter!B36)*(Trades!$T$2:T$9999=Blotter!C36))} -> 0 | J36: =VLOOKUP(D36,Multiplier!B:D,2,0) -> 25000 | K36: =L36-N36/(H36*J36) -> 3.5744981 | L36: =IF(I36=0,IF(H36>0,X36,Y36),Z36) -> 3.7596429 | M36: =I36*J36*L36 -> 0 | N36: {=-SUM((Trades!T$2:T$9999=Blotter!C36)*(Trades!U$2:U$9999=Blotter!B36)*(Trades!V$2:V$9999)*(Trades!W$2:W$9999))*J36+SUM((Trades!T$2:T$9999=Blotter!C36)*(Trades!U$2:U$9999=Blotter!B36)*(Trades!X$2:X$9999))+(L36*I36)*J36} -> 18514.48 | O36: =VLOOKUP(D36,Multiplier!B:H,3,0) -> 0.0708 | P36: 0.09 | R36: =(1-Q36)*P36*J36*H36 -> 9000 | S36: =IF(OR(F36="Futures",F36="Stocks"),IF(I36=0,0,IF(I36>0,L36-O36,L36+O36)),0) -> 0 | T36: =IF(S36>0,IF(ISNUMBER(S36/L36-1),S36/L36-1,0),0) -> 0 | U36: =IF(OR(F36="Futures",F36="Stocks"),IF(I36=0,0,IF(I36>0,K36-P36,K36+P36)),0) -> 0 | V36: =IF(U36>0,IF(ISNUMBER(U36/L36-1),U36/L36-1,0),0) -> 0 | X36: {=IF(ISNUMBER(SUM((Trades!T$2:T$9999=Blotter!C36)*(Trades!U$2:U$9999=Blotter!B36)*(Trades!W$2:W$9999)*(Trades!V$2:V$9999)*(Trades!V$2:V$9999<0))/SUM((Trades!T$2:T$9999=Blotter!C36)*(Trades!U$2:U$9999=Blotter!B36)*(Trades!V$2:V$9999)*(Trades!V$2:V$9999<0))),SUM((Trades!T$2:T$9999=Blotter!C36)*(Trades!U$2:U$9999=Blotter!B36)*(Trades!W$2:W$9999)*(Trades!V$2:V$9999)*(Trades!V$2:V$9999<0))/SUM((Trades!T$2:T$9999=Blotter!C36)*(Trades!U$2:U$9999=Blotter!B36)*(Trades!V$2:V$9999)*(Trades!V$2:V$9999<0)),0)} -> 3.7596429 | Y36: {=IF(ISNUMBER(SUM((Trades!T$2:T$9999=Blotter!C36)*(Trades!U$2:U$9999=Blotter!B36)*(Trades!W$2:W$9999)*(Trades!V$2:V$9999)*(Trades!V$2:V$9999>0))/SUM((Trades!T$2:T$9999=Blotter!C36)*(Trades!U$2:U$9999=Blotter!B36)*(Trades!V$2:V$9999)*(Trades!V$2:V$9999>0))),SUM((Trades!T$2:T$9999=Blotter!C36)*(Trades!U$2:U$9999=Blotter!B36)*(Trades!W$2:W$9999)*(Trades!V$2:V$9999)*(Trades!V$2:V$9999>0))/SUM((Trades!T$2:T$9999=Blotter!C36)*(Trades!U$2:U$9999=Blotter!B36)*(Trades!V$2:V$9999)*(Trades!V$2:V$9999>0)),0)} -> 3.733 | Z36: =IF(C$2="Last",IF(ISNUMBER(VLOOKUP(B36,Data_IB!B:O,14,0)),VLOOKUP(B36,Data_IB!B:O,14,0),0),IF(ISNUMBER(VLOOKUP(B36,Data_IB!B:O,13,0)),VLOOKUP(B36,Data_IB!B:O,13,0),0)) -> 0
B37: INDA 231215C00044000 | C37: 9 | D37: INDA | E37: Equity | F37: Call | G37: =IF(F37="Futures",VLOOKUP(D37,Multiplier!B:I,8,0),0) -> 0 | H37: 70 | I37: {=SUM((Trades!V$2:V$9999)*(Trades!U$2:U$9999=Blotter!B37)*(Trades!$T$2:T$9999=Blotter!C37))} -> 0 | J37: =VLOOKUP(D37,Multiplier!B:D,2,0) -> 100 | K37: =L37-N37/(H37*J37) -> 1.3962474 | L37: =IF(I37=0,IF(H37>0,X37,Y37),Z37) -> 2.325 | M37: =I37*J37*L37 -> 0 | N37: {=-SUM((Trades!T$2:T$9999=Blotter!C37)*(Trades!U$2:U$9999=Blotter!B37)*(Trades!V$2:V$9999)*(Trades!W$2:W$9999))*J37+SUM((Trades!T$2:T$9999=Blotter!C37)*(Trades!U$2:U$9999=Blotter!B37)*(Trades!X$2:X$9999))+(L37*I37)*J37} -> 6501.268 | O37: =VLOOKUP(D37,Multiplier!B:H,3,0) -> 0.3075 | P37: 1.4 | R37: =(1-Q37)*P37*J37*H37 -> 9800 | S37: =IF(OR(F37="Futures",F37="Stocks"),IF(I37=0,0,IF(I37>0,L37-O37,L37+O37)),0) -> 0 | T37: =IF(S37>0,IF(ISNUMBER(S37/L37-1),S37/L37-1,0),0) -> 0 | U37: =IF(OR(F37="Futures",F37="Stocks"),IF(I37=0,0,IF(I37>0,K37-P37,K37+P37)),0) -> 0 | V37: =IF(U37>0,IF(ISNUMBER(U37/L37-1),U37/L37-1,0),0) -> 0 | X37: {=IF(ISNUMBER(SUM((Trades!T$2:T$9999=Blotter!C37)*(Trades!U$2:U$9999=Blotter!B37)*(Trades!W$2:W$9999)*(Trades!V$2:V$9999)*(Trades!V$2:V$9999<0))/SUM((Trades!T$2:T$9999=Blotter!C37)*(Trades!U$2:U$9999=Blotter!B37)*(Trades!V$2:V$9999)*(Trades!V$2:V$9999<0))),SUM((Trades!T$2:T$9999=Blotter!C37)*(Trades!U$2:U$9999=Blotter!B37)*(Trades!W$2:W$9999)*(Trades!V$2:V$9999)*(Trades!V$2:V$9999<0))/SUM((Trades!T$2:T$9999=Blotter!C37)*(Trades!U$2:U$9999=Blotter!B37)*(Trades!V$2:V$9999)*(Trades!V$2:V$9999<0)),0)} -> 2.325 | Y37: {=IF(ISNUMBER(SUM((Trades!T$2:T$9999=Blotter!C37)*(Trades!U$2:U$9999=Blotter!B37)*(Trades!W$2:W$9999)*(Trades!V$2:V$9999)*(Trades!V$2:V$9999>0))/SUM((Trades!T$2:T$9999=Blotter!C37)*(Trades!U$2:U$9999=Blotter!B37)*(Trades!V$2:V$9999)*(Trades!V$2:V$9999>0))),SUM((Trades!T$2:T$9999=Blotter!C37)*(Trades!U$2:U$9999=Blotter!B37)*(Trades!W$2:W$9999)*(Trades!V$2:V$9999)*(Trades!V$2:V$9999>0))/SUM((Trades!T$2:T$9999=Blotter!C37)*(Trades!U$2:U$9999=Blotter!B37)*(Trades!V$2:V$9999)*(Trades!V$2:V$9999>0)),0)} -> 1.3985714 | Z37: =IF(C$2="Last",IF(ISNUMBER(VLOOKUP(B37,Data_IB!B:O,14,0)),VLOOKUP(B37,Data_IB!B:O,14,0),0),IF(ISNUMBER(VLOOKUP(B37,Data_IB!B:O,13,0)),VLOOKUP(B37,Data_IB!B:O,13,0),0)) -> 0
B38: SPXW 230622P04340000 | C38: 10 | D38: SPX | E38: Equity | F38: Put | G38: =IF(F38="Futures",VLOOKUP(D38,Multiplier!B:I,8,0),0) -> 0 | H38: 4 | I38: {=SUM((Trades!V$2:V$9999)*(Trades!U$2:U$9999=Blotter!B38)*(Trades!$T$2:T$9999=Blotter!C38))} -> 0 | J38: =VLOOKUP(D38,Multiplier!B:D,2,0) -> 100 | K38: =L38-N38/(H38*J38) -> 11.505413 | L38: =IF(I38=0,IF(H38>0,X38,Y38),Z38) -> 8.0666667 | M38: =I38*J38*L38 -> 0 | N38: {=-SUM((Trades!T$2:T$9999=Blotter!C38)*(Trades!U$2:U$9999=Blotter!B38)*(Trades!V$2:V$9999)*(Trades!W$2:W$9999))*J38+SUM((Trades!T$2:T$9999=Blotter!C38)*(Trades!U$2:U$9999=Blotter!B38)*(Trades!X$2:X$9999))+(L38*I38)*J38} -> -1375.4986 | O38: =VLOOKUP(D38,Multiplier!B:H,3,0) -> 42 | P38: 8.5 | R38: =(1-Q38)*P38*J38*H38 -> 3400 | S38: =IF(OR(F38="Futures",F38="Stocks"),IF(I38=0,0,IF(I38>0,L38-O38,L38+O38)),0) -> 0 | T38: =IF(S38>0,IF(ISNUMBER(S38/L38-1),S38/L38-1,0),0) -> 0 | U38: =IF(OR(F38="Futures",F38="Stocks"),IF(I38=0,0,IF(I38>0,K38-P38,K38+P38)),0) -> 0 | V38: =IF(U38>0,IF(ISNUMBER(U38/L38-1),U38/L38-1,0),0) -> 0 | X38: {=IF(ISNUMBER(SUM((Trades!T$2:T$9999=Blotter!C38)*(Trades!U$2:U$9999=Blotter!B38)*(Trades!W$2:W$9999)*(Trades!V$2:V$9999)*(Trades!V$2:V$9999<0))/SUM((Trades!T$2:T$9999=Blotter!C38)*(Trades!U$2:U$9999=Blotter!B38)*(Trades!V$2:V$9999)*(Trades!V$2:V$9999<0))),SUM((Trades!T$2:T$9999=Blotter!C38)*(Trades!U$2:U$9999=Blotter!B38)*(Trades!W$2:W$9999)*(Trades!V$2:V$9999)*(Trades!V$2:V$9999<0))/SUM((Trades!T$2:T$9999=Blotter!C38)*(Trades!U$2:U$9999=Blotter!B38)*(Trades!V$2:V$9999)*(Trades!V$2:V$9999<0)),0)} -> 8.0666667 | Y38: {=IF(ISNUMBER(SUM((Trades!T$2:T$9999=Blotter!C38)*(Trades!U$2:U$9999=Blotter!B38)*(Trades!W$2:W$9999)*(Trades!V$2:V$9999)*(Trades!V$2:V$9999>0))/SUM((Trades!T$2:T$9999=Blotter!C38)*(Trades!U$2:U$9999=Blotter!B38)*(Trades!V$2:V$9999)*(Trades!V$2:V$9999>0))),SUM((Trades!T$2:T$9999=Blotter!C38)*(Trades!U$2:U$9999=Blotter!B38)*(Trades!W$2:W$9999)*(Trades!V$2:V$9999)*(Trades!V$2:V$9999>0))/SUM((Trades!T$2:T$9999=Blotter!C38)*(Trades!U$2:U$9999=Blotter!B38)*(Trades!V$2:V$9999)*(Trades!V$2:V$9999>0)),0)} -> 10.333333 | Z38: =IF(C$2="Last",IF(ISNUMBER(VLOOKUP(B38,Data_IB!B:O,14,0)),VLOOKUP(B38,Data_IB!B:O,14,0),0),IF(ISNUMBER(VLOOKUP(B38,Data_IB!B:O,13,0)),VLOOKUP(B38,Data_IB!B:O,13,0),0)) -> 0
B39: RBQ3 | C39: 11 | D39: RB | E39: Commodities | F39: Futures | G39: =IF(F39="Futures",VLOOKUP(D39,Multiplier!B:I,8,0),0) -> 3 | H39: 2 | I39: {=SUM((Trades!V$2:V$9999)*(Trades!U$2:U$9999=Blotter!B39)*(Trades!$T$2:T$9999=Blotter!C39))} -> 0 | J39: =VLOOKUP(D39,Multiplier!B:D,2,0) -> 42000 | K39: =L39-N39/(H39*J39) -> 2.5053707 | L39: =IF(I39=0,IF(H39>0,X39,Y39),Z39) -> 2.5385 | M39: =I39*J39*L39 -> 0 | N39: {=-SUM((Trades!T$2:T$9999=Blotter!C39)*(Trades!U$2:U$9999=Blotter!B39)*(Trades!V$2:V$9999)*(Trades!W$2:W$9999))*J39+SUM((Trades!T$2:T$9999=Blotter!C39)*(Trades!U$2:U$9999=Blotter!B39)*(Trades!X$2:X$9999))+(L39*I39)*J39} -> 2782.86 | O39: =VLOOKUP(D39,Multiplier!B:H,3,0) -> 0.0725 | P39: 0.1 | R39: =(1-Q39)*P39*J39*H39 -> 8400 | S39: =IF(OR(F39="Futures",F39="Stocks"),IF(I39=0,0,IF(I39>0,L39-O39,L39+O39)),0) -> 0 | T39: =IF(S39>0,IF(ISNUMBER(S39/L39-1),S39/L39-1,0),0) -> 0 | U39: =IF(OR(F39="Futures",F39="Stocks"),IF(I39=0,0,IF(I39>0,K39-P39,K39+P39)),0) -> 0 | V39: =IF(U39>0,IF(ISNUMBER(U39/L39-1),U39/L39-1,0),0) -> 0 | X39: {=IF(ISNUMBER(SUM((Trades!T$2:T$9999=Blotter!C39)*(Trades!U$2:U$9999=Blotter!B39)*(Trades!W$2:W$9999)*(Trades!V$2:V$9999)*(Trades!V$2:V$9999<0))/SUM((Trades!T$2:T$9999=Blotter!C39)*(Trades!U$2:U$9999=Blotter!B39)*(Trades!V$2:V$9999)*(Trades!V$2:V$9999<0))),SUM((Trades!T$2:T$9999=Blotter!C39)*(Trades!U$2:U$9999=Blotter!B39)*(Trades!W$2:W$9999)*(Trades!V$2:V$9999)*(Trades!V$2:V$9999<0))/SUM((Trades!T$2:T$9999=Blotter!C39)*(Trades!U$2:U$9999=Blotter!B39)*(Trades!V$2:V$9999)*(Trades!V$2:V$9999<0)),0)} -> 2.5385 | Y39: {=IF(ISNUMBER(SUM((Trades!T$2:T$9999=Blotter!C39)*(Trades!U$2:U$9999=Blotter!B39)*(Trades!W$2:W$9999)*(Trades!V$2:V$9999)*(Trades!V$2:V$9999>0))/SUM((Trades!T$2:T$9999=Blotter!C39)*(Trades!U$2:U$9999=Blotter!B39)*(Trades!V$2:V$9999)*(Trades!V$2:V$9999>0))),SUM((Trades!T$2:T$9999=Blotter!C39)*(Trades!U$2:U$9999=Blotter!B39)*(Trades!W$2:W$9999)*(Trades!V$2:V$9999)*(Trades!V$2:V$9999>0))/SUM((Trades!T$2:T$9999=Blotter!C39)*(Trades!U$2:U$9999=Blotter!B39)*(Trades!V$2:V$9999)*(Trades!V$2:V$9999>0)),0)} -> 2.5323636 | Z39: =IF(C$2="Last",IF(ISNUMBER(VLOOKUP(B39,Data_IB!B:O,14,0)),VLOOKUP(B39,Data_IB!B:O,14,0),0),IF(ISNUMBER(VLOOKUP(B39,Data_IB!B:O,13,0)),VLOOKUP(B39,Data_IB!B:O,13,0),0)) -> 0
B40: C OZC DEC 23 6000 | C40: 13 | D40: ZC | E40: Commodities | F40: Call | G40: =IF(F40="Futures",VLOOKUP(D40,Multiplier!B:I,8,0),0) -> 0 | H40: 12 | I40: {=SUM((Trades!V$2:V$9999)*(Trades!U$2:U$9999=Blotter!B40)*(Trades!$T$2:T$9999=Blotter!C40))} -> 0 | J40: =VLOOKUP(D40,Multiplier!B:D,2,0) -> 50 | K40: =L40-N40/(H40*J40) -> 8.5792 | L40: =IF(I40=0,IF(H40>0,X40,Y40),Z40) -> 8.6666667 | M40: =I40*J40*L40 -> 0 | N40: {=-SUM((Trades!T$2:T$9999=Blotter!C40)*(Trades!U$2:U$9999=Blotter!B40)*(Trades!V$2:V$9999)*(Trades!W$2:W$9999))*J40+SUM((Trades!T$2:T$9999=Blotter!C40)*(Trades!U$2:U$9999=Blotter!B40)*(Trades!X$2:X$9999))+(L40*I40)*J40} -> 52.48 | O40: =VLOOKUP(D40,Multiplier!B:H,3,0) -> 8.25 | P40: 8.5 | R40: =(1-Q40)*P40*J40*H40 -> 5100 | S40: =IF(OR(F40="Futures",F40="Stocks"),IF(I40=0,0,IF(I40>0,L40-O40,L40+O40)),0) -> 0 | T40: =IF(S40>0,IF(ISNUMBER(S40/L40-1),S40/L40-1,0),0) -> 0 | U40: =IF(OR(F40="Futures",F40="Stocks"),IF(I40=0,0,IF(I40>0,K40-P40,K40+P40)),0) -> 0 | V40: =IF(U40>0,IF(ISNUMBER(U40/L40-1),U40/L40-1,0),0) -> 0 | X40: {=IF(ISNUMBER(SUM((Trades!T$2:T$9999=Blotter!C40)*(Trades!U$2:U$9999=Blotter!B40)*(Trades!W$2:W$9999)*(Trades!V$2:V$9999)*(Trades!V$2:V$9999<0))/SUM((Trades!T$2:T$9999=Blotter!C40)*(Trades!U$2:U$9999=Blotter!B40)*(Trades!V$2:V$9999)*(Trades!V$2:V$9999<0))),SUM((Trades!T$2:T$9999=Blotter!C40)*(Trades!U$2:U$9999=Blotter!B40)*(Trades!W$2:W$9999)*(Trades!V$2:V$9999)*(Trades!V$2:V$9999<0))/SUM((Trades!T$2:T$9999=Blotter!C40)*(Trades!U$2:U$9999=Blotter!B40)*(Trades!V$2:V$9999)*(Trades!V$2:V$9999<0)),0)} -> 8.6666667 | Y40: {=IF(ISNUMBER(SUM((Trades!T$2:T$9999=Blotter!C40)*(Trades!U$2:U$9999=Blotter!B40)*(Trades!W$2:W$9999)*(Trades!V$2:V$9999)*(Trades!V$2:V$9999>0))/SUM((Trades!T$2:T$9999=Blotter!C40)*(Trades!U$2:U$9999=Blotter!B40)*(Trades!V$2:V$9999)*(Trades!V$2:V$9999>0))),SUM((Trades!T$2:T$9999=Blotter!C40)*(Trades!U$2:U$9999=Blotter!B40)*(Trades!W$2:W$9999)*(Trades!V$2:V$9999)*(Trades!V$2:V$9999>0))/SUM((Trades!T$2:T$9999=Blotter!C40)*(Trades!U$2:U$9999=Blotter!B40)*(Trades!V$2:V$9999)*(Trades!V$2:V$9999>0)),0)} -> 8.5 | Z40: =IF(C$2="Last",IF(ISNUMBER(VLOOKUP(B40,Data_IB!B:O,14,0)),VLOOKUP(B40,Data_IB!B:O,14,0),0),IF(ISNUMBER(VLOOKUP(B40,Data_IB!B:O,13,0)),VLOOKUP(B40,Data_IB!B:O,13,0),0)) -> 0
B41: ZCU3 | C41: 13 | D41: ZC | E41: Commodities | F41: Futures | G41: =IF(F41="Futures",VLOOKUP(D41,Multiplier!B:I,8,0),0) -> 24 | H41: 4 | I41: {=SUM((Trades!V$2:V$9999)*(Trades!U$2:U$9999=Blotter!B41)*(Trades!$T$2:T$9999=Blotter!C41))} -> 0 | J41: =VLOOKUP(D41,Multiplier!B:D,2,0) -> 50 | K41: =L41-N41/(H41*J41) -> 483.6188 | L41: =IF(I41=0,IF(H41>0,X41,Y41),Z41) -> 538 | M41: =I41*J41*L41 -> 0 | N41: {=-SUM((Trades!T$2:T$9999=Blotter!C41)*(Trades!U$2:U$9999=Blotter!B41)*(Trades!V$2:V$9999)*(Trades!W$2:W$9999))*J41+SUM((Trades!T$2:T$9999=Blotter!C41)*(Trades!U$2:U$9999=Blotter!B41)*(Trades!X$2:X$9999))+(L41*I41)*J41} -> 10876.24 | O41: =VLOOKUP(D41,Multiplier!B:H,3,0) -> 8.25 | P41: 13.5 | Q41: 1 | R41: =(1-Q41)*P41*J41*H41 -> 0 | S41: =IF(OR(F41="Futures",F41="Stocks"),IF(I41=0,0,IF(I41>0,L41-O41,L41+O41)),0) -> 0 | T41: =IF(S41>0,IF(ISNUMBER(S41/L41-1),S41/L41-1,0),0) -> 0 | U41: =IF(OR(F41="Futures",F41="Stocks"),IF(I41=0,0,IF(I41>0,K41-P41,K41+P41)),0) -> 0 | V41: =IF(U41>0,IF(ISNUMBER(U41/L41-1),U41/L41-1,0),0) -> 0 | X41: {=IF(ISNUMBER(SUM((Trades!T$2:T$9999=Blotter!C41)*(Trades!U$2:U$9999=Blotter!B41)*(Trades!W$2:W$9999)*(Trades!V$2:V$9999)*(Trades!V$2:V$9999<0))/SUM((Trades!T$2:T$9999=Blotter!C41)*(Trades!U$2:U$9999=Blotter!B41)*(Trades!V$2:V$9999)*(Trades!V$2:V$9999<0))),SUM((Trades!T$2:T$9999=Blotter!C41)*(Trades!U$2:U$9999=Blotter!B41)*(Trades!W$2:W$9999)*(Trades!V$2:V$9999)*(Trades!V$2:V$9999<0))/SUM((Trades!T$2:T$9999=Blotter!C41)*(Trades!U$2:U$9999=Blotter!B41)*(Trades!V$2:V$9999)*(Trades!V$2:V$9999<0)),0)} -> 538 | Y41: {=IF(ISNUMBER(SUM((Trades!T$2:T$9999=Blotter!C41)*(Trades!U$2:U$9999=Blotter!B41)*(Trades!W$2:W$9999)*(Trades!V$2:V$9999)*(Trades!V$2:V$9999>0))/SUM((Trades!T$2:T$9999=Blotter!C41)*(Trades!U$2:U$9999=Blotter!B41)*(Trades!V$2:V$9999)*(Trades!V$2:V$9999>0))),SUM((Trades!T$2:T$9999=Blotter!C41)*(Trades!U$2:U$9999=Blotter!B41)*(Trades!W$2:W$9999)*(Trades!V$2:V$9999)*(Trades!V$2:V$9999>0))/SUM((Trades!T$2:T$9999=Blotter!C41)*(Trades!U$2:U$9999=Blotter!B41)*(Trades!V$2:V$9999)*(Trades!V$2:V$9999>0)),0)} -> 483.5 | Z41: =IF(C$2="Last",IF(ISNUMBER(VLOOKUP(B41,Data_IB!B:O,14,0)),VLOOKUP(B41,Data_IB!B:O,14,0),0),IF(ISNUMBER(VLOOKUP(B41,Data_IB!B:O,13,0)),VLOOKUP(B41,Data_IB!B:O,13,0),0)) -> 0
B42: ZCZ3 | C42: 13 | D42: ZC | E42: Commodities | F42: Futures | G42: =IF(F42="Futures",VLOOKUP(D42,Multiplier!B:I,8,0),0) -> 24 | H42: 4 | I42: {=SUM((Trades!V$2:V$9999)*(Trades!U$2:U$9999=Blotter!B42)*(Trades!$T$2:T$9999=Blotter!C42))} -> 0 | J42: =VLOOKUP(D42,Multiplier!B:D,2,0) -> 50 | K42: =L42-N42/(H42*J42) -> 532.1188 | L42: =IF(I42=0,IF(H42>0,X42,Y42),Z42) -> 552 | M42: =I42*J42*L42 -> 0 | N42: {=-SUM((Trades!T$2:T$9999=Blotter!C42)*(Trades!U$2:U$9999=Blotter!B42)*(Trades!V$2:V$9999)*(Trades!W$2:W$9999))*J42+SUM((Trades!T$2:T$9999=Blotter!C42)*(Trades!U$2:U$9999=Blotter!B42)*(Trades!X$2:X$9999))+(L42*I42)*J42} -> 3976.24 | O42: =VLOOKUP(D42,Multiplier!B:H,3,0) -> 8.25 | P42: 13.5 | R42: =(1-Q42)*P42*J42*H42 -> 2700 | S42: =IF(OR(F42="Futures",F42="Stocks"),IF(I42=0,0,IF(I42>0,L42-O42,L42+O42)),0) -> 0 | T42: =IF(S42>0,IF(ISNUMBER(S42/L42-1),S42/L42-1,0),0) -> 0 | U42: =IF(OR(F42="Futures",F42="Stocks"),IF(I42=0,0,IF(I42>0,K42-P42,K42+P42)),0) -> 0 | V42: =IF(U42>0,IF(ISNUMBER(U42/L42-1),U42/L42-1,0),0) -> 0 | X42: {=IF(ISNUMBER(SUM((Trades!T$2:T$9999=Blotter!C42)*(Trades!U$2:U$9999=Blotter!B42)*(Trades!W$2:W$9999)*(Trades!V$2:V$9999)*(Trades!V$2:V$9999<0))/SUM((Trades!T$2:T$9999=Blotter!C42)*(Trades!U$2:U$9999=Blotter!B42)*(Trades!V$2:V$9999)*(Trades!V$2:V$9999<0))),SUM((Trades!T$2:T$9999=Blotter!C42)*(Trades!U$2:U$9999=Blotter!B42)*(Trades!W$2:W$9999)*(Trades!V$2:V$9999)*(Trades!V$2:V$9999<0))/SUM((Trades!T$2:T$9999=Blotter!C42)*(Trades!U$2:U$9999=Blotter!B42)*(Trades!V$2:V$9999)*(Trades!V$2:V$9999<0)),0)} -> 552 | Y42: {=IF(ISNUMBER(SUM((Trades!T$2:T$9999=Blotter!C42)*(Trades!U$2:U$9999=Blotter!B42)*(Trades!W$2:W$9999)*(Trades!V$2:V$9999)*(Trades!V$2:V$9999>0))/SUM((Trades!T$2:T$9999=Blotter!C42)*(Trades!U$2:U$9999=Blotter!B42)*(Trades!V$2:V$9999)*(Trades!V$2:V$9999>0))),SUM((Trades!T$2:T$9999=Blotter!C42)*(Trades!U$2:U$9999=Blotter!B42)*(Trades!W$2:W$9999)*(Trades!V$2:V$9999)*(Trades!V$2:V$9999>0))/SUM((Trades!T$2:T$9999=Blotter!C42)*(Trades!U$2:U$9999=Blotter!B42)*(Trades!V$2:V$9999)*(Trades!V$2:V$9999>0)),0)} -> 532 | Z42: =IF(C$2="Last",IF(ISNUMBER(VLOOKUP(B42,Data_IB!B:O,14,0)),VLOOKUP(B42,Data_IB!B:O,14,0),0),IF(ISNUMBER(VLOOKUP(B42,Data_IB!B:O,13,0)),VLOOKUP(B42,Data_IB!B:O,13,0),0)) -> 0
B43: SBV3 | C43: 14 | D43: SB | E43: Commodities | F43: Futures | G43: =IF(F43="Futures",VLOOKUP(D43,Multiplier!B:I,8,0),0) -> 10 | H43: 14 | I43: {=SUM((Trades!V$2:V$9999)*(Trades!U$2:U$9999=Blotter!B43)*(Trades!$T$2:T$9999=Blotter!C43))} -> 0 | J43: =VLOOKUP(D43,Multiplier!B:D,2,0) -> 1120 | K43: =L43-N43/(H43*J43) -> 23.303107 | L43: =IF(I43=0,IF(H43>0,X43,Y43),Z43) -> 24.1875 | M43: =I43*J43*L43 -> 0 | N43: {=-SUM((Trades!T$2:T$9999=Blotter!C43)*(Trades!U$2:U$9999=Blotter!B43)*(Trades!V$2:V$9999)*(Trades!W$2:W$9999))*J43+SUM((Trades!T$2:T$9999=Blotter!C43)*(Trades!U$2:U$9999=Blotter!B43)*(Trades!X$2:X$9999))+(L43*I43)*J43} -> 13867.28 | O43: =VLOOKUP(D43,Multiplier!B:H,3,0) -> 0.89 | P43: 0.63 | R43: =(1-Q43)*P43*J43*H43 -> 9878.4 | S43: =IF(OR(F43="Futures",F43="Stocks"),IF(I43=0,0,IF(I43>0,L43-O43,L43+O43)),0) -> 0 | T43: =IF(S43>0,IF(ISNUMBER(S43/L43-1),S43/L43-1,0),0) -> 0 | U43: =IF(OR(F43="Futures",F43="Stocks"),IF(I43=0,0,IF(I43>0,K43-P43,K43+P43)),0) -> 0 | V43: =IF(U43>0,IF(ISNUMBER(U43/L43-1),U43/L43-1,0),0) -> 0 | X43: {=IF(ISNUMBER(SUM((Trades!T$2:T$9999=Blotter!C43)*(Trades!U$2:U$9999=Blotter!B43)*(Trades!W$2:W$9999)*(Trades!V$2:V$9999)*(Trades!V$2:V$9999<0))/SUM((Trades!T$2:T$9999=Blotter!C43)*(Trades!U$2:U$9999=Blotter!B43)*(Trades!V$2:V$9999)*(Trades!V$2:V$9999<0))),SUM((Trades!T$2:T$9999=Blotter!C43)*(Trades!U$2:U$9999=Blotter!B43)*(Trades!W$2:W$9999)*(Trades!V$2:V$9999)*(Trades!V$2:V$9999<0))/SUM((Trades!T$2:T$9999=Blotter!C43)*(Trades!U$2:U$9999=Blotter!B43)*(Trades!V$2:V$9999)*(Trades!V$2:V$9999<0)),0)} -> 24.1875 | Y43: {=IF(ISNUMBER(SUM((Trades!T$2:T$9999=Blotter!C43)*(Trades!U$2:U$9999=Blotter!B43)*(Trades!W$2:W$9999)*(Trades!V$2:V$9999)*(Trades!V$2:V$9999>0))/SUM((Trades!T$2:T$9999=Blotter!C43)*(Trades!U$2:U$9999=Blotter!B43)*(Trades!V$2:V$9999)*(Trades!V$2:V$9999>0))),SUM((Trades!T$2:T$9999=Blotter!C43)*(Trades!U$2:U$9999=Blotter!B43)*(Trades!W$2:W$9999)*(Trades!V$2:V$9999)*(Trades!V$2:V$9999>0))/SUM((Trades!T$2:T$9999=Blotter!C43)*(Trades!U$2:U$9999=Blotter!B43)*(Trades!V$2:V$9999)*(Trades!V$2:V$9999>0)),0)} -> 23.74 | Z43: =IF(C$2="Last",IF(ISNUMBER(VLOOKUP(B43,Data_IB!B:O,14,0)),VLOOKUP(B43,Data_IB!B:O,14,0),0),IF(ISNUMBER(VLOOKUP(B43,Data_IB!B:O,13,0)),VLOOKUP(B43,Data_IB!B:O,13,0),0)) -> 0
B44: KCU3 | C44: 16 | D44: KC | E44: Commodities | F44: Futures | G44: =IF(F44="Futures",VLOOKUP(D44,Multiplier!B:I,8,0),0) -> 5 | H44: 6 | I44: {=SUM((Trades!V$2:V$9999)*(Trades!U$2:U$9999=Blotter!B44)*(Trades!$T$2:T$9999=Blotter!C44))} -> 0 | J44: =VLOOKUP(D44,Multiplier!B:D,2,0) -> 375 | K44: =L44-N44/(H44*J44) -> 160.71584 | L44: =IF(I44=0,IF(H44>0,X44,Y44),Z44) -> 160.85 | M44: =I44*J44*L44 -> 0 | N44: {=-SUM((Trades!T$2:T$9999=Blotter!C44)*(Trades!U$2:U$9999=Blotter!B44)*(Trades!V$2:V$9999)*(Trades!W$2:W$9999))*J44+SUM((Trades!T$2:T$9999=Blotter!C44)*(Trades!U$2:U$9999=Blotter!B44)*(Trades!X$2:X$9999))+(L44*I44)*J44} -> 301.86 | O44: =VLOOKUP(D44,Multiplier!B:H,3,0) -> 5.38 | P44: 4.4 | R44: =(1-Q44)*P44*J44*H44 -> 9900 | S44: =IF(OR(F44="Futures",F44="Stocks"),IF(I44=0,0,IF(I44>0,L44-O44,L44+O44)),0) -> 0 | T44: =IF(S44>0,IF(ISNUMBER(S44/L44-1),S44/L44-1,0),0) -> 0 | U44: =IF(OR(F44="Futures",F44="Stocks"),IF(I44=0,0,IF(I44>0,K44-P44,K44+P44)),0) -> 0 | V44: =IF(U44>0,IF(ISNUMBER(U44/L44-1),U44/L44-1,0),0) -> 0 | X44: {=IF(ISNUMBER(SUM((Trades!T$2:T$9999=Blotter!C44)*(Trades!U$2:U$9999=Blotter!B44)*(Trades!W$2:W$9999)*(Trades!V$2:V$9999)*(Trades!V$2:V$9999<0))/SUM((Trades!T$2:T$9999=Blotter!C44)*(Trades!U$2:U$9999=Blotter!B44)*(Trades!V$2:V$9999)*(Trades!V$2:V$9999<0))),SUM((Trades!T$2:T$9999=Blotter!C44)*(Trades!U$2:U$9999=Blotter!B44)*(Trades!W$2:W$9999)*(Trades!V$2:V$9999)*(Trades!V$2:V$9999<0))/SUM((Trades!T$2:T$9999=Blotter!C44)*(Trades!U$2:U$9999=Blotter!B44)*(Trades!V$2:V$9999)*(Trades!V$2:V$9999<0)),0)} -> 160.85 | Y44: {=IF(ISNUMBER(SUM((Trades!T$2:T$9999=Blotter!C44)*(Trades!U$2:U$9999=Blotter!B44)*(Trades!W$2:W$9999)*(Trades!V$2:V$9999)*(Trades!V$2:V$9999>0))/SUM((Trades!T$2:T$9999=Blotter!C44)*(Trades!U$2:U$9999=Blotter!B44)*(Trades!V$2:V$9999)*(Trades!V$2:V$9999>0))),SUM((Trades!T$2:T$9999=Blotter!C44)*(Trades!U$2:U$9999=Blotter!B44)*(Trades!W$2:W$9999)*(Trades!V$2:V$9999)*(Trades!V$2:V$9999>0))/SUM((Trades!T$2:T$9999=Blotter!C44)*(Trades!U$2:U$9999=Blotter!B44)*(Trades!V$2:V$9999)*(Trades!V$2:V$9999>0)),0)} -> 160.7 | Z44: =IF(C$2="Last",IF(ISNUMBER(VLOOKUP(B44,Data_IB!B:O,14,0)),VLOOKUP(B44,Data_IB!B:O,14,0),0),IF(ISNUMBER(VLOOKUP(B44,Data_IB!B:O,13,0)),VLOOKUP(B44,Data_IB!B:O,13,0),0)) -> 0
B45: SPX 231020P04390000 | C45: 17 | D45: SPX | E45: Equity | F45: Put | G45: =IF(F45="Futures",VLOOKUP(D45,Multiplier!B:I,8,0),0) -> 0 | H45: 10 | I45: {=SUM((Trades!V$2:V$9999)*(Trades!U$2:U$9999=Blotter!B45)*(Trades!$T$2:T$9999=Blotter!C45))} -> 0 | J45: =VLOOKUP(D45,Multiplier!B:D,2,0) -> 100 | K45: =L45-N45/(H45*J45) -> 14.469008 | L45: =IF(I45=0,IF(H45>0,X45,Y45),Z45) -> 75.65 | M45: =I45*J45*L45 -> 0 | N45: {=-SUM((Trades!T$2:T$9999=Blotter!C45)*(Trades!U$2:U$9999=Blotter!B45)*(Trades!V$2:V$9999)*(Trades!W$2:W$9999))*J45+SUM((Trades!T$2:T$9999=Blotter!C45)*(Trades!U$2:U$9999=Blotter!B45)*(Trades!X$2:X$9999))+(L45*I45)*J45} -> 61180.992 | O45: =VLOOKUP(D45,Multiplier!B:H,3,0) -> 42 | P45: 47.7 | R45: =(1-Q45)*P45*J45*H45 -> 47700 | S45: =IF(OR(F45="Futures",F45="Stocks"),IF(I45=0,0,IF(I45>0,L45-O45,L45+O45)),0) -> 0 | T45: =IF(S45>0,IF(ISNUMBER(S45/L45-1),S45/L45-1,0),0) -> 0 | U45: =IF(OR(F45="Futures",F45="Stocks"),IF(I45=0,0,IF(I45>0,K45-P45,K45+P45)),0) -> 0 | V45: =IF(U45>0,IF(ISNUMBER(U45/L45-1),U45/L45-1,0),0) -> 0 | X45: {=IF(ISNUMBER(SUM((Trades!T$2:T$9999=Blotter!C45)*(Trades!U$2:U$9999=Blotter!B45)*(Trades!W$2:W$9999)*(Trades!V$2:V$9999)*(Trades!V$2:V$9999<0))/SUM((Trades!T$2:T$9999=Blotter!C45)*(Trades!U$2:U$9999=Blotter!B45)*(Trades!V$2:V$9999)*(Trades!V$2:V$9999<0))),SUM((Trades!T$2:T$9999=Blotter!C45)*(Trades!U$2:U$9999=Blotter!B45)*(Trades!W$2:W$9999)*(Trades!V$2:V$9999)*(Trades!V$2:V$9999<0))/SUM((Trades!T$2:T$9999=Blotter!C45)*(Trades!U$2:U$9999=Blotter!B45)*(Trades!V$2:V$9999)*(Trades!V$2:V$9999<0)),0)} -> 75.65 | Y45: {=IF(ISNUMBER(SUM((Trades!T$2:T$9999=Blotter!C45)*(Trades!U$2:U$9999=Blotter!B45)*(Trades!W$2:W$9999)*(Trades!V$2:V$9999)*(Trades!V$2:V$9999>0))/SUM((Trades!T$2:T$9999=Blotter!C45)*(Trades!U$2:U$9999=Blotter!B45)*(Trades!V$2:V$9999)*(Trades!V$2:V$9999>0))),SUM((Trades!T$2:T$9999=Blotter!C45)*(Trades!U$2:U$9999=Blotter!B45)*(Trades!W$2:W$9999)*(Trades!V$2:V$9999)*(Trades!V$2:V$9999>0))/SUM((Trades!T$2:T$9999=Blotter!C45)*(Trades!U$2:U$9999=Blotter!B45)*(Trades!V$2:V$9999)*(Trades!V$2:V$9999>0)),0)} -> 67.975 | Z45: =IF(C$2="Last",IF(ISNUMBER(VLOOKUP(B45,Data_IB!B:O,14,0)),VLOOKUP(B45,Data_IB!B:O,14,0),0),IF(ISNUMBER(VLOOKUP(B45,Data_IB!B:O,13,0)),VLOOKUP(B45,Data_IB!B:O,13,0),0)) -> 0
B46: SPX 231020P04300000 | C46: 17 | D46: SPX | E46: Equity | F46: Put | G46: =IF(F46="Futures",VLOOKUP(D46,Multiplier!B:I,8,0),0) -> 0 | H46: -10 | I46: {=SUM((Trades!V$2:V$9999)*(Trades!U$2:U$9999=Blotter!B46)*(Trades!$T$2:T$9999=Blotter!C46))} -> 0 | J46: =VLOOKUP(D46,Multiplier!B:D,2,0) -> 100 | K46: =L46-N46/(H46*J46) -> 38.52605 | L46: =IF(I46=0,IF(H46>0,X46,Y46),Z46) -> 60.271429 | M46: =I46*J46*L46 -> 0 | N46: {=-SUM((Trades!T$2:T$9999=Blotter!C46)*(Trades!U$2:U$9999=Blotter!B46)*(Trades!V$2:V$9999)*(Trades!W$2:W$9999))*J46+SUM((Trades!T$2:T$9999=Blotter!C46)*(Trades!U$2:U$9999=Blotter!B46)*(Trades!X$2:X$9999))+(L46*I46)*J46} -> -21745.378 | O46: =VLOOKUP(D46,Multiplier!B:H,3,0) -> 42 | P46: 39 | R46: =(1-Q46)*P46*J46*H46 -> -39000 | S46: =IF(OR(F46="Futures",F46="Stocks"),IF(I46=0,0,IF(I46>0,L46-O46,L46+O46)),0) -> 0 | T46: =IF(S46>0,IF(ISNUMBER(S46/L46-1),S46/L46-1,0),0) -> 0 | U46: =IF(OR(F46="Futures",F46="Stocks"),IF(I46=0,0,IF(I46>0,K46-P46,K46+P46)),0) -> 0 | V46: =IF(U46>0,IF(ISNUMBER(U46/L46-1),U46/L46-1,0),0) -> 0 | X46: {=IF(ISNUMBER(SUM((Trades!T$2:T$9999=Blotter!C46)*(Trades!U$2:U$9999=Blotter!B46)*(Trades!W$2:W$9999)*(Trades!V$2:V$9999)*(Trades!V$2:V$9999<0))/SUM((Trades!T$2:T$9999=Blotter!C46)*(Trades!U$2:U$9999=Blotter!B46)*(Trades!V$2:V$9999)*(Trades!V$2:V$9999<0))),SUM((Trades!T$2:T$9999=Blotter!C46)*(Trades!U$2:U$9999=Blotter!B46)*(Trades!W$2:W$9999)*(Trades!V$2:V$9999)*(Trades!V$2:V$9999<0))/SUM((Trades!T$2:T$9999=Blotter!C46)*(Trades!U$2:U$9999=Blotter!B46)*(Trades!V$2:V$9999)*(Trades!V$2:V$9999<0)),0)} -> 54.085714 | Y46: {=IF(ISNUMBER(SUM((Trades!T$2:T$9999=Blotter!C46)*(Trades!U$2:U$9999=Blotter!B46)*(Trades!W$2:W$9999)*(Trades!V$2:V$9999)*(Trades!V$2:V$9999>0))/SUM((Trades!T$2:T$9999=Blotter!C46)*(Trades!U$2:U$9999=Blotter!B46)*(Trades!V$2:V$9999)*(Trades!V$2:V$9999>0))),SUM((Trades!T$2:T$9999=Blotter!C46)*(Trades!U$2:U$9999=Blotter!B46)*(Trades!W$2:W$9999)*(Trades!V$2:V$9999)*(Trades!V$2:V$9999>0))/SUM((Trades!T$2:T$9999=Blotter!C46)*(Trades!U$2:U$9999=Blotter!B46)*(Trades!V$2:V$9999)*(Trades!V$2:V$9999>0)),0)} -> 60.271429 | Z46: =IF(C$2="Last",IF(ISNUMBER(VLOOKUP(B46,Data_IB!B:O,14,0)),VLOOKUP(B46,Data_IB!B:O,14,0),0),IF(ISNUMBER(VLOOKUP(B46,Data_IB!B:O,13,0)),VLOOKUP(B46,Data_IB!B:O,13,0),0)) -> 0
B47: CLV3 | C47: 21 | D47: CL | E47: Commodities | F47: Futures | G47: =IF(F47="Futures",VLOOKUP(D47,Multiplier!B:I,8,0),0) -> 4 | H47: 4 | I47: {=SUM((Trades!V$2:V$9999)*(Trades!U$2:U$9999=Blotter!B47)*(Trades!$T$2:T$9999=Blotter!C47))} -> 0 | J47: =VLOOKUP(D47,Multiplier!B:D,2,0) -> 1000 | K47: =L47-N47/(H47*J47) -> 81.27974 | L47: =IF(I47=0,IF(H47>0,X47,Y47),Z47) -> 86.35 | M47: =I47*J47*L47 -> 0 | N47: {=-SUM((Trades!T$2:T$9999=Blotter!C47)*(Trades!U$2:U$9999=Blotter!B47)*(Trades!V$2:V$9999)*(Trades!W$2:W$9999))*J47+SUM((Trades!T$2:T$9999=Blotter!C47)*(Trades!U$2:U$9999=Blotter!B47)*(Trades!X$2:X$9999))+(L47*I47)*J47} -> 20281.04 | O47: =VLOOKUP(D47,Multiplier!B:H,3,0) -> 2.41 | P47: 2.38 | R47: =(1-Q47)*P47*J47*H47 -> 9520 | S47: =IF(OR(F47="Futures",F47="Stocks"),IF(I47=0,0,IF(I47>0,L47-O47,L47+O47)),0) -> 0 | T47: =IF(S47>0,IF(ISNUMBER(S47/L47-1),S47/L47-1,0),0) -> 0 | U47: =IF(OR(F47="Futures",F47="Stocks"),IF(I47=0,0,IF(I47>0,K47-P47,K47+P47)),0) -> 0 | V47: =IF(U47>0,IF(ISNUMBER(U47/L47-1),U47/L47-1,0),0) -> 0 | X47: {=IF(ISNUMBER(SUM((Trades!T$2:T$9999=Blotter!C47)*(Trades!U$2:U$9999=Blotter!B47)*(Trades!W$2:W$9999)*(Trades!V$2:V$9999)*(Trades!V$2:V$9999<0))/SUM((Trades!T$2:T$9999=Blotter!C47)*(Trades!U$2:U$9999=Blotter!B47)*(Trades!V$2:V$9999)*(Trades!V$2:V$9999<0))),SUM((Trades!T$2:T$9999=Blotter!C47)*(Trades!U$2:U$9999=Blotter!B47)*(Trades!W$2:W$9999)*(Trades!V$2:V$9999)*(Trades!V$2:V$9999<0))/SUM((Trades!T$2:T$9999=Blotter!C47)*(Trades!U$2:U$9999=Blotter!B47)*(Trades!V$2:V$9999)*(Trades!V$2:V$9999<0)),0)} -> 86.35 | Y47: {=IF(ISNUMBER(SUM((Trades!T$2:T$9999=Blotter!C47)*(Trades!U$2:U$9999=Blotter!B47)*(Trades!W$2:W$9999)*(Trades!V$2:V$9999)*(Trades!V$2:V$9999>0))/SUM((Trades!T$2:T$9999=Blotter!C47)*(Trades!U$2:U$9999=Blotter!B47)*(Trades!V$2:V$9999)*(Trades!V$2:V$9999>0))),SUM((Trades!T$2:T$9999=Blotter!C47)*(Trades!U$2:U$9999=Blotter!B47)*(Trades!W$2:W$9999)*(Trades!V$2:V$9999)*(Trades!V$2:V$9999>0))/SUM((Trades!T$2:T$9999=Blotter!C47)*(Trades!U$2:U$9999=Blotter!B47)*(Trades!V$2:V$9999)*(Trades!V$2:V$9999>0)),0)} -> 81.275 | Z47: =IF(C$2="Last",IF(ISNUMBER(VLOOKUP(B47,Data_IB!B:O,14,0)),VLOOKUP(B47,Data_IB!B:O,14,0),0),IF(ISNUMBER(VLOOKUP(B47,Data_IB!B:O,13,0)),VLOOKUP(B47,Data_IB!B:O,13,0),0)) -> 0
B48: CTZ3 | C48: 24 | D48: CT | E48: Commodities | F48: Futures | G48: =IF(F48="Futures",VLOOKUP(D48,Multiplier!B:I,8,0),0) -> 7 | H48: 5 | I48: {=SUM((Trades!V$2:V$9999)*(Trades!U$2:U$9999=Blotter!B48)*(Trades!$T$2:T$9999=Blotter!C48))} -> 0 | J48: =VLOOKUP(D48,Multiplier!B:D,2,0) -> 500 | K48: =L48-N48/(H48*J48) -> 87.46188 | L48: =IF(I48=0,IF(H48>0,X48,Y48),Z48) -> 86.75 | M48: =I48*J48*L48 -> 0 | N48: {=-SUM((Trades!T$2:T$9999=Blotter!C48)*(Trades!U$2:U$9999=Blotter!B48)*(Trades!V$2:V$9999)*(Trades!W$2:W$9999))*J48+SUM((Trades!T$2:T$9999=Blotter!C48)*(Trades!U$2:U$9999=Blotter!B48)*(Trades!X$2:X$9999))+(L48*I48)*J48} -> -1779.7 | O48: =VLOOKUP(D48,Multiplier!B:H,3,0) -> 3.01 | P48: 2 | R48: =(1-Q48)*P48*J48*H48 -> 5000 | S48: =IF(OR(F48="Futures",F48="Stocks"),IF(I48=0,0,IF(I48>0,L48-O48,L48+O48)),0) -> 0 | T48: =IF(S48>0,IF(ISNUMBER(S48/L48-1),S48/L48-1,0),0) -> 0 | U48: =IF(OR(F48="Futures",F48="Stocks"),IF(I48=0,0,IF(I48>0,K48-P48,K48+P48)),0) -> 0 | V48: =IF(U48>0,IF(ISNUMBER(U48/L48-1),U48/L48-1,0),0) -> 0 | X48: {=IF(ISNUMBER(SUM((Trades!T$2:T$9999=Blotter!C48)*(Trades!U$2:U$9999=Blotter!B48)*(Trades!W$2:W$9999)*(Trades!V$2:V$9999)*(Trades!V$2:V$9999<0))/SUM((Trades!T$2:T$9999=Blotter!C48)*(Trades!U$2:U$9999=Blotter!B48)*(Trades!V$2:V$9999)*(Trades!V$2:V$9999<0))),SUM((Trades!T$2:T$9999=Blotter!C48)*(Trades!U$2:U$9999=Blotter!B48)*(Trades!W$2:W$9999)*(Trades!V$2:V$9999)*(Trades!V$2:V$9999<0))/SUM((Trades!T$2:T$9999=Blotter!C48)*(Trades!U$2:U$9999=Blotter!B48)*(Trades!V$2:V$9999)*(Trades!V$2:V$9999<0)),0)} -> 86.75 | Y48: {=IF(ISNUMBER(SUM((Trades!T$2:T$9999=Blotter!C48)*(Trades!U$2:U$9999=Blotter!B48)*(Trades!W$2:W$9999)*(Trades!V$2:V$9999)*(Trades!V$2:V$9999>0))/SUM((Trades!T$2:T$9999=Blotter!C48)*(Trades!U$2:U$9999=Blotter!B48)*(Trades!V$2:V$9999)*(Trades!V$2:V$9999>0))),SUM((Trades!T$2:T$9999=Blotter!C48)*(Trades!U$2:U$9999=Blotter!B48)*(Trades!W$2:W$9999)*(Trades!V$2:V$9999)*(Trades!V$2:V$9999>0))/SUM((Trades!T$2:T$9999=Blotter!C48)*(Trades!U$2:U$9999=Blotter!B48)*(Trades!V$2:V$9999)*(Trades!V$2:V$9999>0)),0)} -> 87.45 | Z48: =IF(C$2="Last",IF(ISNUMBER(VLOOKUP(B48,Data_IB!B:O,14,0)),VLOOKUP(B48,Data_IB!B:O,14,0),0),IF(ISNUMBER(VLOOKUP(B48,Data_IB!B:O,13,0)),VLOOKUP(B48,Data_IB!B:O,13,0),0)) -> 0
B49: LOZ3 C9000 | C49: 27 | D49: CL | E49: Commodities | F49: Call | G49: =IF(F49="Futures",VLOOKUP(D49,Multiplier!B:I,8,0),0) -> 0 | H49: 10 | I49: {=SUM((Trades!V$2:V$9999)*(Trades!U$2:U$9999=Blotter!B49)*(Trades!$T$2:T$9999=Blotter!C49))} -> 0 | J49: =VLOOKUP(D49,Multiplier!B:D,2,0) -> 1000 | K49: =L49-N49/(H49*J49) -> 2.30474 | L49: =IF(I49=0,IF(H49>0,X49,Y49),Z49) -> 1.85 | M49: =I49*J49*L49 -> 0 | N49: {=-SUM((Trades!T$2:T$9999=Blotter!C49)*(Trades!U$2:U$9999=Blotter!B49)*(Trades!V$2:V$9999)*(Trades!W$2:W$9999))*J49+SUM((Trades!T$2:T$9999=Blotter!C49)*(Trades!U$2:U$9999=Blotter!B49)*(Trades!X$2:X$9999))+(L49*I49)*J49} -> -4547.4 | O49: =VLOOKUP(D49,Multiplier!B:H,3,0) -> 2.41 | P49: 2.3 | R49: =(1-Q49)*P49*J49*H49 -> 23000 | S49: =IF(OR(F49="Futures",F49="Stocks"),IF(I49=0,0,IF(I49>0,L49-O49,L49+O49)),0) -> 0 | T49: =IF(S49>0,IF(ISNUMBER(S49/L49-1),S49/L49-1,0),0) -> 0 | U49: =IF(OR(F49="Futures",F49="Stocks"),IF(I49=0,0,IF(I49>0,K49-P49,K49+P49)),0) -> 0 | V49: =IF(U49>0,IF(ISNUMBER(U49/L49-1),U49/L49-1,0),0) -> 0 | X49: {=IF(ISNUMBER(SUM((Trades!T$2:T$9999=Blotter!C49)*(Trades!U$2:U$9999=Blotter!B49)*(Trades!W$2:W$9999)*(Trades!V$2:V$9999)*(Trades!V$2:V$9999<0))/SUM((Trades!T$2:T$9999=Blotter!C49)*(Trades!U$2:U$9999=Blotter!B49)*(Trades!V$2:V$9999)*(Trades!V$2:V$9999<0))),SUM((Trades!T$2:T$9999=Blotter!C49)*(Trades!U$2:U$9999=Blotter!B49)*(Trades!W$2:W$9999)*(Trades!V$2:V$9999)*(Trades!V$2:V$9999<0))/SUM((Trades!T$2:T$9999=Blotter!C49)*(Trades!U$2:U$9999=Blotter!B49)*(Trades!V$2:V$9999)*(Trades!V$2:V$9999<0)),0)} -> 1.85 | Y49: {=IF(ISNUMBER(SUM((Trades!T$2:T$9999=Blotter!C49)*(Trades!U$2:U$9999=Blotter!B49)*(Trades!W$2:W$9999)*(Trades!V$2:V$9999)*(Trades!V$2:V$9999>0))/SUM((Trades!T$2:T$9999=Blotter!C49)*(Trades!U$2:U$9999=Blotter!B49)*(Trades!V$2:V$9999)*(Trades!V$2:V$9999>0))),SUM((Trades!T$2:T$9999=Blotter!C49)*(Trades!U$2:U$9999=Blotter!B49)*(Trades!W$2:W$9999)*(Trades!V$2:V$9999)*(Trades!V$2:V$9999>0))/SUM((Trades!T$2:T$9999=Blotter!C49)*(Trades!U$2:U$9999=Blotter!B49)*(Trades!V$2:V$9999)*(Trades!V$2:V$9999>0)),0)} -> 2.3 | Z49: =IF(C$2="Last",IF(ISNUMBER(VLOOKUP(B49,Data_IB!B:O,14,0)),VLOOKUP(B49,Data_IB!B:O,14,0),0),IF(ISNUMBER(VLOOKUP(B49,Data_IB!B:O,13,0)),VLOOKUP(B49,Data_IB!B:O,13,0),0)) -> 0
B50: LOZ3 C9500 | C50: 27 | D50: CL | E50: Commodities | F50: Call | G50: =IF(F50="Futures",VLOOKUP(D50,Multiplier!B:I,8,0),0) -> 0 | H50: -10 | I50: {=SUM((Trades!V$2:V$9999)*(Trades!U$2:U$9999=Blotter!B50)*(Trades!$T$2:T$9999=Blotter!C50))} -> 0 | J50: =VLOOKUP(D50,Multiplier!B:D,2,0) -> 1000 | K50: =L50-N50/(H50*J50) -> 1.49526 | L50: =IF(I50=0,IF(H50>0,X50,Y50),Z50) -> 0.049 | M50: =I50*J50*L50 -> 0 | N50: {=-SUM((Trades!T$2:T$9999=Blotter!C50)*(Trades!U$2:U$9999=Blotter!B50)*(Trades!V$2:V$9999)*(Trades!W$2:W$9999))*J50+SUM((Trades!T$2:T$9999=Blotter!C50)*(Trades!U$2:U$9999=Blotter!B50)*(Trades!X$2:X$9999))+(L50*I50)*J50} -> 14462.6 | O50: =VLOOKUP(D50,Multiplier!B:H,3,0) -> 2.41 | P50: 1.5 | R50: =(1-Q50)*P50*J50*H50 -> -15000 | S50: =IF(OR(F50="Futures",F50="Stocks"),IF(I50=0,0,IF(I50>0,L50-O50,L50+O50)),0) -> 0 | T50: =IF(S50>0,IF(ISNUMBER(S50/L50-1),S50/L50-1,0),0) -> 0 | U50: =IF(OR(F50="Futures",F50="Stocks"),IF(I50=0,0,IF(I50>0,K50-P50,K50+P50)),0) -> 0 | V50: =IF(U50>0,IF(ISNUMBER(U50/L50-1),U50/L50-1,0),0) -> 0 | X50: {=IF(ISNUMBER(SUM((Trades!T$2:T$9999=Blotter!C50)*(Trades!U$2:U$9999=Blotter!B50)*(Trades!W$2:W$9999)*(Trades!V$2:V$9999)*(Trades!V$2:V$9999<0))/SUM((Trades!T$2:T$9999=Blotter!C50)*(Trades!U$2:U$9999=Blotter!B50)*(Trades!V$2:V$9999)*(Trades!V$2:V$9999<0))),SUM((Trades!T$2:T$9999=Blotter!C50)*(Trades!U$2:U$9999=Blotter!B50)*(Trades!W$2:W$9999)*(Trades!V$2:V$9999)*(Trades!V$2:V$9999<0))/SUM((Trades!T$2:T$9999=Blotter!C50)*(Trades!U$2:U$9999=Blotter!B50)*(Trades!V$2:V$9999)*(Trades!V$2:V$9999<0)),0)} -> 1.5 | Y50: {=IF(ISNUMBER(SUM((Trades!T$2:T$9999=Blotter!C50)*(Trades!U$2:U$9999=Blotter!B50)*(Trades!W$2:W$9999)*(Trades!V$2:V$9999)*(Trades!V$2:V$9999>0))/SUM((Trades!T$2:T$9999=Blotter!C50)*(Trades!U$2:U$9999=Blotter!B50)*(Trades!V$2:V$9999)*(Trades!V$2:V$9999>0))),SUM((Trades!T$2:T$9999=Blotter!C50)*(Trades!U$2:U$9999=Blotter!B50)*(Trades!W$2:W$9999)*(Trades!V$2:V$9999)*(Trades!V$2:V$9999>0))/SUM((Trades!T$2:T$9999=Blotter!C50)*(Trades!U$2:U$9999=Blotter!B50)*(Trades!V$2:V$9999)*(Trades!V$2:V$9999>0)),0)} -> 0.049 | Z50: =IF(C$2="Last",IF(ISNUMBER(VLOOKUP(B50,Data_IB!B:O,14,0)),VLOOKUP(B50,Data_IB!B:O,14,0),0),IF(ISNUMBER(VLOOKUP(B50,Data_IB!B:O,13,0)),VLOOKUP(B50,Data_IB!B:O,13,0),0)) -> 0
B51: EWX3 P4200 | C51: 28 | D51: ES | E51: Equity | F51: Put | G51: =IF(F51="Futures",VLOOKUP(D51,Multiplier!B:I,8,0),0) -> 0 | H51: -10 | I51: {=SUM((Trades!V$2:V$9999)*(Trades!U$2:U$9999=Blotter!B51)*(Trades!$T$2:T$9999=Blotter!C51))} -> 0 | J51: =VLOOKUP(D51,Multiplier!B:D,2,0) -> 50 | K51: =L51-N51/(H51*J51) -> 85.1989 | L51: =IF(I51=0,IF(H51>0,X51,Y51),Z51) -> 56.6875 | M51: =I51*J51*L51 -> 0 | N51: {=-SUM((Trades!T$2:T$9999=Blotter!C51)*(Trades!U$2:U$9999=Blotter!B51)*(Trades!V$2:V$9999)*(Trades!W$2:W$9999))*J51+SUM((Trades!T$2:T$9999=Blotter!C51)*(Trades!U$2:U$9999=Blotter!B51)*(Trades!X$2:X$9999))+(L51*I51)*J51} -> 14255.7 | O51: =VLOOKUP(D51,Multiplier!B:H,3,0) -> 50.57 | P51: -10 | R51: =(1-Q51)*P51*J51*H51 -> 5000 | S51: =IF(OR(F51="Futures",F51="Stocks"),IF(I51=0,0,IF(I51>0,L51-O51,L51+O51)),0) -> 0 | T51: =IF(S51>0,IF(ISNUMBER(S51/L51-1),S51/L51-1,0),0) -> 0 | U51: =IF(OR(F51="Futures",F51="Stocks"),IF(I51=0,0,IF(I51>0,K51-P51,K51+P51)),0) -> 0 | V51: =IF(U51>0,IF(ISNUMBER(U51/L51-1),U51/L51-1,0),0) -> 0 | X51: {=IF(ISNUMBER(SUM((Trades!T$2:T$9999=Blotter!C51)*(Trades!U$2:U$9999=Blotter!B51)*(Trades!W$2:W$9999)*(Trades!V$2:V$9999)*(Trades!V$2:V$9999<0))/SUM((Trades!T$2:T$9999=Blotter!C51)*(Trades!U$2:U$9999=Blotter!B51)*(Trades!V$2:V$9999)*(Trades!V$2:V$9999<0))),SUM((Trades!T$2:T$9999=Blotter!C51)*(Trades!U$2:U$9999=Blotter!B51)*(Trades!W$2:W$9999)*(Trades!V$2:V$9999)*(Trades!V$2:V$9999<0))/SUM((Trades!T$2:T$9999=Blotter!C51)*(Trades!U$2:U$9999=Blotter!B51)*(Trades!V$2:V$9999)*(Trades!V$2:V$9999<0)),0)} -> 71 | Y51: {=IF(ISNUMBER(SUM((Trades!T$2:T$9999=Blotter!C51)*(Trades!U$2:U$9999=Blotter!B51)*(Trades!W$2:W$9999)*(Trades!V$2:V$9999)*(Trades!V$2:V$9999>0))/SUM((Trades!T$2:T$9999=Blotter!C51)*(Trades!U$2:U$9999=Blotter!B51)*(Trades!V$2:V$9999)*(Trades!V$2:V$9999>0))),SUM((Trades!T$2:T$9999=Blotter!C51)*(Trades!U$2:U$9999=Blotter!B51)*(Trades!W$2:W$9999)*(Trades!V$2:V$9999)*(Trades!V$2:V$9999>0))/SUM((Trades!T$2:T$9999=Blotter!C51)*(Trades!U$2:U$9999=Blotter!B51)*(Trades!V$2:V$9999)*(Trades!V$2:V$9999>0)),0)} -> 56.6875 | Z51: =IF(C$2="Last",IF(ISNUMBER(VLOOKUP(B51,Data_IB!B:O,14,0)),VLOOKUP(B51,Data_IB!B:O,14,0),0),IF(ISNUMBER(VLOOKUP(B51,Data_IB!B:O,13,0)),VLOOKUP(B51,Data_IB!B:O,13,0),0)) -> 0
B52: EWX3 C4400 | C52: 28 | D52: ES | E52: Equity | F52: Call | G52: =IF(F52="Futures",VLOOKUP(D52,Multiplier!B:I,8,0),0) -> 0 | H52: 10 | I52: {=SUM((Trades!V$2:V$9999)*(Trades!U$2:U$9999=Blotter!B52)*(Trades!$T$2:T$9999=Blotter!C52))} -> 0 | J52: =VLOOKUP(D52,Multiplier!B:D,2,0) -> 50 | K52: =L52-N52/(H52*J52) -> 81.8068 | L52: =IF(I52=0,IF(H52>0,X52,Y52),Z52) -> 28.75 | M52: =I52*J52*L52 -> 0 | N52: {=-SUM((Trades!T$2:T$9999=Blotter!C52)*(Trades!U$2:U$9999=Blotter!B52)*(Trades!V$2:V$9999)*(Trades!W$2:W$9999))*J52+SUM((Trades!T$2:T$9999=Blotter!C52)*(Trades!U$2:U$9999=Blotter!B52)*(Trades!X$2:X$9999))+(L52*I52)*J52} -> -26528.4 | O52: =VLOOKUP(D52,Multiplier!B:H,3,0) -> 50.57 | P52: 10 | R52: =(1-Q52)*P52*J52*H52 -> 5000 | S52: =IF(OR(F52="Futures",F52="Stocks"),IF(I52=0,0,IF(I52>0,L52-O52,L52+O52)),0) -> 0 | T52: =IF(S52>0,IF(ISNUMBER(S52/L52-1),S52/L52-1,0),0) -> 0 | U52: =IF(OR(F52="Futures",F52="Stocks"),IF(I52=0,0,IF(I52>0,K52-P52,K52+P52)),0) -> 0 | V52: =IF(U52>0,IF(ISNUMBER(U52/L52-1),U52/L52-1,0),0) -> 0 | X52: {=IF(ISNUMBER(SUM((Trades!T$2:T$9999=Blotter!C52)*(Trades!U$2:U$9999=Blotter!B52)*(Trades!W$2:W$9999)*(Trades!V$2:V$9999)*(Trades!V$2:V$9999<0))/SUM((Trades!T$2:T$9999=Blotter!C52)*(Trades!U$2:U$9999=Blotter!B52)*(Trades!V$2:V$9999)*(Trades!V$2:V$9999<0))),SUM((Trades!T$2:T$9999=Blotter!C52)*(Trades!U$2:U$9999=Blotter!B52)*(Trades!W$2:W$9999)*(Trades!V$2:V$9999)*(Trades!V$2:V$9999<0))/SUM((Trades!T$2:T$9999=Blotter!C52)*(Trades!U$2:U$9999=Blotter!B52)*(Trades!V$2:V$9999)*(Trades!V$2:V$9999<0)),0)} -> 28.75 | Y52: {=IF(ISNUMBER(SUM((Trades!T$2:T$9999=Blotter!C52)*(Trades!U$2:U$9999=Blotter!B52)*(Trades!W$2:W$9999)*(Trades!V$2:V$9999)*(Trades!V$2:V$9999>0))/SUM((Trades!T$2:T$9999=Blotter!C52)*(Trades!U$2:U$9999=Blotter!B52)*(Trades!V$2:V$9999)*(Trades!V$2:V$9999>0))),SUM((Trades!T$2:T$9999=Blotter!C52)*(Trades!U$2:U$9999=Blotter!B52)*(Trades!W$2:W$9999)*(Trades!V$2:V$9999)*(Trades!V$2:V$9999>0))/SUM((Trades!T$2:T$9999=Blotter!C52)*(Trades!U$2:U$9999=Blotter!B52)*(Trades!V$2:V$9999)*(Trades!V$2:V$9999>0)),0)} -> 81.75 | Z52: =IF(C$2="Last",IF(ISNUMBER(VLOOKUP(B52,Data_IB!B:O,14,0)),VLOOKUP(B52,Data_IB!B:O,14,0),0),IF(ISNUMBER(VLOOKUP(B52,Data_IB!B:O,13,0)),VLOOKUP(B52,Data_IB!B:O,13,0),0)) -> 0
B53: KOF4 C1.65 | C53: 28 | D53: KC | E53: Commodities | F53: Call | G53: =IF(F53="Futures",VLOOKUP(D53,Multiplier!B:I,8,0),0) -> 0 | H53: 15 | I53: {=SUM((Trades!V$2:V$9999)*(Trades!U$2:U$9999=Blotter!B53)*(Trades!$T$2:T$9999=Blotter!C53))} -> 0 | J53: =VLOOKUP(D53,Multiplier!B:D,2,0) -> 375 | K53: =L53-N53/(H53*J53) -> 3.31584 | L53: =IF(I53=0,IF(H53>0,X53,Y53),Z53) -> 14.5 | M53: =I53*J53*L53 -> 0 | N53: {=-SUM((Trades!T$2:T$9999=Blotter!C53)*(Trades!U$2:U$9999=Blotter!B53)*(Trades!V$2:V$9999)*(Trades!W$2:W$9999))*J53+SUM((Trades!T$2:T$9999=Blotter!C53)*(Trades!U$2:U$9999=Blotter!B53)*(Trades!X$2:X$9999))+(L53*I53)*J53} -> 62910.9 | O53: =VLOOKUP(D53,Multiplier!B:H,3,0) -> 5.38 | P53: 3.3 | R53: =(1-Q53)*P53*J53*H53 -> 18562.5 | S53: =IF(OR(F53="Futures",F53="Stocks"),IF(I53=0,0,IF(I53>0,L53-O53,L53+O53)),0) -> 0 | T53: =IF(S53>0,IF(ISNUMBER(S53/L53-1),S53/L53-1,0),0) -> 0 | U53: =IF(OR(F53="Futures",F53="Stocks"),IF(I53=0,0,IF(I53>0,K53-P53,K53+P53)),0) -> 0 | V53: =IF(U53>0,IF(ISNUMBER(U53/L53-1),U53/L53-1,0),0) -> 0 | X53: {=IF(ISNUMBER(SUM((Trades!T$2:T$9999=Blotter!C53)*(Trades!U$2:U$9999=Blotter!B53)*(Trades!W$2:W$9999)*(Trades!V$2:V$9999)*(Trades!V$2:V$9999<0))/SUM((Trades!T$2:T$9999=Blotter!C53)*(Trades!U$2:U$9999=Blotter!B53)*(Trades!V$2:V$9999)*(Trades!V$2:V$9999<0))),SUM((Trades!T$2:T$9999=Blotter!C53)*(Trades!U$2:U$9999=Blotter!B53)*(Trades!W$2:W$9999)*(Trades!V$2:V$9999)*(Trades!V$2:V$9999<0))/SUM((Trades!T$2:T$9999=Blotter!C53)*(Trades!U$2:U$9999=Blotter!B53)*(Trades!V$2:V$9999)*(Trades!V$2:V$9999<0)),0)} -> 14.5 | Y53: {=IF(ISNUMBER(SUM((Trades!T$2:T$9999=Blotter!C53)*(Trades!U$2:U$9999=Blotter!B53)*(Trades!W$2:W$9999)*(Trades!V$2:V$9999)*(Trades!V$2:V$9999>0))/SUM((Trades!T$2:T$9999=Blotter!C53)*(Trades!U$2:U$9999=Blotter!B53)*(Trades!V$2:V$9999)*(Trades!V$2:V$9999>0))),SUM((Trades!T$2:T$9999=Blotter!C53)*(Trades!U$2:U$9999=Blotter!B53)*(Trades!W$2:W$9999)*(Trades!V$2:V$9999)*(Trades!V$2:V$9999>0))/SUM((Trades!T$2:T$9999=Blotter!C53)*(Trades!U$2:U$9999=Blotter!B53)*(Trades!V$2:V$9999)*(Trades!V$2:V$9999>0)),0)} -> 3.3 | Z53: =IF(C$2="Last",IF(ISNUMBER(VLOOKUP(B53,Data_IB!B:O,14,0)),VLOOKUP(B53,Data_IB!B:O,14,0),0),IF(ISNUMBER(VLOOKUP(B53,Data_IB!B:O,13,0)),VLOOKUP(B53,Data_IB!B:O,13,0),0)) -> 0
... B63: SAVE | C63: 35 | D63: SAVE-S | E63: Equity | F63: Stocks | G63: =IF(F63="Futures",VLOOKUP(D63,Multiplier!B:I,8,0),0) -> 0 | H63: 1000 | I63: {=SUM((Trades!V$2:V$9999)*(Trades!U$2:U$9999=Blotter!B63)*(Trades!$T$2:T$9999=Blotter!C63))} -> 0 | J63: =VLOOKUP(D63,Multiplier!B:D,2,0) -> 1 | K63: =L63-N63/(H63*J63) -> 16.160275 | L63: =IF(I63=0,IF(H63>0,X63,Y63),Z63) -> 16.25 | M63: =I63*J63*L63 -> 0 | N63: {=-SUM((Trades!T$2:T$9999=Blotter!C63)*(Trades!U$2:U$9999=Blotter!B63)*(Trades!V$2:V$9999)*(Trades!W$2:W$9999))*J63+SUM((Trades!T$2:T$9999=Blotter!C63)*(Trades!U$2:U$9999=Blotter!B63)*(Trades!X$2:X$9999))+(L63*I63)*J63} -> 89.725 | O63: =VLOOKUP(D63,Multiplier!B:H,3,0) -> 1.06 | P63: 1.06 | R63: =(1-Q63)*P63*J63*H63 -> 1060 | S63: =IF(OR(F63="Futures",F63="Stocks"),IF(I63=0,0,IF(I63>0,L63-O63,L63+O63)),0) -> 0 | T63: =IF(S63>0,IF(ISNUMBER(S63/L63-1),S63/L63-1,0),0) -> 0 | U63: =IF(OR(F63="Futures",F63="Stocks"),IF(I63=0,0,IF(I63>0,K63-P63,K63+P63)),0) -> 0 | V63: =IF(U63>0,IF(ISNUMBER(U63/L63-1),U63/L63-1,0),0) -> 0 | X63: {=IF(ISNUMBER(SUM((Trades!T$2:T$9999=Blotter!C63)*(Trades!U$2:U$9999=Blotter!B63)*(Trades!W$2:W$9999)*(Trades!V$2:V$9999)*(Trades!V$2:V$9999<0))/SUM((Trades!T$2:T$9999=Blotter!C63)*(Trades!U$2:U$9999=Blotter!B63)*(Trades!V$2:V$9999)*(Trades!V$2:V$9999<0))),SUM((Trades!T$2:T$9999=Blotter!C63)*(Trades!U$2:U$9999=Blotter!B63)*(Trades!W$2:W$9999)*(Trades!V$2:V$9999)*(Trades!V$2:V$9999<0))/SUM((Trades!T$2:T$9999=Blotter!C63)*(Trades!U$2:U$9999=Blotter!B63)*(Trades!V$2:V$9999)*(Trades!V$2:V$9999<0)),0)} -> 16.25 | Y63: {=IF(ISNUMBER(SUM((Trades!T$2:T$9999=Blotter!C63)*(Trades!U$2:U$9999=Blotter!B63)*(Trades!W$2:W$9999)*(Trades!V$2:V$9999)*(Trades!V$2:V$9999>0))/SUM((Trades!T$2:T$9999=Blotter!C63)*(Trades!U$2:U$9999=Blotter!B63)*(Trades!V$2:V$9999)*(Trades!V$2:V$9999>0))),SUM((Trades!T$2:T$9999=Blotter!C63)*(Trades!U$2:U$9999=Blotter!B63)*(Trades!W$2:W$9999)*(Trades!V$2:V$9999)*(Trades!V$2:V$9999>0))/SUM((Trades!T$2:T$9999=Blotter!C63)*(Trades!U$2:U$9999=Blotter!B63)*(Trades!V$2:V$9999)*(Trades!V$2:V$9999>0)),0)} -> 16.15 | Z63: =IF(C$2="Last",IF(ISNUMBER(VLOOKUP(B63,Data_IB!B:O,14,0)),VLOOKUP(B63,Data_IB!B:O,14,0),0),IF(ISNUMBER(VLOOKUP(B63,Data_IB!B:O,13,0)),VLOOKUP(B63,Data_IB!B:O,13,0),0)) -> 0
B64: NGG4 | C64: 36 | D64: NG | E64: Commodities | F64: Futures | G64: =IF(F64="Futures",VLOOKUP(D64,Multiplier!B:I,8,0),0) -> 8 | H64: 12 | I64: {=SUM((Trades!V$2:V$9999)*(Trades!U$2:U$9999=Blotter!B64)*(Trades!$T$2:T$9999=Blotter!C64))} -> 0 | J64: =VLOOKUP(D64,Multiplier!B:D,2,0) -> 10000 | K64: =L64-N64/(H64*J64) -> 2.384974 | L64: =IF(I64=0,IF(H64>0,X64,Y64),Z64) -> 2.7475 | M64: =I64*J64*L64 -> 0 | N64: {=-SUM((Trades!T$2:T$9999=Blotter!C64)*(Trades!U$2:U$9999=Blotter!B64)*(Trades!V$2:V$9999)*(Trades!W$2:W$9999))*J64+SUM((Trades!T$2:T$9999=Blotter!C64)*(Trades!U$2:U$9999=Blotter!B64)*(Trades!X$2:X$9999))+(L64*I64)*J64} -> 43503.12 | O64: =VLOOKUP(D64,Multiplier!B:H,3,0) -> 0.132 | P64: 0.156 | Q64: 1 | R64: =(1-Q64)*P64*J64*H64 -> 0 | S64: =IF(OR(F64="Futures",F64="Stocks"),IF(I64=0,0,IF(I64>0,L64-O64,L64+O64)),0) -> 0 | T64: =IF(S64>0,IF(ISNUMBER(S64/L64-1),S64/L64-1,0),0) -> 0 | U64: =IF(OR(F64="Futures",F64="Stocks"),IF(I64=0,0,IF(I64>0,K64-P64,K64+P64)),0) -> 0 | V64: =IF(U64>0,IF(ISNUMBER(U64/L64-1),U64/L64-1,0),0) -> 0 | X64: {=IF(ISNUMBER(SUM((Trades!T$2:T$9999=Blotter!C64)*(Trades!U$2:U$9999=Blotter!B64)*(Trades!W$2:W$9999)*(Trades!V$2:V$9999)*(Trades!V$2:V$9999<0))/SUM((Trades!T$2:T$9999=Blotter!C64)*(Trades!U$2:U$9999=Blotter!B64)*(Trades!V$2:V$9999)*(Trades!V$2:V$9999<0))),SUM((Trades!T$2:T$9999=Blotter!C64)*(Trades!U$2:U$9999=Blotter!B64)*(Trades!W$2:W$9999)*(Trades!V$2:V$9999)*(Trades!V$2:V$9999<0))/SUM((Trades!T$2:T$9999=Blotter!C64)*(Trades!U$2:U$9999=Blotter!B64)*(Trades!V$2:V$9999)*(Trades!V$2:V$9999<0)),0)} -> 2.7475 | Y64: {=IF(ISNUMBER(SUM((Trades!T$2:T$9999=Blotter!C64)*(Trades!U$2:U$9999=Blotter!B64)*(Trades!W$2:W$9999)*(Trades!V$2:V$9999)*(Trades!V$2:V$9999>0))/SUM((Trades!T$2:T$9999=Blotter!C64)*(Trades!U$2:U$9999=Blotter!B64)*(Trades!V$2:V$9999)*(Trades!V$2:V$9999>0))),SUM((Trades!T$2:T$9999=Blotter!C64)*(Trades!U$2:U$9999=Blotter!B64)*(Trades!W$2:W$9999)*(Trades!V$2:V$9999)*(Trades!V$2:V$9999>0))/SUM((Trades!T$2:T$9999=Blotter!C64)*(Trades!U$2:U$9999=Blotter!B64)*(Trades!V$2:V$9999)*(Trades!V$2:V$9999>0)),0)} -> 2.3845 | Z64: =IF(C$2="Last",IF(ISNUMBER(VLOOKUP(B64,Data_IB!B:O,14,0)),VLOOKUP(B64,Data_IB!B:O,14,0),0),IF(ISNUMBER(VLOOKUP(B64,Data_IB!B:O,13,0)),VLOOKUP(B64,Data_IB!B:O,13,0),0)) -> 0
B65: NGH4 | C65: 36 | D65: NG | E65: Commodities | F65: Futures | G65: =IF(F65="Futures",VLOOKUP(D65,Multiplier!B:I,8,0),0) -> 8 | H65: 12 | I65: {=SUM((Trades!V$2:V$9999)*(Trades!U$2:U$9999=Blotter!B65)*(Trades!$T$2:T$9999=Blotter!C65))} -> 0 | J65: =VLOOKUP(D65,Multiplier!B:D,2,0) -> 10000 | K65: =L65-N65/(H65*J65) -> 2.093498 | L65: =IF(I65=0,IF(H65>0,X65,Y65),Z65) -> 2.115 | M65: =I65*J65*L65 -> 0 | N65: {=-SUM((Trades!T$2:T$9999=Blotter!C65)*(Trades!U$2:U$9999=Blotter!B65)*(Trades!V$2:V$9999)*(Trades!W$2:W$9999))*J65+SUM((Trades!T$2:T$9999=Blotter!C65)*(Trades!U$2:U$9999=Blotter!B65)*(Trades!X$2:X$9999))+(L65*I65)*J65} -> 2580.24 | O65: =VLOOKUP(D65,Multiplier!B:H,3,0) -> 0.132 | P65: 0.156 | R65: =(1-Q65)*P65*J65*H65 -> 18720 | S65: =IF(OR(F65="Futures",F65="Stocks"),IF(I65=0,0,IF(I65>0,L65-O65,L65+O65)),0) -> 0 | T65: =IF(S65>0,IF(ISNUMBER(S65/L65-1),S65/L65-1,0),0) -> 0 | U65: =IF(OR(F65="Futures",F65="Stocks"),IF(I65=0,0,IF(I65>0,K65-P65,K65+P65)),0) -> 0 | V65: =IF(U65>0,IF(ISNUMBER(U65/L65-1),U65/L65-1,0),0) -> 0 | X65: {=IF(ISNUMBER(SUM((Trades!T$2:T$9999=Blotter!C65)*(Trades!U$2:U$9999=Blotter!B65)*(Trades!W$2:W$9999)*(Trades!V$2:V$9999)*(Trades!V$2:V$9999<0))/SUM((Trades!T$2:T$9999=Blotter!C65)*(Trades!U$2:U$9999=Blotter!B65)*(Trades!V$2:V$9999)*(Trades!V$2:V$9999<0))),SUM((Trades!T$2:T$9999=Blotter!C65)*(Trades!U$2:U$9999=Blotter!B65)*(Trades!W$2:W$9999)*(Trades!V$2:V$9999)*(Trades!V$2:V$9999<0))/SUM((Trades!T$2:T$9999=Blotter!C65)*(Trades!U$2:U$9999=Blotter!B65)*(Trades!V$2:V$9999)*(Trades!V$2:V$9999<0)),0)} -> 2.115 | Y65: {=IF(ISNUMBER(SUM((Trades!T$2:T$9999=Blotter!C65)*(Trades!U$2:U$9999=Blotter!B65)*(Trades!W$2:W$9999)*(Trades!V$2:V$9999)*(Trades!V$2:V$9999>0))/SUM((Trades!T$2:T$9999=Blotter!C65)*(Trades!U$2:U$9999=Blotter!B65)*(Trades!V$2:V$9999)*(Trades!V$2:V$9999>0))),SUM((Trades!T$2:T$9999=Blotter!C65)*(Trades!U$2:U$9999=Blotter!B65)*(Trades!W$2:W$9999)*(Trades!V$2:V$9999)*(Trades!V$2:V$9999>0))/SUM((Trades!T$2:T$9999=Blotter!C65)*(Trades!U$2:U$9999=Blotter!B65)*(Trades!V$2:V$9999)*(Trades!V$2:V$9999>0)),0)} -> 2.05 | Z65: =IF(C$2="Last",IF(ISNUMBER(VLOOKUP(B65,Data_IB!B:O,14,0)),VLOOKUP(B65,Data_IB!B:O,14,0),0),IF(ISNUMBER(VLOOKUP(B65,Data_IB!B:O,13,0)),VLOOKUP(B65,Data_IB!B:O,13,0),0)) -> 0
B66: HGH4 | C66: 37 | D66: HG | E66: Commodities | F66: Futures | G66: =IF(F66="Futures",VLOOKUP(D66,Multiplier!B:I,8,0),0) -> 6 | H66: 5 | I66: {=SUM((Trades!V$2:V$9999)*(Trades!U$2:U$9999=Blotter!B66)*(Trades!$T$2:T$9999=Blotter!C66))} -> 0 | J66: =VLOOKUP(D66,Multiplier!B:D,2,0) -> 25000 | K66: =L66-N66/(H66*J66) -> 3.5887603 | L66: =IF(I66=0,IF(H66>0,X66,Y66),Z66) -> 3.8314516 | M66: =I66*J66*L66 -> 0 | N66: {=-SUM((Trades!T$2:T$9999=Blotter!C66)*(Trades!U$2:U$9999=Blotter!B66)*(Trades!V$2:V$9999)*(Trades!W$2:W$9999))*J66+SUM((Trades!T$2:T$9999=Blotter!C66)*(Trades!U$2:U$9999=Blotter!B66)*(Trades!X$2:X$9999))+(L66*I66)*J66} -> 30336.42 | O66: =VLOOKUP(D66,Multiplier!B:H,3,0) -> 0.0708 | P66: 0.0708 | R66: =(1-Q66)*P66*J66*H66 -> 8850 | S66: =IF(OR(F66="Futures",F66="Stocks"),IF(I66=0,0,IF(I66>0,L66-O66,L66+O66)),0) -> 0 | T66: =IF(S66>0,IF(ISNUMBER(S66/L66-1),S66/L66-1,0),0) -> 0 | U66: =IF(OR(F66="Futures",F66="Stocks"),IF(I66=0,0,IF(I66>0,K66-P66,K66+P66)),0) -> 0 | V66: =IF(U66>0,IF(ISNUMBER(U66/L66-1),U66/L66-1,0),0) -> 0 | X66: {=IF(ISNUMBER(SUM((Trades!T$2:T$9999=Blotter!C66)*(Trades!U$2:U$9999=Blotter!B66)*(Trades!W$2:W$9999)*(Trades!V$2:V$9999)*(Trades!V$2:V$9999<0))/SUM((Trades!T$2:T$9999=Blotter!C66)*(Trades!U$2:U$9999=Blotter!B66)*(Trades!V$2:V$9999)*(Trades!V$2:V$9999<0))),SUM((Trades!T$2:T$9999=Blotter!C66)*(Trades!U$2:U$9999=Blotter!B66)*(Trades!W$2:W$9999)*(Trades!V$2:V$9999)*(Trades!V$2:V$9999<0))/SUM((Trades!T$2:T$9999=Blotter!C66)*(Trades!U$2:U$9999=Blotter!B66)*(Trades!V$2:V$9999)*(Trades!V$2:V$9999<0)),0)} -> 3.8314516 | Y66: {=IF(ISNUMBER(SUM((Trades!T$2:T$9999=Blotter!C66)*(Trades!U$2:U$9999=Blotter!B66)*(Trades!W$2:W$9999)*(Trades!V$2:V$9999)*(Trades!V$2:V$9999>0))/SUM((Trades!T$2:T$9999=Blotter!C66)*(Trades!U$2:U$9999=Blotter!B66)*(Trades!V$2:V$9999)*(Trades!V$2:V$9999>0))),SUM((Trades!T$2:T$9999=Blotter!C66)*(Trades!U$2:U$9999=Blotter!B66)*(Trades!W$2:W$9999)*(Trades!V$2:V$9999)*(Trades!V$2:V$9999>0))/SUM((Trades!T$2:T$9999=Blotter!C66)*(Trades!U$2:U$9999=Blotter!B66)*(Trades!V$2:V$9999)*(Trades!V$2:V$9999>0)),0)} -> 3.8116855 | Z66: =IF(C$2="Last",IF(ISNUMBER(VLOOKUP(B66,Data_IB!B:O,14,0)),VLOOKUP(B66,Data_IB!B:O,14,0),0),IF(ISNUMBER(VLOOKUP(B66,Data_IB!B:O,13,0)),VLOOKUP(B66,Data_IB!B:O,13,0),0)) -> 0
B67: HGK4 | C67: 37 | D67: HG | E67: Commodities | F67: Futures | G67: =IF(F67="Futures",VLOOKUP(D67,Multiplier!B:I,8,0),0) -> 6 | H67: 5 | I67: {=SUM((Trades!V$2:V$9999)*(Trades!U$2:U$9999=Blotter!B67)*(Trades!$T$2:T$9999=Blotter!C67))} -> 0 | J67: =VLOOKUP(D67,Multiplier!B:D,2,0) -> 25000 | K67: =L67-N67/(H67*J67) -> 3.8846976 | L67: =IF(I67=0,IF(H67>0,X67,Y67),Z67) -> 3.89 | M67: =I67*J67*L67 -> 0 | N67: {=-SUM((Trades!T$2:T$9999=Blotter!C67)*(Trades!U$2:U$9999=Blotter!B67)*(Trades!V$2:V$9999)*(Trades!W$2:W$9999))*J67+SUM((Trades!T$2:T$9999=Blotter!C67)*(Trades!U$2:U$9999=Blotter!B67)*(Trades!X$2:X$9999))+(L67*I67)*J67} -> 662.8 | O67: =VLOOKUP(D67,Multiplier!B:H,3,0) -> 0.0708 | P67: 0.0708 | R67: =(1-Q67)*P67*J67*H67 -> 8850 | S67: =IF(OR(F67="Futures",F67="Stocks"),IF(I67=0,0,IF(I67>0,L67-O67,L67+O67)),0) -> 0 | T67: =IF(S67>0,IF(ISNUMBER(S67/L67-1),S67/L67-1,0),0) -> 0 | U67: =IF(OR(F67="Futures",F67="Stocks"),IF(I67=0,0,IF(I67>0,K67-P67,K67+P67)),0) -> 0 | V67: =IF(U67>0,IF(ISNUMBER(U67/L67-1),U67/L67-1,0),0) -> 0 | X67: {=IF(ISNUMBER(SUM((Trades!T$2:T$9999=Blotter!C67)*(Trades!U$2:U$9999=Blotter!B67)*(Trades!W$2:W$9999)*(Trades!V$2:V$9999)*(Trades!V$2:V$9999<0))/SUM((Trades!T$2:T$9999=Blotter!C67)*(Trades!U$2:U$9999=Blotter!B67)*(Trades!V$2:V$9999)*(Trades!V$2:V$9999<0))),SUM((Trades!T$2:T$9999=Blotter!C67)*(Trades!U$2:U$9999=Blotter!B67)*(Trades!W$2:W$9999)*(Trades!V$2:V$9999)*(Trades!V$2:V$9999<0))/SUM((Trades!T$2:T$9999=Blotter!C67)*(Trades!U$2:U$9999=Blotter!B67)*(Trades!V$2:V$9999)*(Trades!V$2:V$9999<0)),0)} -> 3.89 | Y67: {=IF(ISNUMBER(SUM((Trades!T$2:T$9999=Blotter!C67)*(Trades!U$2:U$9999=Blotter!B67)*(Trades!W$2:W$9999)*(Trades!V$2:V$9999)*(Trades!V$2:V$9999>0))/SUM((Trades!T$2:T$9999=Blotter!C67)*(Trades!U$2:U$9999=Blotter!B67)*(Trades!V$2:V$9999)*(Trades!V$2:V$9999>0))),SUM((Trades!T$2:T$9999=Blotter!C67)*(Trades!U$2:U$9999=Blotter!B67)*(Trades!W$2:W$9999)*(Trades!V$2:V$9999)*(Trades!V$2:V$9999>0))/SUM((Trades!T$2:T$9999=Blotter!C67)*(Trades!U$2:U$9999=Blotter!B67)*(Trades!V$2:V$9999)*(Trades!V$2:V$9999>0)),0)} -> 3.8845 | Z67: =IF(C$2="Last",IF(ISNUMBER(VLOOKUP(B67,Data_IB!B:O,14,0)),VLOOKUP(B67,Data_IB!B:O,14,0),0),IF(ISNUMBER(VLOOKUP(B67,Data_IB!B:O,13,0)),VLOOKUP(B67,Data_IB!B:O,13,0),0)) -> 0
B68: CYTK | C68: 40 | D68: CYTK-S | E68: Equity | F68: Stocks | G68: =IF(F68="Futures",VLOOKUP(D68,Multiplier!B:I,8,0),0) -> 0 | H68: 3000 | I68: {=SUM((Trades!V$2:V$9999)*(Trades!U$2:U$9999=Blotter!B68)*(Trades!$T$2:T$9999=Blotter!C68))} -> 4000 | J68: =VLOOKUP(D68,Multiplier!B:D,2,0) -> 1 | K68: =L68-N68/(H68*J68) -> 101.43422 | L68: =IF(I68=0,IF(H68>0,X68,Y68),Z68) -> 0 | M68: =I68*J68*L68 -> 0 | N68: {=-SUM((Trades!T$2:T$9999=Blotter!C68)*(Trades!U$2:U$9999=Blotter!B68)*(Trades!V$2:V$9999)*(Trades!W$2:W$9999))*J68+SUM((Trades!T$2:T$9999=Blotter!C68)*(Trades!U$2:U$9999=Blotter!B68)*(Trades!X$2:X$9999))+(L68*I68)*J68} -> -304302.67 | O68: =VLOOKUP(D68,Multiplier!B:H,3,0) -> 7.23 | P68: 7.23 | R68: =(1-Q68)*P68*J68*H68 -> 21690 | S68: =IF(OR(F68="Futures",F68="Stocks"),IF(I68=0,0,IF(I68>0,L68-O68,L68+O68)),0) -> -7.23 | T68: =IF(S68>0,IF(ISNUMBER(S68/L68-1),S68/L68-1,0),0) -> 0 | U68: =IF(OR(F68="Futures",F68="Stocks"),IF(I68=0,0,IF(I68>0,K68-P68,K68+P68)),0) -> 94.204224 | V68: =IF(U68>0,IF(ISNUMBER(U68/L68-1),U68/L68-1,0),0) -> 0 | X68: {=IF(ISNUMBER(SUM((Trades!T$2:T$9999=Blotter!C68)*(Trades!U$2:U$9999=Blotter!B68)*(Trades!W$2:W$9999)*(Trades!V$2:V$9999)*(Trades!V$2:V$9999<0))/SUM((Trades!T$2:T$9999=Blotter!C68)*(Trades!U$2:U$9999=Blotter!B68)*(Trades!V$2:V$9999)*(Trades!V$2:V$9999<0))),SUM((Trades!T$2:T$9999=Blotter!C68)*(Trades!U$2:U$9999=Blotter!B68)*(Trades!W$2:W$9999)*(Trades!V$2:V$9999)*(Trades!V$2:V$9999<0))/SUM((Trades!T$2:T$9999=Blotter!C68)*(Trades!U$2:U$9999=Blotter!B68)*(Trades!V$2:V$9999)*(Trades!V$2:V$9999<0)),0)} -> 70.14 | Y68: {=IF(ISNUMBER(SUM((Trades!T$2:T$9999=Blotter!C68)*(Trades!U$2:U$9999=Blotter!B68)*(Trades!W$2:W$9999)*(Trades!V$2:V$9999)*(Trades!V$2:V$9999>0))/SUM((Trades!T$2:T$9999=Blotter!C68)*(Trades!U$2:U$9999=Blotter!B68)*(Trades!V$2:V$9999)*(Trades!V$2:V$9999>0))),SUM((Trades!T$2:T$9999=Blotter!C68)*(Trades!U$2:U$9999=Blotter!B68)*(Trades!W$2:W$9999)*(Trades!V$2:V$9999)*(Trades!V$2:V$9999>0))/SUM((Trades!T$2:T$9999=Blotter!C68)*(Trades!U$2:U$9999=Blotter!B68)*(Trades!V$2:V$9999)*(Trades!V$2:V$9999>0)),0)} -> 73.785515 | Z68: =IF(C$2="Last",IF(ISNUMBER(VLOOKUP(B68,Data_IB!B:O,14,0)),VLOOKUP(B68,Data_IB!B:O,14,0),0),IF(ISNUMBER(VLOOKUP(B68,Data_IB!B:O,13,0)),VLOOKUP(B68,Data_IB!B:O,13,0),0)) -> 0
B69: CLG4 | C69: 41 | D69: CL | E69: Commodities | F69: Futures | G69: =IF(F69="Futures",VLOOKUP(D69,Multiplier!B:I,8,0),0) -> 4 | H69: 4 | I69: {=SUM((Trades!V$2:V$9999)*(Trades!U$2:U$9999=Blotter!B69)*(Trades!$T$2:T$9999=Blotter!C69))} -> 0 | J69: =VLOOKUP(D69,Multiplier!B:D,2,0) -> 1000 | K69: =L69-N69/(H69*J69) -> 71.94474 | L69: =IF(I69=0,IF(H69>0,X69,Y69),Z69) -> 72 | M69: =I69*J69*L69 -> 0 | N69: {=-SUM((Trades!T$2:T$9999=Blotter!C69)*(Trades!U$2:U$9999=Blotter!B69)*(Trades!V$2:V$9999)*(Trades!W$2:W$9999))*J69+SUM((Trades!T$2:T$9999=Blotter!C69)*(Trades!U$2:U$9999=Blotter!B69)*(Trades!X$2:X$9999))+(L69*I69)*J69} -> 221.04 | O69: =VLOOKUP(D69,Multiplier!B:H,3,0) -> 2.41 | P69: 2.6 | Q69: 1 | R69: =(1-Q69)*P69*J69*H69 -> 0 | S69: =IF(OR(F69="Futures",F69="Stocks"),IF(I69=0,0,IF(I69>0,L69-O69,L69+O69)),0) -> 0 | T69: =IF(S69>0,IF(ISNUMBER(S69/L69-1),S69/L69-1,0),0) -> 0 | U69: =IF(OR(F69="Futures",F69="Stocks"),IF(I69=0,0,IF(I69>0,K69-P69,K69+P69)),0) -> 0 | V69: =IF(U69>0,IF(ISNUMBER(U69/L69-1),U69/L69-1,0),0) -> 0 | X69: {=IF(ISNUMBER(SUM((Trades!T$2:T$9999=Blotter!C69)*(Trades!U$2:U$9999=Blotter!B69)*(Trades!W$2:W$9999)*(Trades!V$2:V$9999)*(Trades!V$2:V$9999<0))/SUM((Trades!T$2:T$9999=Blotter!C69)*(Trades!U$2:U$9999=Blotter!B69)*(Trades!V$2:V$9999)*(Trades!V$2:V$9999<0))),SUM((Trades!T$2:T$9999=Blotter!C69)*(Trades!U$2:U$9999=Blotter!B69)*(Trades!W$2:W$9999)*(Trades!V$2:V$9999)*(Trades!V$2:V$9999<0))/SUM((Trades!T$2:T$9999=Blotter!C69)*(Trades!U$2:U$9999=Blotter!B69)*(Trades!V$2:V$9999)*(Trades!V$2:V$9999<0)),0)} -> 72 | Y69: {=IF(ISNUMBER(SUM((Trades!T$2:T$9999=Blotter!C69)*(Trades!U$2:U$9999=Blotter!B69)*(Trades!W$2:W$9999)*(Trades!V$2:V$9999)*(Trades!V$2:V$9999>0))/SUM((Trades!T$2:T$9999=Blotter!C69)*(Trades!U$2:U$9999=Blotter!B69)*(Trades!V$2:V$9999)*(Trades!V$2:V$9999>0))),SUM((Trades!T$2:T$9999=Blotter!C69)*(Trades!U$2:U$9999=Blotter!B69)*(Trades!W$2:W$9999)*(Trades!V$2:V$9999)*(Trades!V$2:V$9999>0))/SUM((Trades!T$2:T$9999=Blotter!C69)*(Trades!U$2:U$9999=Blotter!B69)*(Trades!V$2:V$9999)*(Trades!V$2:V$9999>0)),0)} -> 71.94 | Z69: =IF(C$2="Last",IF(ISNUMBER(VLOOKUP(B69,Data_IB!B:O,14,0)),VLOOKUP(B69,Data_IB!B:O,14,0),0),IF(ISNUMBER(VLOOKUP(B69,Data_IB!B:O,13,0)),VLOOKUP(B69,Data_IB!B:O,13,0),0)) -> 0
B70: CLH4 | C70: 41 | D70: CL | E70: Commodities | F70: Futures | G70: =IF(F70="Futures",VLOOKUP(D70,Multiplier!B:I,8,0),0) -> 4 | H70: 5 | I70: {=SUM((Trades!V$2:V$9999)*(Trades!U$2:U$9999=Blotter!B70)*(Trades!$T$2:T$9999=Blotter!C70))} -> 0 | J70: =VLOOKUP(D70,Multiplier!B:D,2,0) -> 1000 | K70: =L70-N70/(H70*J70) -> 73.97074 | L70: =IF(I70=0,IF(H70>0,X70,Y70),Z70) -> 73.996 | M70: =I70*J70*L70 -> 0 | N70: {=-SUM((Trades!T$2:T$9999=Blotter!C70)*(Trades!U$2:U$9999=Blotter!B70)*(Trades!V$2:V$9999)*(Trades!W$2:W$9999))*J70+SUM((Trades!T$2:T$9999=Blotter!C70)*(Trades!U$2:U$9999=Blotter!B70)*(Trades!X$2:X$9999))+(L70*I70)*J70} -> 126.3 | O70: =VLOOKUP(D70,Multiplier!B:H,3,0) -> 2.41 | P70: 2.6 | R70: =(1-Q70)*P70*J70*H70 -> 13000 | S70: =IF(OR(F70="Futures",F70="Stocks"),IF(I70=0,0,IF(I70>0,L70-O70,L70+O70)),0) -> 0 | T70: =IF(S70>0,IF(ISNUMBER(S70/L70-1),S70/L70-1,0),0) -> 0 | U70: =IF(OR(F70="Futures",F70="Stocks"),IF(I70=0,0,IF(I70>0,K70-P70,K70+P70)),0) -> 0 | V70: =IF(U70>0,IF(ISNUMBER(U70/L70-1),U70/L70-1,0),0) -> 0 | X70: {=IF(ISNUMBER(SUM((Trades!T$2:T$9999=Blotter!C70)*(Trades!U$2:U$9999=Blotter!B70)*(Trades!W$2:W$9999)*(Trades!V$2:V$9999)*(Trades!V$2:V$9999<0))/SUM((Trades!T$2:T$9999=Blotter!C70)*(Trades!U$2:U$9999=Blotter!B70)*(Trades!V$2:V$9999)*(Trades!V$2:V$9999<0))),SUM((Trades!T$2:T$9999=Blotter!C70)*(Trades!U$2:U$9999=Blotter!B70)*(Trades!W$2:W$9999)*(Trades!V$2:V$9999)*(Trades!V$2:V$9999<0))/SUM((Trades!T$2:T$9999=Blotter!C70)*(Trades!U$2:U$9999=Blotter!B70)*(Trades!V$2:V$9999)*(Trades!V$2:V$9999<0)),0)} -> 73.996 | Y70: {=IF(ISNUMBER(SUM((Trades!T$2:T$9999=Blotter!C70)*(Trades!U$2:U$9999=Blotter!B70)*(Trades!W$2:W$9999)*(Trades!V$2:V$9999)*(Trades!V$2:V$9999>0))/SUM((Trades!T$2:T$9999=Blotter!C70)*(Trades!U$2:U$9999=Blotter!B70)*(Trades!V$2:V$9999)*(Trades!V$2:V$9999>0))),SUM((Trades!T$2:T$9999=Blotter!C70)*(Trades!U$2:U$9999=Blotter!B70)*(Trades!W$2:W$9999)*(Trades!V$2:V$9999)*(Trades!V$2:V$9999>0))/SUM((Trades!T$2:T$9999=Blotter!C70)*(Trades!U$2:U$9999=Blotter!B70)*(Trades!V$2:V$9999)*(Trades!V$2:V$9999>0)),0)} -> 73.966 | Z70: =IF(C$2="Last",IF(ISNUMBER(VLOOKUP(B70,Data_IB!B:O,14,0)),VLOOKUP(B70,Data_IB!B:O,14,0),0),IF(ISNUMBER(VLOOKUP(B70,Data_IB!B:O,13,0)),VLOOKUP(B70,Data_IB!B:O,13,0),0)) -> 0
B71: ZWH4 | C71: 43 | D71: ZW | E71: Commodities | F71: Futures | G71: =IF(F71="Futures",VLOOKUP(D71,Multiplier!B:I,8,0),0) -> 12 | H71: 20 | I71: {=SUM((Trades!V$2:V$9999)*(Trades!U$2:U$9999=Blotter!B71)*(Trades!$T$2:T$9999=Blotter!C71))} -> 0 | J71: =VLOOKUP(D71,Multiplier!B:D,2,0) -> 50 | K71: =L71-N71/(H71*J71) -> 595.63425 | L71: =IF(I71=0,IF(H71>0,X71,Y71),Z71) -> 592.69231 | M71: =I71*J71*L71 -> 0 | N71: {=-SUM((Trades!T$2:T$9999=Blotter!C71)*(Trades!U$2:U$9999=Blotter!B71)*(Trades!V$2:V$9999)*(Trades!W$2:W$9999))*J71+SUM((Trades!T$2:T$9999=Blotter!C71)*(Trades!U$2:U$9999=Blotter!B71)*(Trades!X$2:X$9999))+(L71*I71)*J71} -> -2941.94 | O71: =VLOOKUP(D71,Multiplier!B:H,3,0) -> 17.25 | P71: 18 | Q71: 1 | R71: =(1-Q71)*P71*J71*H71 -> 0 | S71: =IF(OR(F71="Futures",F71="Stocks"),IF(I71=0,0,IF(I71>0,L71-O71,L71+O71)),0) -> 0 | T71: =IF(S71>0,IF(ISNUMBER(S71/L71-1),S71/L71-1,0),0) -> 0 | U71: =IF(OR(F71="Futures",F71="Stocks"),IF(I71=0,0,IF(I71>0,K71-P71,K71+P71)),0) -> 0 | V71: =IF(U71>0,IF(ISNUMBER(U71/L71-1),U71/L71-1,0),0) -> 0 | X71: {=IF(ISNUMBER(SUM((Trades!T$2:T$9999=Blotter!C71)*(Trades!U$2:U$9999=Blotter!B71)*(Trades!W$2:W$9999)*(Trades!V$2:V$9999)*(Trades!V$2:V$9999<0))/SUM((Trades!T$2:T$9999=Blotter!C71)*(Trades!U$2:U$9999=Blotter!B71)*(Trades!V$2:V$9999)*(Trades!V$2:V$9999<0))),SUM((Trades!T$2:T$9999=Blotter!C71)*(Trades!U$2:U$9999=Blotter!B71)*(Trades!W$2:W$9999)*(Trades!V$2:V$9999)*(Trades!V$2:V$9999<0))/SUM((Trades!T$2:T$9999=Blotter!C71)*(Trades!U$2:U$9999=Blotter!B71)*(Trades!V$2:V$9999)*(Trades!V$2:V$9999<0)),0)} -> 592.69231 | Y71: {=IF(ISNUMBER(SUM((Trades!T$2:T$9999=Blotter!C71)*(Trades!U$2:U$9999=Blotter!B71)*(Trades!W$2:W$9999)*(Trades!V$2:V$9999)*(Trades!V$2:V$9999>0))/SUM((Trades!T$2:T$9999=Blotter!C71)*(Trades!U$2:U$9999=Blotter!B71)*(Trades!V$2:V$9999)*(Trades!V$2:V$9999>0))),SUM((Trades!T$2:T$9999=Blotter!C71)*(Trades!U$2:U$9999=Blotter!B71)*(Trades!W$2:W$9999)*(Trades!V$2:V$9999)*(Trades!V$2:V$9999>0))/SUM((Trades!T$2:T$9999=Blotter!C71)*(Trades!U$2:U$9999=Blotter!B71)*(Trades!V$2:V$9999)*(Trades!V$2:V$9999>0)),0)} -> 594.83654 | Z71: =IF(C$2="Last",IF(ISNUMBER(VLOOKUP(B71,Data_IB!B:O,14,0)),VLOOKUP(B71,Data_IB!B:O,14,0),0),IF(ISNUMBER(VLOOKUP(B71,Data_IB!B:O,13,0)),VLOOKUP(B71,Data_IB!B:O,13,0),0)) -> 0
B72: ZWK4 | C72: 43 | D72: ZW | E72: Commodities | F72: Futures | G72: =IF(F72="Futures",VLOOKUP(D72,Multiplier!B:I,8,0),0) -> 12 | H72: 20 | I72: {=SUM((Trades!V$2:V$9999)*(Trades!U$2:U$9999=Blotter!B72)*(Trades!$T$2:T$9999=Blotter!C72))} -> 0 | J72: =VLOOKUP(D72,Multiplier!B:D,2,0) -> 50 | K72: =L72-N72/(H72*J72) -> 566.37723 | L72: =IF(I72=0,IF(H72>0,X72,Y72),Z72) -> 570.33333 | M72: =I72*J72*L72 -> 0 | N72: {=-SUM((Trades!T$2:T$9999=Blotter!C72)*(Trades!U$2:U$9999=Blotter!B72)*(Trades!V$2:V$9999)*(Trades!W$2:W$9999))*J72+SUM((Trades!T$2:T$9999=Blotter!C72)*(Trades!U$2:U$9999=Blotter!B72)*(Trades!X$2:X$9999))+(L72*I72)*J72} -> 3956.1 | O72: =VLOOKUP(D72,Multiplier!B:H,3,0) -> 17.25 | P72: 18 | R72: =(1-Q72)*P72*J72*H72 -> 18000 | S72: =IF(OR(F72="Futures",F72="Stocks"),IF(I72=0,0,IF(I72>0,L72-O72,L72+O72)),0) -> 0 | T72: =IF(S72>0,IF(ISNUMBER(S72/L72-1),S72/L72-1,0),0) -> 0 | U72: =IF(OR(F72="Futures",F72="Stocks"),IF(I72=0,0,IF(I72>0,K72-P72,K72+P72)),0) -> 0 | V72: =IF(U72>0,IF(ISNUMBER(U72/L72-1),U72/L72-1,0),0) -> 0 | X72: {=IF(ISNUMBER(SUM((Trades!T$2:T$9999=Blotter!C72)*(Trades!U$2:U$9999=Blotter!B72)*(Trades!W$2:W$9999)*(Trades!V$2:V$9999)*(Trades!V$2:V$9999<0))/SUM((Trades!T$2:T$9999=Blotter!C72)*(Trades!U$2:U$9999=Blotter!B72)*(Trades!V$2:V$9999)*(Trades!V$2:V$9999<0))),SUM((Trades!T$2:T$9999=Blotter!C72)*(Trades!U$2:U$9999=Blotter!B72)*(Trades!W$2:W$9999)*(Trades!V$2:V$9999)*(Trades!V$2:V$9999<0))/SUM((Trades!T$2:T$9999=Blotter!C72)*(Trades!U$2:U$9999=Blotter!B72)*(Trades!V$2:V$9999)*(Trades!V$2:V$9999<0)),0)} -> 570.33333 | Y72: {=IF(ISNUMBER(SUM((Trades!T$2:T$9999=Blotter!C72)*(Trades!U$2:U$9999=Blotter!B72)*(Trades!W$2:W$9999)*(Trades!V$2:V$9999)*(Trades!V$2:V$9999>0))/SUM((Trades!T$2:T$9999=Blotter!C72)*(Trades!U$2:U$9999=Blotter!B72)*(Trades!V$2:V$9999)*(Trades!V$2:V$9999>0))),SUM((Trades!T$2:T$9999=Blotter!C72)*(Trades!U$2:U$9999=Blotter!B72)*(Trades!W$2:W$9999)*(Trades!V$2:V$9999)*(Trades!V$2:V$9999>0))/SUM((Trades!T$2:T$9999=Blotter!C72)*(Trades!U$2:U$9999=Blotter!B72)*(Trades!V$2:V$9999)*(Trades!V$2:V$9999>0)),0)} -> 568.89583 | Z72: =IF(C$2="Last",IF(ISNUMBER(VLOOKUP(B72,Data_IB!B:O,14,0)),VLOOKUP(B72,Data_IB!B:O,14,0),0),IF(ISNUMBER(VLOOKUP(B72,Data_IB!B:O,13,0)),VLOOKUP(B72,Data_IB!B:O,13,0),0)) -> 0
B73: CTK4 | C73: 46 | D73: CT | E73: Commodities | F73: Futures | G73: =IF(F73="Futures",VLOOKUP(D73,Multiplier!B:I,8,0),0) -> 7 | H73: 20 | I73: {=SUM((Trades!V$2:V$9999)*(Trades!U$2:U$9999=Blotter!B73)*(Trades!$T$2:T$9999=Blotter!C73))} -> 0 | J73: =VLOOKUP(D73,Multiplier!B:D,2,0) -> 500 | K73: =L73-N73/(H73*J73) -> 94.146473 | L73: =IF(I73=0,IF(H73>0,X73,Y73),Z73) -> 93.737881 | M73: =I73*J73*L73 -> 0 | N73: {=-SUM((Trades!T$2:T$9999=Blotter!C73)*(Trades!U$2:U$9999=Blotter!B73)*(Trades!V$2:V$9999)*(Trades!W$2:W$9999))*J73+SUM((Trades!T$2:T$9999=Blotter!C73)*(Trades!U$2:U$9999=Blotter!B73)*(Trades!X$2:X$9999))+(L73*I73)*J73} -> -4085.92 | O73: =VLOOKUP(D73,Multiplier!B:H,3,0) -> 3.01 | P73: 1.87 | Q73: 1 | R73: =(1-Q73)*P73*J73*H73 -> 0 | S73: =IF(OR(F73="Futures",F73="Stocks"),IF(I73=0,0,IF(I73>0,L73-O73,L73+O73)),0) -> 0 | T73: =IF(S73>0,IF(ISNUMBER(S73/L73-1),S73/L73-1,0),0) -> 0 | U73: =IF(OR(F73="Futures",F73="Stocks"),IF(I73=0,0,IF(I73>0,K73-P73,K73+P73)),0) -> 0 | V73: =IF(U73>0,IF(ISNUMBER(U73/L73-1),U73/L73-1,0),0) -> 0 | X73: {=IF(ISNUMBER(SUM((Trades!T$2:T$9999=Blotter!C73)*(Trades!U$2:U$9999=Blotter!B73)*(Trades!W$2:W$9999)*(Trades!V$2:V$9999)*(Trades!V$2:V$9999<0))/SUM((Trades!T$2:T$9999=Blotter!C73)*(Trades!U$2:U$9999=Blotter!B73)*(Trades!V$2:V$9999)*(Trades!V$2:V$9999<0))),SUM((Trades!T$2:T$9999=Blotter!C73)*(Trades!U$2:U$9999=Blotter!B73)*(Trades!W$2:W$9999)*(Trades!V$2:V$9999)*(Trades!V$2:V$9999<0))/SUM((Trades!T$2:T$9999=Blotter!C73)*(Trades!U$2:U$9999=Blotter!B73)*(Trades!V$2:V$9999)*(Trades!V$2:V$9999<0)),0)} -> 93.737881 | Y73: {=IF(ISNUMBER(SUM((Trades!T$2:T$9999=Blotter!C73)*(Trades!U$2:U$9999=Blotter!B73)*(Trades!W$2:W$9999)*(Trades!V$2:V$9999)*(Trades!V$2:V$9999>0))/SUM((Trades!T$2:T$9999=Blotter!C73)*(Trades!U$2:U$9999=Blotter!B73)*(Trades!V$2:V$9999)*(Trades!V$2:V$9999>0))),SUM((Trades!T$2:T$9999=Blotter!C73)*(Trades!U$2:U$9999=Blotter!B73)*(Trades!W$2:W$9999)*(Trades!V$2:V$9999)*(Trades!V$2:V$9999>0))/SUM((Trades!T$2:T$9999=Blotter!C73)*(Trades!U$2:U$9999=Blotter!B73)*(Trades!V$2:V$9999)*(Trades!V$2:V$9999>0)),0)} -> 93.795254 | Z73: =IF(C$2="Last",IF(ISNUMBER(VLOOKUP(B73,Data_IB!B:O,14,0)),VLOOKUP(B73,Data_IB!B:O,14,0),0),IF(ISNUMBER(VLOOKUP(B73,Data_IB!B:O,13,0)),VLOOKUP(B73,Data_IB!B:O,13,0),0)) -> 0
B74: CTN4 | C74: 46 | D74: CT | E74: Commodities | F74: Futures | G74: =IF(F74="Futures",VLOOKUP(D74,Multiplier!B:I,8,0),0) -> 7 | H74: 16 | I74: {=SUM((Trades!V$2:V$9999)*(Trades!U$2:U$9999=Blotter!B74)*(Trades!$T$2:T$9999=Blotter!C74))} -> 10 | J74: =VLOOKUP(D74,Multiplier!B:D,2,0) -> 500 | K74: =L74-N74/(H74*J74) -> 50.0779 | L74: =IF(I74=0,IF(H74>0,X74,Y74),Z74) -> 0 | M74: =I74*J74*L74 -> 0 | N74: {=-SUM((Trades!T$2:T$9999=Blotter!C74)*(Trades!U$2:U$9999=Blotter!B74)*(Trades!V$2:V$9999)*(Trades!W$2:W$9999))*J74+SUM((Trades!T$2:T$9999=Blotter!C74)*(Trades!U$2:U$9999=Blotter!B74)*(Trades!X$2:X$9999))+(L74*I74)*J74} -> -400623.2 | O74: =VLOOKUP(D74,Multiplier!B:H,3,0) -> 3.01 | P74: 1.87 | R74: =(1-Q74)*P74*J74*H74 -> 14960 | S74: =IF(OR(F74="Futures",F74="Stocks"),IF(I74=0,0,IF(I74>0,L74-O74,L74+O74)),0) -> -3.01 | T74: =IF(S74>0,IF(ISNUMBER(S74/L74-1),S74/L74-1,0),0) -> 0 | U74: =IF(OR(F74="Futures",F74="Stocks"),IF(I74=0,0,IF(I74>0,K74-P74,K74+P74)),0) -> 48.2079 | V74: =IF(U74>0,IF(ISNUMBER(U74/L74-1),U74/L74-1,0),0) -> 0 | X74: {=IF(ISNUMBER(SUM((Trades!T$2:T$9999=Blotter!C74)*(Trades!U$2:U$9999=Blotter!B74)*(Trades!W$2:W$9999)*(Trades!V$2:V$9999)*(Trades!V$2:V$9999<0))/SUM((Trades!T$2:T$9999=Blotter!C74)*(Trades!U$2:U$9999=Blotter!B74)*(Trades!V$2:V$9999)*(Trades!V$2:V$9999<0))),SUM((Trades!T$2:T$9999=Blotter!C74)*(Trades!U$2:U$9999=Blotter!B74)*(Trades!W$2:W$9999)*(Trades!V$2:V$9999)*(Trades!V$2:V$9999<0))/SUM((Trades!T$2:T$9999=Blotter!C74)*(Trades!U$2:U$9999=Blotter!B74)*(Trades!V$2:V$9999)*(Trades!V$2:V$9999<0)),0)} -> 80.004 | Y74: {=IF(ISNUMBER(SUM((Trades!T$2:T$9999=Blotter!C74)*(Trades!U$2:U$9999=Blotter!B74)*(Trades!W$2:W$9999)*(Trades!V$2:V$9999)*(Trades!V$2:V$9999>0))/SUM((Trades!T$2:T$9999=Blotter!C74)*(Trades!U$2:U$9999=Blotter!B74)*(Trades!V$2:V$9999)*(Trades!V$2:V$9999>0))),SUM((Trades!T$2:T$9999=Blotter!C74)*(Trades!U$2:U$9999=Blotter!B74)*(Trades!W$2:W$9999)*(Trades!V$2:V$9999)*(Trades!V$2:V$9999>0))/SUM((Trades!T$2:T$9999=Blotter!C74)*(Trades!U$2:U$9999=Blotter!B74)*(Trades!V$2:V$9999)*(Trades!V$2:V$9999>0)),0)} -> 80.028286 | Z74: =IF(C$2="Last",IF(ISNUMBER(VLOOKUP(B74,Data_IB!B:O,14,0)),VLOOKUP(B74,Data_IB!B:O,14,0),0),IF(ISNUMBER(VLOOKUP(B74,Data_IB!B:O,13,0)),VLOOKUP(B74,Data_IB!B:O,13,0),0)) -> 0
B75: CLJ4 | C75: 47 | D75: CL | E75: Commodities | F75: Futures | G75: =IF(F75="Futures",VLOOKUP(D75,Multiplier!B:I,8,0),0) -> 4 | H75: 4 | I75: {=SUM((Trades!V$2:V$9999)*(Trades!U$2:U$9999=Blotter!B75)*(Trades!$T$2:T$9999=Blotter!C75))} -> 0 | J75: =VLOOKUP(D75,Multiplier!B:D,2,0) -> 1000 | K75: =L75-N75/(H75*J75) -> 79.50474 | L75: =IF(I75=0,IF(H75>0,X75,Y75),Z75) -> 79.55 | M75: =I75*J75*L75 -> 0 | N75: {=-SUM((Trades!T$2:T$9999=Blotter!C75)*(Trades!U$2:U$9999=Blotter!B75)*(Trades!V$2:V$9999)*(Trades!W$2:W$9999))*J75+SUM((Trades!T$2:T$9999=Blotter!C75)*(Trades!U$2:U$9999=Blotter!B75)*(Trades!X$2:X$9999))+(L75*I75)*J75} -> 181.04 | O75: =VLOOKUP(D75,Multiplier!B:H,3,0) -> 2.41 | P75: 2.41 | Q75: 1 | R75: =(1-Q75)*P75*J75*H75 -> 0 | S75: =IF(OR(F75="Futures",F75="Stocks"),IF(I75=0,0,IF(I75>0,L75-O75,L75+O75)),0) -> 0 | T75: =IF(S75>0,IF(ISNUMBER(S75/L75-1),S75/L75-1,0),0) -> 0 | U75: =IF(OR(F75="Futures",F75="Stocks"),IF(I75=0,0,IF(I75>0,K75-P75,K75+P75)),0) -> 0 | V75: =IF(U75>0,IF(ISNUMBER(U75/L75-1),U75/L75-1,0),0) -> 0 | X75: {=IF(ISNUMBER(SUM((Trades!T$2:T$9999=Blotter!C75)*(Trades!U$2:U$9999=Blotter!B75)*(Trades!W$2:W$9999)*(Trades!V$2:V$9999)*(Trades!V$2:V$9999<0))/SUM((Trades!T$2:T$9999=Blotter!C75)*(Trades!U$2:U$9999=Blotter!B75)*(Trades!V$2:V$9999)*(Trades!V$2:V$9999<0))),SUM((Trades!T$2:T$9999=Blotter!C75)*(Trades!U$2:U$9999=Blotter!B75)*(Trades!W$2:W$9999)*(Trades!V$2:V$9999)*(Trades!V$2:V$9999<0))/SUM((Trades!T$2:T$9999=Blotter!C75)*(Trades!U$2:U$9999=Blotter!B75)*(Trades!V$2:V$9999)*(Trades!V$2:V$9999<0)),0)} -> 79.55 | Y75: {=IF(ISNUMBER(SUM((Trades!T$2:T$9999=Blotter!C75)*(Trades!U$2:U$9999=Blotter!B75)*(Trades!W$2:W$9999)*(Trades!V$2:V$9999)*(Trades!V$2:V$9999>0))/SUM((Trades!T$2:T$9999=Blotter!C75)*(Trades!U$2:U$9999=Blotter!B75)*(Trades!V$2:V$9999)*(Trades!V$2:V$9999>0))),SUM((Trades!T$2:T$9999=Blotter!C75)*(Trades!U$2:U$9999=Blotter!B75)*(Trades!W$2:W$9999)*(Trades!V$2:V$9999)*(Trades!V$2:V$9999>0))/SUM((Trades!T$2:T$9999=Blotter!C75)*(Trades!U$2:U$9999=Blotter!B75)*(Trades!V$2:V$9999)*(Trades!V$2:V$9999>0)),0)} -> 79.5 | Z75: =IF(C$2="Last",IF(ISNUMBER(VLOOKUP(B75,Data_IB!B:O,14,0)),VLOOKUP(B75,Data_IB!B:O,14,0),0),IF(ISNUMBER(VLOOKUP(B75,Data_IB!B:O,13,0)),VLOOKUP(B75,Data_IB!B:O,13,0),0)) -> 0
B76: EWJ4 P4920 | C76: 48 | D76: ES | E76: Equity | F76: Put | G76: =IF(F76="Futures",VLOOKUP(D76,Multiplier!B:I,8,0),0) -> 0 | H76: -20 | I76: {=SUM((Trades!V$2:V$9999)*(Trades!U$2:U$9999=Blotter!B76)*(Trades!$T$2:T$9999=Blotter!C76))} -> 0 | J76: =VLOOKUP(D76,Multiplier!B:D,2,0) -> 50 | K76: =L76-N76/(H76*J76) -> 27.4432 | L76: =IF(I76=0,IF(H76>0,X76,Y76),Z76) -> 11.45 | M76: =I76*J76*L76 -> 0 | N76: {=-SUM((Trades!T$2:T$9999=Blotter!C76)*(Trades!U$2:U$9999=Blotter!B76)*(Trades!V$2:V$9999)*(Trades!W$2:W$9999))*J76+SUM((Trades!T$2:T$9999=Blotter!C76)*(Trades!U$2:U$9999=Blotter!B76)*(Trades!X$2:X$9999))+(L76*I76)*J76} -> 15993.2 | O76: =VLOOKUP(D76,Multiplier!B:H,3,0) -> 50.57 | P76: 28.9716 | Q76: 1 | R76: =(1-Q76)*P76*J76*H76 -> 0 | S76: =IF(OR(F76="Futures",F76="Stocks"),IF(I76=0,0,IF(I76>0,L76-O76,L76+O76)),0) -> 0 | T76: =IF(S76>0,IF(ISNUMBER(S76/L76-1),S76/L76-1,0),0) -> 0 | U76: =IF(OR(F76="Futures",F76="Stocks"),IF(I76=0,0,IF(I76>0,K76-P76,K76+P76)),0) -> 0 | V76: =IF(U76>0,IF(ISNUMBER(U76/L76-1),U76/L76-1,0),0) -> 0 | X76: {=IF(ISNUMBER(SUM((Trades!T$2:T$9999=Blotter!C76)*(Trades!U$2:U$9999=Blotter!B76)*(Trades!W$2:W$9999)*(Trades!V$2:V$9999)*(Trades!V$2:V$9999<0))/SUM((Trades!T$2:T$9999=Blotter!C76)*(Trades!U$2:U$9999=Blotter!B76)*(Trades!V$2:V$9999)*(Trades!V$2:V$9999<0))),SUM((Trades!T$2:T$9999=Blotter!C76)*(Trades!U$2:U$9999=Blotter!B76)*(Trades!W$2:W$9999)*(Trades!V$2:V$9999)*(Trades!V$2:V$9999<0))/SUM((Trades!T$2:T$9999=Blotter!C76)*(Trades!U$2:U$9999=Blotter!B76)*(Trades!V$2:V$9999)*(Trades!V$2:V$9999<0)),0)} -> 27.5 | Y76: {=IF(ISNUMBER(SUM((Trades!T$2:T$9999=Blotter!C76)*(Trades!U$2:U$9999=Blotter!B76)*(Trades!W$2:W$9999)*(Trades!V$2:V$9999)*(Trades!V$2:V$9999>0))/SUM((Trades!T$2:T$9999=Blotter!C76)*(Trades!U$2:U$9999=Blotter!B76)*(Trades!V$2:V$9999)*(Trades!V$2:V$9999>0))),SUM((Trades!T$2:T$9999=Blotter!C76)*(Trades!U$2:U$9999=Blotter!B76)*(Trades!W$2:W$9999)*(Trades!V$2:V$9999)*(Trades!V$2:V$9999>0))/SUM((Trades!T$2:T$9999=Blotter!C76)*(Trades!U$2:U$9999=Blotter!B76)*(Trades!V$2:V$9999)*(Trades!V$2:V$9999>0)),0)} -> 11.45 | Z76: =IF(C$2="Last",IF(ISNUMBER(VLOOKUP(B76,Data_IB!B:O,14,0)),VLOOKUP(B76,Data_IB!B:O,14,0),0),IF(ISNUMBER(VLOOKUP(B76,Data_IB!B:O,13,0)),VLOOKUP(B76,Data_IB!B:O,13,0),0)) -> 0
B77: EWJ4 P5020 | C77: 48 | D77: ES | E77: Equity | F77: Put | G77: =IF(F77="Futures",VLOOKUP(D77,Multiplier!B:I,8,0),0) -> 0 | H77: 20 | I77: {=SUM((Trades!V$2:V$9999)*(Trades!U$2:U$9999=Blotter!B77)*(Trades!$T$2:T$9999=Blotter!C77))} -> 0 | J77: =VLOOKUP(D77,Multiplier!B:D,2,0) -> 50 | K77: =L77-N77/(H77*J77) -> 42.4318 | L77: =IF(I77=0,IF(H77>0,X77,Y77),Z77) -> 34.25 | M77: =I77*J77*L77 -> 0 | N77: {=-SUM((Trades!T$2:T$9999=Blotter!C77)*(Trades!U$2:U$9999=Blotter!B77)*(Trades!V$2:V$9999)*(Trades!W$2:W$9999))*J77+SUM((Trades!T$2:T$9999=Blotter!C77)*(Trades!U$2:U$9999=Blotter!B77)*(Trades!X$2:X$9999))+(L77*I77)*J77} -> -8181.8 | O77: =VLOOKUP(D77,Multiplier!B:H,3,0) -> 50.57 | P77: 44.7784 | R77: =(1-Q77)*P77*J77*H77 -> 44778.4 | S77: =IF(OR(F77="Futures",F77="Stocks"),IF(I77=0,0,IF(I77>0,L77-O77,L77+O77)),0) -> 0 | T77: =IF(S77>0,IF(ISNUMBER(S77/L77-1),S77/L77-1,0),0) -> 0 | U77: =IF(OR(F77="Futures",F77="Stocks"),IF(I77=0,0,IF(I77>0,K77-P77,K77+P77)),0) -> 0 | V77: =IF(U77>0,IF(ISNUMBER(U77/L77-1),U77/L77-1,0),0) -> 0 | X77: {=IF(ISNUMBER(SUM((Trades!T$2:T$9999=Blotter!C77)*(Trades!U$2:U$9999=Blotter!B77)*(Trades!W$2:W$9999)*(Trades!V$2:V$9999)*(Trades!V$2:V$9999<0))/SUM((Trades!T$2:T$9999=Blotter!C77)*(Trades!U$2:U$9999=Blotter!B77)*(Trades!V$2:V$9999)*(Trades!V$2:V$9999<0))),SUM((Trades!T$2:T$9999=Blotter!C77)*(Trades!U$2:U$9999=Blotter!B77)*(Trades!W$2:W$9999)*(Trades!V$2:V$9999)*(Trades!V$2:V$9999<0))/SUM((Trades!T$2:T$9999=Blotter!C77)*(Trades!U$2:U$9999=Blotter!B77)*(Trades!V$2:V$9999)*(Trades!V$2:V$9999<0)),0)} -> 34.25 | Y77: {=IF(ISNUMBER(SUM((Trades!T$2:T$9999=Blotter!C77)*(Trades!U$2:U$9999=Blotter!B77)*(Trades!W$2:W$9999)*(Trades!V$2:V$9999)*(Trades!V$2:V$9999>0))/SUM((Trades!T$2:T$9999=Blotter!C77)*(Trades!U$2:U$9999=Blotter!B77)*(Trades!V$2:V$9999)*(Trades!V$2:V$9999>0))),SUM((Trades!T$2:T$9999=Blotter!C77)*(Trades!U$2:U$9999=Blotter!B77)*(Trades!W$2:W$9999)*(Trades!V$2:V$9999)*(Trades!V$2:V$9999>0))/SUM((Trades!T$2:T$9999=Blotter!C77)*(Trades!U$2:U$9999=Blotter!B77)*(Trades!V$2:V$9999)*(Trades!V$2:V$9999>0)),0)} -> 42.375 | Z77: =IF(C$2="Last",IF(ISNUMBER(VLOOKUP(B77,Data_IB!B:O,14,0)),VLOOKUP(B77,Data_IB!B:O,14,0),0),IF(ISNUMBER(VLOOKUP(B77,Data_IB!B:O,13,0)),VLOOKUP(B77,Data_IB!B:O,13,0),0)) -> 0
B78: KCK4 | C78: 48 | D78: KC | E78: Commodities | F78: Futures | G78: =IF(F78="Futures",VLOOKUP(D78,Multiplier!B:I,8,0),0) -> 5 | H78: 10 | I78: {=SUM((Trades!V$2:V$9999)*(Trades!U$2:U$9999=Blotter!B78)*(Trades!$T$2:T$9999=Blotter!C78))} -> 0 | J78: =VLOOKUP(D78,Multiplier!B:D,2,0) -> 375 | K78: =L78-N78/(H78*J78) -> 180.35668 | L78: =IF(I78=0,IF(H78>0,X78,Y78),Z78) -> 190.875 | M78: =I78*J78*L78 -> 0 | N78: {=-SUM((Trades!T$2:T$9999=Blotter!C78)*(Trades!U$2:U$9999=Blotter!B78)*(Trades!V$2:V$9999)*(Trades!W$2:W$9999))*J78+SUM((Trades!T$2:T$9999=Blotter!C78)*(Trades!U$2:U$9999=Blotter!B78)*(Trades!X$2:X$9999))+(L78*I78)*J78} -> 39443.7 | O78: =VLOOKUP(D78,Multiplier!B:H,3,0) -> 5.38 | P78: 3.5 | R78: =(1-Q78)*P78*J78*H78 -> 13125 | S78: =IF(OR(F78="Futures",F78="Stocks"),IF(I78=0,0,IF(I78>0,L78-O78,L78+O78)),0) -> 0 | T78: =IF(S78>0,IF(ISNUMBER(S78/L78-1),S78/L78-1,0),0) -> 0 | U78: =IF(OR(F78="Futures",F78="Stocks"),IF(I78=0,0,IF(I78>0,K78-P78,K78+P78)),0) -> 0 | V78: =IF(U78>0,IF(ISNUMBER(U78/L78-1),U78/L78-1,0),0) -> 0 | X78: {=IF(ISNUMBER(SUM((Trades!T$2:T$9999=Blotter!C78)*(Trades!U$2:U$9999=Blotter!B78)*(Trades!W$2:W$9999)*(Trades!V$2:V$9999)*(Trades!V$2:V$9999<0))/SUM((Trades!T$2:T$9999=Blotter!C78)*(Trades!U$2:U$9999=Blotter!B78)*(Trades!V$2:V$9999)*(Trades!V$2:V$9999<0))),SUM((Trades!T$2:T$9999=Blotter!C78)*(Trades!U$2:U$9999=Blotter!B78)*(Trades!W$2:W$9999)*(Trades!V$2:V$9999)*(Trades!V$2:V$9999<0))/SUM((Trades!T$2:T$9999=Blotter!C78)*(Trades!U$2:U$9999=Blotter!B78)*(Trades!V$2:V$9999)*(Trades!V$2:V$9999<0)),0)} -> 190.875 | Y78: {=IF(ISNUMBER(SUM((Trades!T$2:T$9999=Blotter!C78)*(Trades!U$2:U$9999=Blotter!B78)*(Trades!W$2:W$9999)*(Trades!V$2:V$9999)*(Trades!V$2:V$9999>0))/SUM((Trades!T$2:T$9999=Blotter!C78)*(Trades!U$2:U$9999=Blotter!B78)*(Trades!V$2:V$9999)*(Trades!V$2:V$9999>0))),SUM((Trades!T$2:T$9999=Blotter!C78)*(Trades!U$2:U$9999=Blotter!B78)*(Trades!W$2:W$9999)*(Trades!V$2:V$9999)*(Trades!V$2:V$9999>0))/SUM((Trades!T$2:T$9999=Blotter!C78)*(Trades!U$2:U$9999=Blotter!B78)*(Trades!V$2:V$9999)*(Trades!V$2:V$9999>0)),0)} -> 185.6 | Z78: =IF(C$2="Last",IF(ISNUMBER(VLOOKUP(B78,Data_IB!B:O,14,0)),VLOOKUP(B78,Data_IB!B:O,14,0),0),IF(ISNUMBER(VLOOKUP(B78,Data_IB!B:O,13,0)),VLOOKUP(B78,Data_IB!B:O,13,0),0)) -> 0
B79: ZSK4 | C79: 49 | D79: ZS | E79: Commodities | F79: Futures | G79: =IF(F79="Futures",VLOOKUP(D79,Multiplier!B:I,8,0),0) -> 10 | H79: 20 | I79: {=SUM((Trades!V$2:V$9999)*(Trades!U$2:U$9999=Blotter!B79)*(Trades!$T$2:T$9999=Blotter!C79))} -> 0 | J79: =VLOOKUP(D79,Multiplier!B:D,2,0) -> 50 | K79: =L79-N79/(H79*J79) -> 1182.7235 | L79: =IF(I79=0,IF(H79>0,X79,Y79),Z79) -> 1179.2 | M79: =I79*J79*L79 -> 0 | N79: {=-SUM((Trades!T$2:T$9999=Blotter!C79)*(Trades!U$2:U$9999=Blotter!B79)*(Trades!V$2:V$9999)*(Trades!W$2:W$9999))*J79+SUM((Trades!T$2:T$9999=Blotter!C79)*(Trades!U$2:U$9999=Blotter!B79)*(Trades!X$2:X$9999))+(L79*I79)*J79} -> -3523.5 | O79: =VLOOKUP(D79,Multiplier!B:H,3,0) -> 19.75 | P79: 20.5 | R79: =(1-Q79)*P79*J79*H79 -> 20500 | S79: =IF(OR(F79="Futures",F79="Stocks"),IF(I79=0,0,IF(I79>0,L79-O79,L79+O79)),0) -> 0 | T79: =IF(S79>0,IF(ISNUMBER(S79/L79-1),S79/L79-1,0),0) -> 0 | U79: =IF(OR(F79="Futures",F79="Stocks"),IF(I79=0,0,IF(I79>0,K79-P79,K79+P79)),0) -> 0 | V79: =IF(U79>0,IF(ISNUMBER(U79/L79-1),U79/L79-1,0),0) -> 0 | X79: {=IF(ISNUMBER(SUM((Trades!T$2:T$9999=Blotter!C79)*(Trades!U$2:U$9999=Blotter!B79)*(Trades!W$2:W$9999)*(Trades!V$2:V$9999)*(Trades!V$2:V$9999<0))/SUM((Trades!T$2:T$9999=Blotter!C79)*(Trades!U$2:U$9999=Blotter!B79)*(Trades!V$2:V$9999)*(Trades!V$2:V$9999<0))),SUM((Trades!T$2:T$9999=Blotter!C79)*(Trades!U$2:U$9999=Blotter!B79)*(Trades!W$2:W$9999)*(Trades!V$2:V$9999)*(Trades!V$2:V$9999<0))/SUM((Trades!T$2:T$9999=Blotter!C79)*(Trades!U$2:U$9999=Blotter!B79)*(Trades!V$2:V$9999)*(Trades!V$2:V$9999<0)),0)} -> 1179.2 | Y79: {=IF(ISNUMBER(SUM((Trades!T$2:T$9999=Blotter!C79)*(Trades!U$2:U$9999=Blotter!B79)*(Trades!W$2:W$9999)*(Trades!V$2:V$9999)*(Trades!V$2:V$9999>0))/SUM((Trades!T$2:T$9999=Blotter!C79)*(Trades!U$2:U$9999=Blotter!B79)*(Trades!V$2:V$9999)*(Trades!V$2:V$9999>0))),SUM((Trades!T$2:T$9999=Blotter!C79)*(Trades!U$2:U$9999=Blotter!B79)*(Trades!W$2:W$9999)*(Trades!V$2:V$9999)*(Trades!V$2:V$9999>0))/SUM((Trades!T$2:T$9999=Blotter!C79)*(Trades!U$2:U$9999=Blotter!B79)*(Trades!V$2:V$9999)*(Trades!V$2:V$9999>0)),0)} -> 1181.9 | Z79: =IF(C$2="Last",IF(ISNUMBER(VLOOKUP(B79,Data_IB!B:O,14,0)),VLOOKUP(B79,Data_IB!B:O,14,0),0),IF(ISNUMBER(VLOOKUP(B79,Data_IB!B:O,13,0)),VLOOKUP(B79,Data_IB!B:O,13,0),0)) -> 0
B80: NQM4 | C80: 53 | D80: NQ | E80: Equity | F80: Futures | G80: =IF(F80="Futures",VLOOKUP(D80,Multiplier!B:I,8,0),0) -> 2 | H80: -3 | I80: {=SUM((Trades!V$2:V$9999)*(Trades!U$2:U$9999=Blotter!B80)*(Trades!$T$2:T$9999=Blotter!C80))} -> 0 | J80: =VLOOKUP(D80,Multiplier!B:D,2,0) -> 20 | K80: =L80-N80/(H80*J80) -> 17589.77 | L80: =IF(I80=0,IF(H80>0,X80,Y80),Z80) -> 17515.66 | M80: =I80*J80*L80 -> 0 | N80: {=-SUM((Trades!T$2:T$9999=Blotter!C80)*(Trades!U$2:U$9999=Blotter!B80)*(Trades!V$2:V$9999)*(Trades!W$2:W$9999))*J80+SUM((Trades!T$2:T$9999=Blotter!C80)*(Trades!U$2:U$9999=Blotter!B80)*(Trades!X$2:X$9999))+(L80*I80)*J80} -> 4446.6 | O80: =VLOOKUP(D80,Multiplier!B:H,3,0) -> 248 | P80: 248 | R80: =(1-Q80)*P80*J80*H80 -> -14880 | S80: =IF(OR(F80="Futures",F80="Stocks"),IF(I80=0,0,IF(I80>0,L80-O80,L80+O80)),0) -> 0 | T80: =IF(S80>0,IF(ISNUMBER(S80/L80-1),S80/L80-1,0),0) -> 0 | U80: =IF(OR(F80="Futures",F80="Stocks"),IF(I80=0,0,IF(I80>0,K80-P80,K80+P80)),0) -> 0 | V80: =IF(U80>0,IF(ISNUMBER(U80/L80-1),U80/L80-1,0),0) -> 0 | X80: {=IF(ISNUMBER(SUM((Trades!T$2:T$9999=Blotter!C80)*(Trades!U$2:U$9999=Blotter!B80)*(Trades!W$2:W$9999)*(Trades!V$2:V$9999)*(Trades!V$2:V$9999<0))/SUM((Trades!T$2:T$9999=Blotter!C80)*(Trades!U$2:U$9999=Blotter!B80)*(Trades!V$2:V$9999)*(Trades!V$2:V$9999<0))),SUM((Trades!T$2:T$9999=Blotter!C80)*(Trades!U$2:U$9999=Blotter!B80)*(Trades!W$2:W$9999)*(Trades!V$2:V$9999)*(Trades!V$2:V$9999<0))/SUM((Trades!T$2:T$9999=Blotter!C80)*(Trades!U$2:U$9999=Blotter!B80)*(Trades!V$2:V$9999)*(Trades!V$2:V$9999<0)),0)} -> 17522.056 | Y80: {=IF(ISNUMBER(SUM((Trades!T$2:T$9999=Blotter!C80)*(Trades!U$2:U$9999=Blotter!B80)*(Trades!W$2:W$9999)*(Trades!V$2:V$9999)*(Trades!V$2:V$9999>0))/SUM((Trades!T$2:T$9999=Blotter!C80)*(Trades!U$2:U$9999=Blotter!B80)*(Trades!V$2:V$9999)*(Trades!V$2:V$9999>0))),SUM((Trades!T$2:T$9999=Blotter!C80)*(Trades!U$2:U$9999=Blotter!B80)*(Trades!W$2:W$9999)*(Trades!V$2:V$9999)*(Trades!V$2:V$9999>0))/SUM((Trades!T$2:T$9999=Blotter!C80)*(Trades!U$2:U$9999=Blotter!B80)*(Trades!V$2:V$9999)*(Trades!V$2:V$9999>0)),0)} -> 17515.66 | Z80: =IF(C$2="Last",IF(ISNUMBER(VLOOKUP(B80,Data_IB!B:O,14,0)),VLOOKUP(B80,Data_IB!B:O,14,0),0),IF(ISNUMBER(VLOOKUP(B80,Data_IB!B:O,13,0)),VLOOKUP(B80,Data_IB!B:O,13,0),0)) -> 0
B81: CCN4 | C81: 56 | D81: CC | E81: Commodities | F81: Futures | G81: =IF(F81="Futures",VLOOKUP(D81,Multiplier!B:I,8,0),0) -> 3 | H81: 5 | I81: {=SUM((Trades!V$2:V$9999)*(Trades!U$2:U$9999=Blotter!B81)*(Trades!$T$2:T$9999=Blotter!C81))} -> 0 | J81: =VLOOKUP(D81,Multiplier!B:D,2,0) -> 10 | K81: =L81-N81/(H81*J81) -> 9269.4571 | L81: =IF(I81=0,IF(H81>0,X81,Y81),Z81) -> 8100.1111 | M81: =I81*J81*L81 -> 0 | N81: {=-SUM((Trades!T$2:T$9999=Blotter!C81)*(Trades!U$2:U$9999=Blotter!B81)*(Trades!V$2:V$9999)*(Trades!W$2:W$9999))*J81+SUM((Trades!T$2:T$9999=Blotter!C81)*(Trades!U$2:U$9999=Blotter!B81)*(Trades!X$2:X$9999))+(L81*I81)*J81} -> -58467.3 | O81: =VLOOKUP(D81,Multiplier!B:H,3,0) -> 400 | P81: 400 | R81: =(1-Q81)*P81*J81*H81 -> 20000 | S81: =IF(OR(F81="Futures",F81="Stocks"),IF(I81=0,0,IF(I81>0,L81-O81,L81+O81)),0) -> 0 | T81: =IF(S81>0,IF(ISNUMBER(S81/L81-1),S81/L81-1,0),0) -> 0 | U81: =IF(OR(F81="Futures",F81="Stocks"),IF(I81=0,0,IF(I81>0,K81-P81,K81+P81)),0) -> 0 | V81: =IF(U81>0,IF(ISNUMBER(U81/L81-1),U81/L81-1,0),0) -> 0 | X81: {=IF(ISNUMBER(SUM((Trades!T$2:T$9999=Blotter!C81)*(Trades!U$2:U$9999=Blotter!B81)*(Trades!W$2:W$9999)*(Trades!V$2:V$9999)*(Trades!V$2:V$9999<0))/SUM((Trades!T$2:T$9999=Blotter!C81)*(Trades!U$2:U$9999=Blotter!B81)*(Trades!V$2:V$9999)*(Trades!V$2:V$9999<0))),SUM((Trades!T$2:T$9999=Blotter!C81)*(Trades!U$2:U$9999=Blotter!B81)*(Trades!W$2:W$9999)*(Trades!V$2:V$9999)*(Trades!V$2:V$9999<0))/SUM((Trades!T$2:T$9999=Blotter!C81)*(Trades!U$2:U$9999=Blotter!B81)*(Trades!V$2:V$9999)*(Trades!V$2:V$9999<0)),0)} -> 8100.1111 | Y81: {=IF(ISNUMBER(SUM((Trades!T$2:T$9999=Blotter!C81)*(Trades!U$2:U$9999=Blotter!B81)*(Trades!W$2:W$9999)*(Trades!V$2:V$9999)*(Trades!V$2:V$9999>0))/SUM((Trades!T$2:T$9999=Blotter!C81)*(Trades!U$2:U$9999=Blotter!B81)*(Trades!V$2:V$9999)*(Trades!V$2:V$9999>0))),SUM((Trades!T$2:T$9999=Blotter!C81)*(Trades!U$2:U$9999=Blotter!B81)*(Trades!W$2:W$9999)*(Trades!V$2:V$9999)*(Trades!V$2:V$9999>0))/SUM((Trades!T$2:T$9999=Blotter!C81)*(Trades!U$2:U$9999=Blotter!B81)*(Trades!V$2:V$9999)*(Trades!V$2:V$9999>0)),0)} -> 8229.4444 | Z81: =IF(C$2="Last",IF(ISNUMBER(VLOOKUP(B81,Data_IB!B:O,14,0)),VLOOKUP(B81,Data_IB!B:O,14,0),0),IF(ISNUMBER(VLOOKUP(B81,Data_IB!B:O,13,0)),VLOOKUP(B81,Data_IB!B:O,13,0),0)) -> 0

Sheet Cash_Mgmt
C2: COUPON | D2: ENTRY PRICE | E2: QUANTITY | F2: EXIT PRICE | G2: TOTAL | H2: RISK FREE P&L
B3: INTEREST | G3: =2060.74+768.64+6750 -> 9579.38
B4: INTEREST ACCRUALS | G4: 3376 | H4: =-G4 -> -3376
B5: T-BOND 4 CPN | H5: =(C9*E9*100) -> 0
B6: T-BOND 3 CPN | H6: =(C10*E10*100) -> 0
B7: T-BOND 2 CPN | H7: =(C11*E11*100) -> 0
B8: T-BOND CPN
B9: T-BOND 4
B10: T-BOND 3
B11: T-BOND 2
B12: T-BOND
B13: Total | G13: =SUM(G3:G12) -> 12955.38 | H13: =SUM(H3:H12) -> -3376

Sheet NAV
B2: Date | C2: ∆ Shares | D2: ∆ Capital | E2: BoP Capital $ | F2: Management Fee $ | G2: Performance Fee $ | H2: Costs $ | I2: P&L $ | J2: EoP Capital $ | K2: Shares | L2: NAV | M2: Perf. ITD | N2: Perf. MTD | O2: Volatility
B3: 45654 | J3: =L3*K3 -> 1000000 | K3: 1000 | L3: 1000 | M3: 0 | N3: 0
B4: 45685 | D4: =C4*L3 -> 0 | E4: =J3+D4 -> 1000000 | I4: -7562.17 | J4: =E4-F4-G4-H4+I4 -> 992437.83 | K4: =K3+C4 -> 1000 | L4: =J4/K4 -> 992.43783 | M4: =L4/$L$3-1 -> -0.00756217 | N4: =L4/L3-1 -> -0.00756217
B5: 45716 | D5: =C5*L4 -> 0 | E5: =J4+D5 -> 992437.83 | I5: -16180.91 | J5: =E5-F5-G5-H5+I5 -> 976256.92 | K5: =K4+C5 -> 1000 | L5: =J5/K5 -> 976.25692 | M5: =L5/$L$3-1 -> -0.02374308 | N5: =L5/L4-1 -> -0.016304205 | O5: =STDEVP(N$4:N5)*SQRT(12) -> 0.015141649
B6: 45744 | D6: =C6*L5 -> 0 | E6: =J5+D6 -> 976256.92 | I6: 46816.42 | J6: =E6-F6-G6-H6+I6 -> 1023073.3 | K6: =K5+C6 -> 1000 | L6: =J6/K6 -> 1023.0733 | M6: =L6/$L$3-1 -> 0.02307334 | N6: =L6/L5-1 -> 0.04795502 | O6: =STDEVP(N$4:N6)*SQRT(12) -> 0.098575383
B7: 45775 | D7: =C7*L6 -> 0 | E7: =J6+D7 -> 1023073.3 | I7: 33940.01 | J7: =E7-F7-G7-H7+I7 -> 1057013.4 | K7: =K6+C7 -> 1000 | L7: =J7/K7 -> 1057.0134 | M7: =L7/$L$3-1 -> 0.05701335 | N7: =L7/L6-1 -> 0.033174562 | O7: =STDEVP(N$4:N7)*SQRT(12) -> 0.093329743
B8: 45805 | D8: =C8*L7 -> 0 | E8: =J7+D8 -> 1057013.4 | I8: 28411.06 | J8: =E8-F8-G8-H8+I8 -> 1085424.4 | K8: =K7+C8 -> 1000 | L8: =J8/K8 -> 1085.4244 | M8: =L8/$L$3-1 -> 0.08542441 | N8: =L8/L7-1 -> 0.02687862 | O8: =STDEVP(N$4:N8)*SQRT(12) -> 0.085272361
B9: 45836 | D9: =C9*L8 -> 0 | E9: =J8+D9 -> 1085424.4 | I9: =-174083.62+187500 -> 13416.38 | J9: =E9-F9-G9-H9+I9 -> 1098840.8 | K9: =K8+C9 -> 1000 | L9: =J9/K9 -> 1098.8408 | M9: =L9/$L$3-1 -> 0.09884079 | N9: =L9/L8-1 -> 0.012360492 | O9: =STDEVP(N$4:N9)*SQRT(12) -> 0.078056066 | Q9: =J9-$R$9 -> 911340.79 | R9: 187500
B10: 45866 | C10: =1000000/L9 -> 910.04994 | D10: =C10*L9 -> 1000000 | E10: =J9+D10 -> 2098840.8 | I10: -20156.18 | J10: =E10-F10-G10-H10+I10 -> 2078684.6 | K10: =K9+C10 -> 1910.0499 | L10: =J10/K10 -> 1088.2881 | M10: =L10/$L$3-1 -> 0.088288092 | N10: =L10/L9-1 -> -0.0096034821 | O10: =STDEVP(N$4:N10)*SQRT(12) -> 0.078688667 | Q10: =J10-$R$9 -> 1891184.6
B11: 45897 | D11: =C11*L10 -> 0 | E11: =J10+D11 -> 2078684.6 | I11: 86459.62 | J11: =E11-F11-G11-H11+I11 -> 2165144.2 | K11: =K10+C11 -> 1910.0499 | L11: =J11/K11 -> 1133.5537 | M11: =L11/$L$3-1 -> 0.13355373 | N11: =L11/L10-1 -> 0.041593429 | O11: =STDEVP(N$4:N11)*SQRT(12) -> 0.080841961 | Q11: =J11-$R$9 -> 1977644.2
B12: 45928 | E12: =J11+D12 -> 2165144.2 | I12: 20597.2 | J12: =E12-F12-G12-H12+I12 -> 2185741.4 | K12: =K11+C12 -> 1910.0499 | L12: =J12/K12 -> 1144.3373 | M12: =L12/$L$3-1 -> 0.14433732 | N12: =L12/L11-1 -> 0.0095130845 | O12: =STDEVP(N$4:N12)*SQRT(12) -> 0.076551211 | Q12: =J12-$R$9 -> 1998241.4
B13: 45958 | E13: =J12+D13 -> 2185741.4 | I13: -5581.31 | J13: =E13-F13-G13-H13+I13 -> 2180160.1 | K13: =K12+C13 -> 1910.0499 | L13: =J13/K13 -> 1141.4152 | M13: =L13/$L$3-1 -> 0.14141524 | N13: =L13/L12-1 -> -0.0025535088 | O13: =STDEVP(N$4:N13)*SQRT(12) -> 0.074964233 | Q13: =J13-$R$9 -> 1992660.1
B14: 45989 | E14: =J13+D14 -> 2180160.1 | I14: 88970.84 | J14: =E14-F14-G14-H14+I14 -> 2269131 | K14: =K13+C14 -> 1910.0499 | L14: =J14/K14 -> 1187.9956 | M14: =L14/$L$3-1 -> 0.18799562 | N14: =L14/L13-1 -> 0.040809315 | O14: =STDEVP(N$4:N14)*SQRT(12) -> 0.076458811 | Q14: =J14-$R$9 -> 2081631
B15: 46019 | E15: =J14+D15 -> 2269131 | I15: 15498.1 | J15: =E15-F15-G15-H15+I15 -> 2284629.1 | K15: =K14+C15 -> 1910.0499 | L15: =J15/K15 -> 1196.1096 | M15: =L15/$L$3-1 -> 0.19610959 | N15: =L15/L14-1 -> 0.0068299716 | O15: =STDEVP(N$4:N15)*SQRT(12) -> 0.073731058 | Q15: =J15-$R$9 -> 2097129.1
B16: 46050 | E16: =J15+D16 -> 2284629.1 | I16: -89660.25 | J16: =E16-F16-G16-H16+I16 -> 2194968.8 | K16: =K15+C16 -> 1910.0499 | L16: =J16/K16 -> 1149.1683 | M16: =L16/$L$3-1 -> 0.14916828 | N16: =L16/L15-1 -> -0.039244992 | O16: =STDEVP(N$4:N16)*SQRT(12) -> 0.086886124 | Q16: =J16-$R$9 -> 2007468.8
B17: 46081 | E17: =J16+D17 -> 2194968.8 | I17: =Blotter!C$4-SUM(NAV!I$4:I16) -> -711257.24 | J17: =E17-F17-G17-H17+I17 -> 1483711.6 | K17: =K16+C17 -> 1910.0499 | L17: =J17/K17 -> 776.79203 | M17: =L17/$L$3-1 -> -0.22320797 | N17: =L17/L16-1 -> -0.3240398 | O17: =STDEVP(N$4:N17)*SQRT(12) -> 0.31046392 | Q17: =J17-$R$9 -> 1296211.6
B18: 46109
B19: 46140
B20: 46170
B21: 46201
B22: 46231
B23: 46262
B24: 46293

Sheet PLB
B2: DATE | C2: WEEK | D2: P&L $ | E2: RISK $ | F2: RISK-RETURN | G2: OPEN/CLOSE | H2: BoP NAV $ | I2: ∆ CAPITAL | J2: EoP NAV$ | K2: WK PERF % | L2: PERF % | M2: BoP MIN NAV $ | N2: ∆ CAPITAL | O2: EoP MIN NAV $ | P2: WK PLB % | Q2: PLB % | R2: Initial PLB % | T2: DATE | U2: WEEK | V2: INSTRUMENT | W2: THEME | X2: TECHNICAL SET-UP | Z2: INSTRUMENT | AA2: THEME | AB2: TECHNICAL SET-UP
C3: 0 | H3: 0 | I3: 1000000 | J3: =H3+I3 -> 1000000 | M3: =H3 -> 0 | N3: 1000000 | O3: =M3+N3 -> 1000000 | R3: 0
B4: 45026 | C4: =C3+1 -> 1 | D4: {=SUM((Blotter!C$19:C$1013=C4)*(Blotter!N$19:N$1013)*1)} -> 6275.4921 | E4: {=SUM((Blotter!B$19:C$1013=C4)*(Blotter!R$19:R$1013)*1)} -> 9900 | F4: =IF(ISNUMBER(D4/E4),D4/E4,0) -> 0.63388809 | G4: {=IF(SUM((Blotter!C$19:C$1013=PLB!C4)*(Blotter!M$19:M$1013))=0,"C","O")} -> C | H4: =J3+D4 -> 1006275.5 | J4: =H4+I4 -> 1006275.5 | K4: =H4/J3-1 -> 0.0062754921 | L4: =(1+K4)*(1+L3)-1 -> 0.0062754921 | M4: =O3-IF(G4="O",O3*1%,-D4) -> 1006275.5 | N4: =I4 -> 0 | O4: =M4+N4 -> 1006275.5 | P4: =M4/O3-1 -> 0.0062754921 | Q4: =(1+P4)*(1+Q3)-1 -> 0.0062754921 | R4: =(1-1%)*(1+R3)-1 -> -0.01 | T4: =B4 -> 45026 | U4: =C4 -> 1 | V4: Long SPX Put Spread | W4: US economy hard-landing / earnings estimates downward revisions
B5: =B4+7 -> 45033 | C5: =C4+1 -> 2 | D5: {=SUM((Blotter!C$19:C$1013=C5)*(Blotter!N$19:N$1013)*1)} -> 4505.6 | E5: {=SUM((Blotter!B$19:C$1013=C5)*(Blotter!R$19:R$1013)*1)} -> 9000 | F5: =IF(ISNUMBER(D5/E5),D5/E5,0) -> 0.50062222 | G5: {=IF(SUM((Blotter!C$19:C$1013=PLB!C5)*(Blotter!M$19:M$1013))=0,"C","O")} -> C | H5: =J4+D5 -> 1010781.1 | J5: =H5+I5 -> 1010781.1 | K5: =H5/J4-1 -> 0.0044775015 | L5: =(1+K5)*(1+L4)-1 -> 0.010781092 | M5: =O4-IF(G5="O",O4*1%,-D5) -> 1010781.1 | N5: =I5 -> 0 | O5: =M5+N5 -> 1010781.1 | P5: =M5/O4-1 -> 0.0044775015 | Q5: =(1+P5)*(1+Q4)-1 -> 0.010781092 | R5: =(1-1%)*(1+R4)-1 -> -0.0199 | T5: =B5 -> 45033 | U5: =C5 -> 2 | V5: Long Natural Gas Futures | W5: Major producers pulling back on drilling and completing wells | X5: 80% correction, extreme oversold, basing around $2
B6: =B5+7 -> 45040 | C6: =C5+1 -> 3 | D6: {=SUM((Blotter!C$19:C$1013=C6)*(Blotter!N$19:N$1013)*1)} -> -1753.56 | E6: {=SUM((Blotter!B$19:C$1013=C6)*(Blotter!R$19:R$1013)*1)} -> 8400 | F6: =IF(ISNUMBER(D6/E6),D6/E6,0) -> -0.20875714 | G6: {=IF(SUM((Blotter!C$19:C$1013=PLB!C6)*(Blotter!M$19:M$1013))=0,"C","O")} -> C | H6: =J5+D6 -> 1009027.5 | J6: =H6+I6 -> 1009027.5 | K6: =H6/J5-1 -> -0.0017348564 | L6: =(1+K6)*(1+L5)-1 -> 0.0090275321 | M6: =O5-IF(G6="O",O5*1%,-D6) -> 1009027.5 | N6: =I6 -> 0 | O6: =M6+N6 -> 1009027.5 | P6: =M6/O5-1 -> -0.0017348564 | Q6: =(1+P6)*(1+Q5)-1 -> 0.0090275321 | R6: =(1-1%)*(1+R5)-1 -> -0.029701 | T6: =B6 -> 45040 | U6: =C6 -> 3 | V6: Long Gasoline Futures | W6: OPEC cuts / OPEC production at 2003 levels / positive seasonality / US driving season | X6: Weekly 50% retracement / daily up trigger
B7: =B6+7 -> 45047 | C7: =C6+1 -> 4 | D7: {=SUM((Blotter!C$19:C$1013=C7)*(Blotter!N$19:N$1013)*1)} -> 0 | E7: {=SUM((Blotter!B$19:C$1013=C7)*(Blotter!R$19:R$1013)*1)} -> 0 | F7: =IF(ISNUMBER(D7/E7),D7/E7,0) -> 0 | G7: {=IF(SUM((Blotter!C$19:C$1013=PLB!C7)*(Blotter!M$19:M$1013))=0,"C","O")} -> C | H7: =J6+D7 -> 1009027.5 | J7: =H7+I7 -> 1009027.5 | K7: =H7/J6-1 -> 0 | L7: =(1+K7)*(1+L6)-1 -> 0.0090275321 | M7: =O6-IF(G7="O",O6*1%,-D7) -> 1009027.5 | N7: =I7 -> 0 | O7: =M7+N7 -> 1009027.5 | P7: =M7/O6-1 -> 0 | Q7: =(1+P7)*(1+Q6)-1 -> 0.0090275321 | R7: =(1-1%)*(1+R6)-1 -> -0.03940399 | T7: =B7 -> 45047 | U7: =C7 -> 4
B8: =B7+7 -> 45054 | C8: =C7+1 -> 5 | D8: {=SUM((Blotter!C$19:C$1013=C8)*(Blotter!N$19:N$1013)*1)} -> 11592.76 | E8: {=SUM((Blotter!B$19:C$1013=C8)*(Blotter!R$19:R$1013)*1)} -> 9100 | F8: =IF(ISNUMBER(D8/E8),D8/E8,0) -> 1.2739297 | G8: {=IF(SUM((Blotter!C$19:C$1013=PLB!C8)*(Blotter!M$19:M$1013))=0,"C","O")} -> C | H8: =J7+D8 -> 1020620.3 | J8: =H8+I8 -> 1020620.3 | K8: =H8/J7-1 -> 0.011489042 | L8: =(1+K8)*(1+L7)-1 -> 0.020620292 | M8: =O7-IF(G8="O",O7*1%,-D8) -> 1020620.3 | N8: =I8 -> 0 | O8: =M8+N8 -> 1020620.3 | P8: =M8/O7-1 -> 0.011489042 | Q8: =(1+P8)*(1+Q7)-1 -> 0.020620292 | R8: =(1-1%)*(1+R7)-1 -> -0.04900995 | T8: =B8 -> 45054 | U8: =C8 -> 5 | V8: Long Nasdaq Futures and Calls | W8: Solid earnings reports by mega-cap tech stocks | X8: QTR up trigger
B9: =B8+7 -> 45061 | C9: =C8+1 -> 6 | D9: {=SUM((Blotter!C$19:C$1013=C9)*(Blotter!N$19:N$1013)*1)} -> -16328.51 | E9: {=SUM((Blotter!B$19:C$1013=C9)*(Blotter!R$19:R$1013)*1)} -> 19950 | F9: =IF(ISNUMBER(D9/E9),D9/E9,0) -> -0.81847168 | G9: {=IF(SUM((Blotter!C$19:C$1013=PLB!C9)*(Blotter!M$19:M$1013))=0,"C","O")} -> C | H9: =J8+D9 -> 1004291.8 | J9: =H9+I9 -> 1004291.8 | K9: =H9/J8-1 -> -0.015998614 | L9: =(1+K9)*(1+L8)-1 -> 0.0042917821 | M9: =O8-IF(G9="O",O8*1%,-D9) -> 1004291.8 | N9: =I9 -> 0 | O9: =M9+N9 -> 1004291.8 | P9: =M9/O8-1 -> -0.015998614 | Q9: =(1+P9)*(1+Q8)-1 -> 0.0042917821 | R9: =(1-1%)*(1+R8)-1 -> -0.058519851 | T9: =B9 -> 45061 | U9: =C9 -> 6 | V9: Long Silver Futures | W9: Precious Metals strength on the back of Central Banks buying Gold and talks about global de-dollarization / ongoing supply deficit | X9: Weekly 50% retracement / rotation up from the $24 price area
B10: =B9+7 -> 45068 | C10: =C9+1 -> 7 | D10: {=SUM((Blotter!C$19:C$1013=C10)*(Blotter!N$19:N$1013)*1)} -> 0 | E10: {=SUM((Blotter!B$19:C$1013=C10)*(Blotter!R$19:R$1013)*1)} -> 0 | F10: =IF(ISNUMBER(D10/E10),D10/E10,0) -> 0 | G10: {=IF(SUM((Blotter!C$19:C$1013=PLB!C10)*(Blotter!M$19:M$1013))=0,"C","O")} -> C | H10: =J9+D10 -> 1004291.8 | J10: =H10+I10 -> 1004291.8 | K10: =H10/J9-1 -> 0 | L10: =(1+K10)*(1+L9)-1 -> 0.0042917821 | M10: =O9-IF(G10="O",O9*1%,-D10) -> 1004291.8 | N10: =I10 -> 0 | O10: =M10+N10 -> 1004291.8 | P10: =M10/O9-1 -> 0 | Q10: =(1+P10)*(1+Q9)-1 -> 0.0042917821 | R10: =(1-1%)*(1+R9)-1 -> -0.067934652 | T10: =B10 -> 45068 | U10: =C10 -> 7
B11: =B10+7 -> 45075 | C11: =C10+1 -> 8 | D11: {=SUM((Blotter!C$19:C$1013=C11)*(Blotter!N$19:N$1013)*1)} -> 21910.44 | E11: {=SUM((Blotter!B$19:C$1013=C11)*(Blotter!R$19:R$1013)*1)} -> 9000 | F11: =IF(ISNUMBER(D11/E11),D11/E11,0) -> 2.4344933 | G11: {=IF(SUM((Blotter!C$19:C$1013=PLB!C11)*(Blotter!M$19:M$1013))=0,"C","O")} -> C | H11: =J10+D11 -> 1026202.2 | J11: =H11+I11 -> 1026202.2 | K11: =H11/J10-1 -> 0.021816807 | L11: =(1+K11)*(1+L10)-1 -> 0.026202222 | M11: =O10-IF(G11="O",O10*1%,-D11) -> 1026202.2 | N11: =I11 -> 0 | O11: =M11+N11 -> 1026202.2 | P11: =M11/O10-1 -> 0.021816807 | Q11: =(1+P11)*(1+Q10)-1 -> 0.026202222 | R11: =(1-1%)*(1+R10)-1 -> -0.077255306 | T11: =B11 -> 45075 | U11: =C11 -> 8 | V11: Long Copper Futures | W11: Long-term shortage / declining production levels in Chile | X11: Weekly 78.6% retracement and 200SMA test / weekly up trigger
B12: =B11+7 -> 45082 | C12: =C11+1 -> 9 | D12: {=SUM((Blotter!C$19:C$1013=C12)*(Blotter!N$19:N$1013)*1)} -> 6501.268 | E12: {=SUM((Blotter!B$19:C$1013=C12)*(Blotter!R$19:R$1013)*1)} -> 9800 | F12: =IF(ISNUMBER(D12/E12),D12/E12,0) -> 0.66339469 | G12: {=IF(SUM((Blotter!C$19:C$1013=PLB!C12)*(Blotter!M$19:M$1013))=0,"C","O")} -> C | H12: =J11+D12 -> 1032703.5 | J12: =H12+I12 -> 1032703.5 | K12: =H12/J11-1 -> 0.0063352699 | L12: =(1+K12)*(1+L11)-1 -> 0.03270349 | M12: =O11-IF(G12="O",O11*1%,-D12) -> 1032703.5 | N12: =I12 -> 0 | O12: =M12+N12 -> 1032703.5 | P12: =M12/O11-1 -> 0.0063352699 | Q12: =(1+P12)*(1+Q11)-1 -> 0.03270349 | R12: =(1-1%)*(1+R11)-1 -> -0.086482753 | T12: =B12 -> 45082 | U12: =C12 -> 9 | V12: Long India ETF Calls | W12: India’s infrastructure boom, could become the third largest economy in a few years | X12: Bullish long-term set-up similar to the recent break-out in the Nikkei 225 / weekly doji + weekly up
B13: =B12+7 -> 45089 | C13: =C12+1 -> 10 | D13: {=SUM((Blotter!C$19:C$1013=C13)*(Blotter!N$19:N$1013)*1)} -> -1375.4986 | E13: {=SUM((Blotter!B$19:C$1013=C13)*(Blotter!R$19:R$1013)*1)} -> 3400 | F13: =IF(ISNUMBER(D13/E13),D13/E13,0) -> -0.40455841 | G13: {=IF(SUM((Blotter!C$19:C$1013=PLB!C13)*(Blotter!M$19:M$1013))=0,"C","O")} -> C | H13: =J12+D13 -> 1031328 | J13: =H13+I13 -> 1031328 | K13: =H13/J12-1 -> -0.0013319395 | L13: =(1+K13)*(1+L12)-1 -> 0.031327992 | M13: =O12-IF(G13="O",O12*1%,-D13) -> 1031328 | N13: =I13 -> 0 | O13: =M13+N13 -> 1031328 | P13: =M13/O12-1 -> -0.0013319395 | Q13: =(1+P13)*(1+Q12)-1 -> 0.031327992 | R13: =(1-1%)*(1+R12)-1 -> -0.095617925 | T13: =B13 -> 45089 | U13: =C13 -> 10 | V13: Long SPX Puts | W13: Short-term hedge against FOMC volatility
B14: =B13+7 -> 45096 | C14: =C13+1 -> 11 | D14: {=SUM((Blotter!C$19:C$1013=C14)*(Blotter!N$19:N$1013)*1)} -> 2782.86 | E14: {=SUM((Blotter!B$19:C$1013=C14)*(Blotter!R$19:R$1013)*1)} -> 8400 | F14: =IF(ISNUMBER(D14/E14),D14/E14,0) -> 0.33129286 | G14: {=IF(SUM((Blotter!C$19:C$1013=PLB!C14)*(Blotter!M$19:M$1013))=0,"C","O")} -> C | H14: =J13+D14 -> 1034110.9 | J14: =H14+I14 -> 1034110.9 | K14: =H14/J13-1 -> 0.0026983268 | L14: =(1+K14)*(1+L13)-1 -> 0.034110852 | M14: =O13-IF(G14="O",O13*1%,-D14) -> 1034110.9 | N14: =I14 -> 0 | O14: =M14+N14 -> 1034110.9 | P14: =M14/O13-1 -> 0.0026983268 | Q14: =(1+P14)*(1+Q13)-1 -> 0.034110852 | R14: =(1-1%)*(1+R13)-1 -> -0.10466175 | T14: =B14 -> 45096 | U14: =C14 -> 11 | V14: Long Gasoline Futures | W14: US economy hard landing probability decreasing / OPEC production at 2003 levels / positive seasonality and US driving season | X14: Weekly horizontal triangle trigger > 2.75
B15: =B14+7 -> 45103 | C15: =C14+1 -> 12 | D15: {=SUM((Blotter!C$19:C$1013=C15)*(Blotter!N$19:N$1013)*1)} -> 0 | E15: {=SUM((Blotter!B$19:C$1013=C15)*(Blotter!R$19:R$1013)*1)} -> 0 | F15: =IF(ISNUMBER(D15/E15),D15/E15,0) -> 0 | G15: {=IF(SUM((Blotter!C$19:C$1013=PLB!C15)*(Blotter!M$19:M$1013))=0,"C","O")} -> C | H15: =J14+D15 -> 1034110.9 | J15: =H15+I15 -> 1034110.9 | K15: =H15/J14-1 -> 0 | L15: =(1+K15)*(1+L14)-1 -> 0.034110852 | M15: =O14-IF(G15="O",O14*1%,-D15) -> 1034110.9 | N15: =I15 -> 0 | O15: =M15+N15 -> 1034110.9 | P15: =M15/O14-1 -> 0 | Q15: =(1+P15)*(1+Q14)-1 -> 0.034110852 | R15: =(1-1%)*(1+R14)-1 -> -0.11361513 | T15: =B15 -> 45103 | U15: =C15 -> 12
B16: =B15+7 -> 45110 | C16: =C15+1 -> 13 | D16: {=SUM((Blotter!C$19:C$1013=C16)*(Blotter!N$19:N$1013)*1)} -> 14904.96 | E16: {=SUM((Blotter!B$19:C$1013=C16)*(Blotter!R$19:R$1013)*1)} -> 7800 | F16: =IF(ISNUMBER(D16/E16),D16/E16,0) -> 1.9108923 | G16: {=IF(SUM((Blotter!C$19:C$1013=PLB!C16)*(Blotter!M$19:M$1013))=0,"C","O")} -> C | H16: =J15+D16 -> 1049015.8 | J16: =H16+I16 -> 1049015.8 | K16: =H16/J15-1 -> 0.01441331 | L16: =(1+K16)*(1+L15)-1 -> 0.049015812 | M16: =O15-IF(G16="O",O15*1%,-D16) -> 1049015.8 | N16: =I16 -> 0 | O16: =M16+N16 -> 1049015.8 | P16: =M16/O15-1 -> 0.01441331 | Q16: =(1+P16)*(1+Q15)-1 -> 0.049015812 | R16: =(1-1%)*(1+R15)-1 -> -0.12247898 | T16: =B16 -> 45110 | U16: =C16 -> 13 | V16: Long Corn Futures and Calls | W16: Notable soil moisture deterioration in the core US Corn Belt over the last four weeks / US Crops in Drought Area Rise to 70%: USDA | X16: Monthly bull flag / first break-out attempt rejection and entry at lower price range
B17: =B16+7 -> 45117 | C17: =C16+1 -> 14 | D17: {=SUM((Blotter!C$19:C$1013=C17)*(Blotter!N$19:N$1013)*1)} -> 13867.28 | E17: {=SUM((Blotter!B$19:C$1013=C17)*(Blotter!R$19:R$1013)*1)} -> 9878.4 | F17: =IF(ISNUMBER(D17/E17),D17/E17,0) -> 1.4037982 | G17: {=IF(SUM((Blotter!C$19:C$1013=PLB!C17)*(Blotter!M$19:M$1013))=0,"C","O")} -> C | H17: =J16+D17 -> 1062883.1 | J17: =H17+I17 -> 1062883.1 | K17: =H17/J16-1 -> 0.013219324 | L17: =(1+K17)*(1+L16)-1 -> 0.062883092 | M17: =O16-IF(G17="O",O16*1%,-D17) -> 1062883.1 | N17: =I17 -> 0 | O17: =M17+N17 -> 1062883.1 | P17: =M17/O16-1 -> 0.013219324 | Q17: =(1+P17)*(1+Q16)-1 -> 0.062883092 | R17: =(1-1%)*(1+R16)-1 -> -0.13125419 | T17: =B17 -> 45117 | U17: =C17 -> 14 | V17: Long Sugar Futures | W17: Large downward crop revisions in the key producing countries (India, Thailand, China and Pakistan) | X17: 61.8% retracement of the YTD move and bounce / daily bull flag break-out
B18: =B17+7 -> 45124 | C18: =C17+1 -> 15 | D18: {=SUM((Blotter!C$19:C$1013=C18)*(Blotter!N$19:N$1013)*1)} -> 0 | E18: {=SUM((Blotter!B$19:C$1013=C18)*(Blotter!R$19:R$1013)*1)} -> 0 | F18: =IF(ISNUMBER(D18/E18),D18/E18,0) -> 0 | G18: {=IF(SUM((Blotter!C$19:C$1013=PLB!C18)*(Blotter!M$19:M$1013))=0,"C","O")} -> C | H18: =J17+D18 -> 1062883.1 | J18: =H18+I18 -> 1062883.1 | K18: =H18/J17-1 -> 0 | L18: =(1+K18)*(1+L17)-1 -> 0.062883092 | M18: =O17-IF(G18="O",O17*1%,-D18) -> 1062883.1 | N18: =I18 -> 0 | O18: =M18+N18 -> 1062883.1 | P18: =M18/O17-1 -> 0 | Q18: =(1+P18)*(1+Q17)-1 -> 0.062883092 | R18: =(1-1%)*(1+R17)-1 -> -0.13994165 | T18: =B18 -> 45124 | U18: =C18 -> 15
B19: =B18+7 -> 45131 | C19: =C18+1 -> 16 | D19: {=SUM((Blotter!C$19:C$1013=C19)*(Blotter!N$19:N$1013)*1)} -> 301.86 | E19: {=SUM((Blotter!B$19:C$1013=C19)*(Blotter!R$19:R$1013)*1)} -> 9900 | F19: =IF(ISNUMBER(D19/E19),D19/E19,0) -> 0.030490909 | G19: {=IF(SUM((Blotter!C$19:C$1013=PLB!C19)*(Blotter!M$19:M$1013))=0,"C","O")} -> C | H19: =J18+D19 -> 1063185 | J19: =H19+I19 -> 1063185 | K19: =H19/J18-1 -> 0.00028400113 | L19: =(1+K19)*(1+L18)-1 -> 0.063184952 | M19: =O18-IF(G19="O",O18*1%,-D19) -> 1063185 | N19: =I19 -> 0 | O19: =M19+N19 -> 1063185 | P19: =M19/O18-1 -> 0.00028400113 | Q19: =(1+P19)*(1+Q18)-1 -> 0.063184952 | R19: =(1-1%)*(1+R18)-1 -> -0.14854223 | T19: =B19 -> 45131 | U19: =C19 -> 16 | V19: Long Coffee Futures | W19: Extreme weather conditions (El Nino) could hit major producers like Vietnam and Indonesia. Brazil’s crop has also been impacted by drought | X19: 3x weekly up @ 200SMA
B20: =B19+7 -> 45138 | C20: =C19+1 -> 17 | D20: {=SUM((Blotter!C$19:C$1013=C20)*(Blotter!N$19:N$1013)*1)} -> 39435.613 | E20: {=SUM((Blotter!B$19:C$1013=C20)*(Blotter!R$19:R$1013)*1)} -> 8700 | F20: =IF(ISNUMBER(D20/E20),D20/E20,0) -> 4.5328291 | G20: {=IF(SUM((Blotter!C$19:C$1013=PLB!C20)*(Blotter!M$19:M$1013))=0,"C","O")} -> C | H20: =J19+D20 -> 1102620.6 | J20: =H20+I20 -> 1102620.6 | K20: =H20/J19-1 -> 0.03709196 | L20: =(1+K20)*(1+L19)-1 -> 0.10262057 | M20: =O19-IF(G20="O",O19*1%,-D20) -> 1102620.6 | N20: =I20 -> 0 | O20: =M20+N20 -> 1102620.6 | P20: =M20/O19-1 -> 0.03709196 | Q20: =(1+P20)*(1+Q19)-1 -> 0.10262057 | R20: =(1-1%)*(1+R19)-1 -> -0.15705681 | T20: =B20 -> 45138 | U20: =C20 -> 17 | V20: Long SPX Put Spread | W20: Hedge Funds ‘Throwing In Towel’ on short bets / overbought on multiple time-frames / US10Y breaking above 4% | X20: weekly RSI = 70 / 10 weekly candles from 9SMA / daily down trigger
B21: =B20+7 -> 45145 | C21: =C20+1 -> 18 | D21: {=SUM((Blotter!C$19:C$1013=C21)*(Blotter!N$19:N$1013)*1)} -> 0 | E21: {=SUM((Blotter!B$19:C$1013=C21)*(Blotter!R$19:R$1013)*1)} -> 0 | F21: =IF(ISNUMBER(D21/E21),D21/E21,0) -> 0 | G21: {=IF(SUM((Blotter!C$19:C$1013=PLB!C21)*(Blotter!M$19:M$1013))=0,"C","O")} -> C | H21: =J20+D21 -> 1102620.6 | J21: =H21+I21 -> 1102620.6 | K21: =H21/J20-1 -> 0 | L21: =(1+K21)*(1+L20)-1 -> 0.10262057 | M21: =O20-IF(G21="O",O20*1%,-D21) -> 1102620.6 | N21: =I21 -> 0 | O21: =M21+N21 -> 1102620.6 | P21: =M21/O20-1 -> 0 | Q21: =(1+P21)*(1+Q20)-1 -> 0.10262057 | R21: =(1-1%)*(1+R20)-1 -> -0.16548624 | T21: =B21 -> 45145 | U21: =C21 -> 18
B22: =B21+7 -> 45152 | C22: =C21+1 -> 19 | D22: {=SUM((Blotter!C$19:C$1013=C22)*(Blotter!N$19:N$1013)*1)} -> 0 | E22: {=SUM((Blotter!B$19:C$1013=C22)*(Blotter!R$19:R$1013)*1)} -> 0 | F22: =IF(ISNUMBER(D22/E22),D22/E22,0) -> 0 | G22: {=IF(SUM((Blotter!C$19:C$1013=PLB!C22)*(Blotter!M$19:M$1013))=0,"C","O")} -> C | H22: =J21+D22 -> 1102620.6 | J22: =H22+I22 -> 1102620.6 | K22: =H22/J21-1 -> 0 | L22: =(1+K22)*(1+L21)-1 -> 0.10262057 | M22: =O21-IF(G22="O",O21*1%,-D22) -> 1102620.6 | N22: =I22 -> 0 | O22: =M22+N22 -> 1102620.6 | P22: =M22/O21-1 -> 0 | Q22: =(1+P22)*(1+Q21)-1 -> 0.10262057 | R22: =(1-1%)*(1+R21)-1 -> -0.17383138 | T22: =B22 -> 45152 | U22: =C22 -> 19
B23: =B22+7 -> 45159 | C23: =C22+1 -> 20 | D23: {=SUM((Blotter!C$19:C$1013=C23)*(Blotter!N$19:N$1013)*1)} -> 0 | E23: {=SUM((Blotter!B$19:C$1013=C23)*(Blotter!R$19:R$1013)*1)} -> 0 | F23: =IF(ISNUMBER(D23/E23),D23/E23,0) -> 0 | G23: {=IF(SUM((Blotter!C$19:C$1013=PLB!C23)*(Blotter!M$19:M$1013))=0,"C","O")} -> C | H23: =J22+D23 -> 1102620.6 | J23: =H23+I23 -> 1102620.6 | K23: =H23/J22-1 -> 0 | L23: =(1+K23)*(1+L22)-1 -> 0.10262057 | M23: =O22-IF(G23="O",O22*1%,-D23) -> 1102620.6 | N23: =I23 -> 0 | O23: =M23+N23 -> 1102620.6 | P23: =M23/O22-1 -> 0 | Q23: =(1+P23)*(1+Q22)-1 -> 0.10262057 | R23: =(1-1%)*(1+R22)-1 -> -0.18209306 | T23: =B23 -> 45159 | U23: =C23 -> 20
B24: =B23+7 -> 45166 | C24: =C23+1 -> 21 | D24: {=SUM((Blotter!C$19:C$1013=C24)*(Blotter!N$19:N$1013)*1)} -> 20281.04 | E24: {=SUM((Blotter!B$19:C$1013=C24)*(Blotter!R$19:R$1013)*1)} -> 9520 | F24: =IF(ISNUMBER(D24/E24),D24/E24,0) -> 2.1303613 | G24: {=IF(SUM((Blotter!C$19:C$1013=PLB!C24)*(Blotter!M$19:M$1013))=0,"C","O")} -> C | H24: =J23+D24 -> 1122901.6 | J24: =H24+I24 -> 1122901.6 | K24: =H24/J23-1 -> 0.01839349 | L24: =(1+K24)*(1+L23)-1 -> 0.12290161 | M24: =O23-IF(G24="O",O23*1%,-D24) -> 1122901.6 | N24: =I24 -> 0 | O24: =M24+N24 -> 1122901.6 | P24: =M24/O23-1 -> 0.01839349 | Q24: =(1+P24)*(1+Q23)-1 -> 0.12290161 | R24: =(1-1%)*(1+R23)-1 -> -0.19027213 | T24: =B24 -> 45166 | U24: =C24 -> 21 | V24: Long WTI Futures | W24: Saudi Arabia and Russia output cuts / China’s potential new stimulus plan | X24: Weekly bull flag / weekly up > 81.75 / TP: 1.618% = 88.50
B25: =B24+7 -> 45173 | C25: =C24+1 -> 22 | D25: {=SUM((Blotter!C$19:C$1013=C25)*(Blotter!N$19:N$1013)*1)} -> 0 | E25: {=SUM((Blotter!B$19:C$1013=C25)*(Blotter!R$19:R$1013)*1)} -> 0 | F25: =IF(ISNUMBER(D25/E25),D25/E25,0) -> 0 | G25: {=IF(SUM((Blotter!C$19:C$1013=PLB!C25)*(Blotter!M$19:M$1013))=0,"C","O")} -> C | H25: =J24+D25 -> 1122901.6 | J25: =H25+I25 -> 1122901.6 | K25: =H25/J24-1 -> 0 | L25: =(1+K25)*(1+L24)-1 -> 0.12290161 | M25: =O24-IF(G25="O",O24*1%,-D25) -> 1122901.6 | N25: =I25 -> 0 | O25: =M25+N25 -> 1122901.6 | P25: =M25/O24-1 -> 0 | Q25: =(1+P25)*(1+Q24)-1 -> 0.12290161 | R25: =(1-1%)*(1+R24)-1 -> -0.19836941 | T25: =B25 -> 45173 | U25: =C25 -> 22
B26: =B25+7 -> 45180 | C26: =C25+1 -> 23 | D26: {=SUM((Blotter!C$19:C$1013=C26)*(Blotter!N$19:N$1013)*1)} -> 0 | E26: {=SUM((Blotter!B$19:C$1013=C26)*(Blotter!R$19:R$1013)*1)} -> 0 | F26: =IF(ISNUMBER(D26/E26),D26/E26,0) -> 0 | G26: {=IF(SUM((Blotter!C$19:C$1013=PLB!C26)*(Blotter!M$19:M$1013))=0,"C","O")} -> C | H26: =J25+D26 -> 1122901.6 | J26: =H26+I26 -> 1122901.6 | K26: =H26/J25-1 -> 0 | L26: =(1+K26)*(1+L25)-1 -> 0.12290161 | M26: =O25-IF(G26="O",O25*1%,-D26) -> 1122901.6 | N26: =I26 -> 0 | O26: =M26+N26 -> 1122901.6 | P26: =M26/O25-1 -> 0 | Q26: =(1+P26)*(1+Q25)-1 -> 0.12290161 | R26: =(1-1%)*(1+R25)-1 -> -0.20638572 | T26: =B26 -> 45180 | U26: =C26 -> 23
B27: =B26+7 -> 45187 | C27: =C26+1 -> 24 | D27: {=SUM((Blotter!C$19:C$1013=C27)*(Blotter!N$19:N$1013)*1)} -> -1779.7 | E27: {=SUM((Blotter!B$19:C$1013=C27)*(Blotter!R$19:R$1013)*1)} -> 5000 | F27: =IF(ISNUMBER(D27/E27),D27/E27,0) -> -0.35594 | G27: {=IF(SUM((Blotter!C$19:C$1013=PLB!C27)*(Blotter!M$19:M$1013))=0,"C","O")} -> C | H27: =J26+D27 -> 1121121.9 | J27: =H27+I27 -> 1121121.9 | K27: =H27/J26-1 -> -0.0015849118 | L27: =(1+K27)*(1+L26)-1 -> 0.12112191 | M27: =O26-IF(G27="O",O26*1%,-D27) -> 1121121.9 | N27: =I27 -> 0 | O27: =M27+N27 -> 1121121.9 | P27: =M27/O26-1 -> -0.0015849118 | Q27: =(1+P27)*(1+Q26)-1 -> 0.12112191 | R27: =(1-1%)*(1+R26)-1 -> -0.21432186 | T27: =B27 -> 45187 | U27: =C27 -> 24 | V27: Long Cotton Futures | W27: US expected to harvest smallest crop since 2015, import from China expected to rebound (USDA) | X27: 11 months consolidation / upper boundary $88-90 / Cocoa recent break-out analog
B28: =B27+7 -> 45194 | C28: =C27+1 -> 25 | D28: {=SUM((Blotter!C$19:C$1013=C28)*(Blotter!N$19:N$1013)*1)} -> 0 | E28: {=SUM((Blotter!B$19:C$1013=C28)*(Blotter!R$19:R$1013)*1)} -> 0 | F28: =IF(ISNUMBER(D28/E28),D28/E28,0) -> 0 | G28: {=IF(SUM((Blotter!C$19:C$1013=PLB!C28)*(Blotter!M$19:M$1013))=0,"C","O")} -> C | H28: =J27+D28 -> 1121121.9 | J28: =H28+I28 -> 1121121.9 | K28: =H28/J27-1 -> 0 | L28: =(1+K28)*(1+L27)-1 -> 0.12112191 | M28: =O27-IF(G28="O",O27*1%,-D28) -> 1121121.9 | N28: =I28 -> 0 | O28: =M28+N28 -> 1121121.9 | P28: =M28/O27-1 -> 0 | Q28: =(1+P28)*(1+Q27)-1 -> 0.12112191 | R28: =(1-1%)*(1+R27)-1 -> -0.22217864 | T28: =B28 -> 45194 | U28: =C28 -> 25
B29: =B28+7 -> 45201 | C29: =C28+1 -> 26 | D29: {=SUM((Blotter!C$19:C$1013=C29)*(Blotter!N$19:N$1013)*1)} -> 0 | E29: {=SUM((Blotter!B$19:C$1013=C29)*(Blotter!R$19:R$1013)*1)} -> 0 | F29: =IF(ISNUMBER(D29/E29),D29/E29,0) -> 0 | G29: {=IF(SUM((Blotter!C$19:C$1013=PLB!C29)*(Blotter!M$19:M$1013))=0,"C","O")} -> C | H29: =J28+D29 -> 1121121.9 | I29: 1000000 | J29: =H29+I29 -> 2121121.9 | K29: =H29/J28-1 -> 0 | L29: =(1+K29)*(1+L28)-1 -> 0.12112191 | M29: =O28-IF(G29="O",O28*1%,-D29) -> 1121121.9 | N29: =I29 -> 1000000 | O29: =M29+N29 -> 2121121.9 | P29: =M29/O28-1 -> 0 | Q29: =(1+P29)*(1+Q28)-1 -> 0.12112191 | R29: =(1-1%)*(1+R28)-1 -> -0.22995685 | T29: =B29 -> 45201 | U29: =C29 -> 26
B30: =B29+7 -> 45208 | C30: =C29+1 -> 27 | D30: {=SUM((Blotter!C$19:C$1013=C30)*(Blotter!N$19:N$1013)*1)} -> 9915.2 | E30: {=SUM((Blotter!B$19:C$1013=C30)*(Blotter!R$19:R$1013)*1)} -> 8000 | F30: =IF(ISNUMBER(D30/E30),D30/E30,0) -> 1.2394 | G30: {=IF(SUM((Blotter!C$19:C$1013=PLB!C30)*(Blotter!M$19:M$1013))=0,"C","O")} -> C | H30: =J29+D30 -> 2131037.1 | J30: =H30+I30 -> 2131037.1 | K30: =H30/J29-1 -> 0.0046745074 | L30: =(1+K30)*(1+L29)-1 -> 0.1263626 | M30: =O29-IF(G30="O",O29*1%,-D30) -> 2131037.1 | N30: =I30 -> 0 | O30: =M30+N30 -> 2131037.1 | P30: =M30/O29-1 -> 0.0046745074 | Q30: =(1+P30)*(1+Q29)-1 -> 0.1263626 | R30: =(1-1%)*(1+R29)-1 -> -0.23765729 | T30: =B30 -> 45208 | U30: =C30 -> 27 | V30: Long WTI Call Spread | W30: Israel-Palestine war / Saudi Arabia and Russia output cuts | X30: Retracement of the gap up (gap fill) after the war announcement and daily up
B31: =B30+7 -> 45215 | C31: =C30+1 -> 28 | D31: {=SUM((Blotter!C$19:C$1013=C31)*(Blotter!N$19:N$1013)*1)} -> 24861.6 | E31: {=SUM((Blotter!B$19:C$1013=C31)*(Blotter!R$19:R$1013)*1)} -> 19562.5 | F31: =IF(ISNUMBER(D31/E31),D31/E31,0) -> 1.2708805 | G31: {=IF(SUM((Blotter!C$19:C$1013=PLB!C31)*(Blotter!M$19:M$1013))=0,"C","O")} -> C | H31: =J30+D31 -> 2155898.7 | J31: =H31+I31 -> 2155898.7 | K31: =H31/J30-1 -> 0.011666432 | L31: =(1+K31)*(1+L30)-1 -> 0.13950323 | M31: =O30-IF(G31="O",O30*1%,-D31) -> 2155898.7 | N31: =I31 -> 0 | O31: =M31+N31 -> 2155898.7 | P31: =M31/O30-1 -> 0.011666432 | Q31: =(1+P31)*(1+Q30)-1 -> 0.13950323 | R31: =(1-1%)*(1+R30)-1 -> -0.24528071 | T31: =B31 -> 45215 | U31: =C31 -> 28 | V31: Long SPX Futures Reverse Call Spread | W31: Core inflation below 2%, no more rate hikes from the Fed / extreme bearish positioning / positive seasonality | X31: ABC summer correction completed / daily bull flag breakout (pre) | Z31: Long Coffee Futures | AA31: Extreme weather conditions (El Nino) could hit major producers like Vietnam and Indonesia. Brazil’s crop has also been impacted by drought | AB31: Weekly double bottom / weekly bull flag breakout (pre)
B32: =B31+7 -> 45222 | C32: =C31+1 -> 29 | D32: {=SUM((Blotter!C$19:C$1013=C32)*(Blotter!N$19:N$1013)*1)} -> 0 | E32: {=SUM((Blotter!B$19:C$1013=C32)*(Blotter!R$19:R$1013)*1)} -> 0 | F32: =IF(ISNUMBER(D32/E32),D32/E32,0) -> 0 | G32: {=IF(SUM((Blotter!C$19:C$1013=PLB!C32)*(Blotter!M$19:M$1013))=0,"C","O")} -> C | H32: =J31+D32 -> 2155898.7 | J32: =H32+I32 -> 2155898.7 | K32: =H32/J31-1 -> 0 | L32: =(1+K32)*(1+L31)-1 -> 0.13950323 | M32: =O31-IF(G32="O",O31*1%,-D32) -> 2155898.7 | N32: =I32 -> 0 | O32: =M32+N32 -> 2155898.7 | P32: =M32/O31-1 -> 0 | Q32: =(1+P32)*(1+Q31)-1 -> 0.13950323 | R32: =(1-1%)*(1+R31)-1 -> -0.25282791 | T32: =B32 -> 45222 | U32: =C32 -> 29
B33: =B32+7 -> 45229 | C33: =C32+1 -> 30 | D33: {=SUM((Blotter!C$19:C$1013=C33)*(Blotter!N$19:N$1013)*1)} -> 0 | E33: {=SUM((Blotter!B$19:C$1013=C33)*(Blotter!R$19:R$1013)*1)} -> 0 | F33: =IF(ISNUMBER(D33/E33),D33/E33,0) -> 0 | G33: {=IF(SUM((Blotter!C$19:C$1013=PLB!C33)*(Blotter!M$19:M$1013))=0,"C","O")} -> C | H33: =J32+D33 -> 2155898.7 | J33: =H33+I33 -> 2155898.7 | K33: =H33/J32-1 -> 0 | L33: =(1+K33)*(1+L32)-1 -> 0.13950323 | M33: =O32-IF(G33="O",O32*1%,-D33) -> 2155898.7 | N33: =I33 -> 0 | O33: =M33+N33 -> 2155898.7 | P33: =M33/O32-1 -> 0 | Q33: =(1+P33)*(1+Q32)-1 -> 0.13950323 | R33: =(1-1%)*(1+R32)-1 -> -0.26029963 | T33: =B33 -> 45229 | U33: =C33 -> 30
B34: =B33+7 -> 45236 | C34: =C33+1 -> 31 | D34: {=SUM((Blotter!C$19:C$1013=C34)*(Blotter!N$19:N$1013)*1)} -> -870.9355 | E34: {=SUM((Blotter!B$19:C$1013=C34)*(Blotter!R$19:R$1013)*1)} -> 11490 | F34: =IF(ISNUMBER(D34/E34),D34/E34,0) -> -0.075799434 | G34: {=IF(SUM((Blotter!C$19:C$1013=PLB!C34)*(Blotter!M$19:M$1013))=0,"C","O")} -> C | H34: =J33+D34 -> 2155027.8 | J34: =H34+I34 -> 2155027.8 | K34: =H34/J33-1 -> -0.00040397793 | L34: =(1+K34)*(1+L33)-1 -> 0.1390429 | M34: =O33-IF(G34="O",O33*1%,-D34) -> 2155027.8 | N34: =I34 -> 0 | O34: =M34+N34 -> 2155027.8 | P34: =M34/O33-1 -> -0.00040397793 | Q34: =(1+P34)*(1+Q33)-1 -> 0.1390429 | R34: =(1-1%)*(1+R33)-1 -> -0.26769663 | T34: =B34 -> 45236 | U34: =C34 -> 31 | V34: Long Uranium ETF Call Spread | W34: Structural long-term supply deficit / geopolitical risk: Niger coup, ban on Russian nuclear fuel | X34: Monthly bull flag breakout / TP 161.8% = 40
B35: =B34+7 -> 45243 | C35: =C34+1 -> 32 | D35: {=SUM((Blotter!C$19:C$1013=C35)*(Blotter!N$19:N$1013)*1)} -> -7556.4 | E35: {=SUM((Blotter!B$19:C$1013=C35)*(Blotter!R$19:R$1013)*1)} -> 17600 | F35: =IF(ISNUMBER(D35/E35),D35/E35,0) -> -0.42934091 | G35: {=IF(SUM((Blotter!C$19:C$1013=PLB!C35)*(Blotter!M$19:M$1013))=0,"C","O")} -> C | H35: =J34+D35 -> 2147471.4 | J35: =H35+I35 -> 2147471.4 | K35: =H35/J34-1 -> -0.0035064049 | L35: =(1+K35)*(1+L34)-1 -> 0.13504895 | M35: =O34-IF(G35="O",O34*1%,-D35) -> 2147471.4 | N35: =I35 -> 0 | O35: =M35+N35 -> 2147471.4 | P35: =M35/O34-1 -> -0.0035064049 | Q35: =(1+P35)*(1+Q34)-1 -> 0.13504895 | R35: =(1-1%)*(1+R34)-1 -> -0.27501966 | T35: =B35 -> 45243 | U35: =C35 -> 32 | V35: Long Lean Hogs Call Spread | W35: U.S. pork exports are up 14% YoY. U.S. pork is the cheapest in the world, while EU prices are near record high. The U.S. pork industry is expected to gain global market share | X35: Weekly bull flag breakout (adjusted chart) | Y35: https://www.nationalhogfarmer.com/market-news/searching-for-a-low
B36: =B35+7 -> 45250 | C36: =C35+1 -> 33 | D36: {=SUM((Blotter!C$19:C$1013=C36)*(Blotter!N$19:N$1013)*1)} -> 0 | E36: {=SUM((Blotter!B$19:C$1013=C36)*(Blotter!R$19:R$1013)*1)} -> 0 | F36: =IF(ISNUMBER(D36/E36),D36/E36,0) -> 0 | G36: {=IF(SUM((Blotter!C$19:C$1013=PLB!C36)*(Blotter!M$19:M$1013))=0,"C","O")} -> C | H36: =J35+D36 -> 2147471.4 | J36: =H36+I36 -> 2147471.4 | K36: =H36/J35-1 -> 0 | L36: =(1+K36)*(1+L35)-1 -> 0.13504895 | M36: =O35-IF(G36="O",O35*1%,-D36) -> 2147471.4 | N36: =I36 -> 0 | O36: =M36+N36 -> 2147471.4 | P36: =M36/O35-1 -> 0 | Q36: =(1+P36)*(1+Q35)-1 -> 0.13504895 | R36: =(1-1%)*(1+R35)-1 -> -0.28226947 | T36: =B36 -> 45250 | U36: =C36 -> 33
B37: =B36+7 -> 45257 | C37: =C36+1 -> 34 | D37: {=SUM((Blotter!C$19:C$1013=C37)*(Blotter!N$19:N$1013)*1)} -> -16467.4 | E37: {=SUM((Blotter!B$19:C$1013=C37)*(Blotter!R$19:R$1013)*1)} -> 19598 | F37: =IF(ISNUMBER(D37/E37),D37/E37,0) -> -0.84025921 | G37: {=IF(SUM((Blotter!C$19:C$1013=PLB!C37)*(Blotter!M$19:M$1013))=0,"C","O")} -> C | H37: =J36+D37 -> 2131004 | J37: =H37+I37 -> 2131004 | K37: =H37/J36-1 -> -0.0076682745 | L37: =(1+K37)*(1+L36)-1 -> 0.12634508 | M37: =O36-IF(G37="O",O36*1%,-D37) -> 2131004 | N37: =I37 -> 0 | O37: =M37+N37 -> 2131004 | P37: =M37/O36-1 -> -0.0076682745 | Q37: =(1+P37)*(1+Q36)-1 -> 0.12634508 | R37: =(1-1%)*(1+R36)-1 -> -0.28944677 | T37: =B37 -> 45257 | U37: =C37 -> 34 | V37: Long WTI and Gasoline Futures | W37: OPEC discussing a preliminary agreement for an additional cut of more than 1mbd | X37: CL: weekly up after $20 retracement / RB: 3x weekly up
B38: =B37+7 -> 45264 | C38: =C37+1 -> 35 | D38: {=SUM((Blotter!C$19:C$1013=C38)*(Blotter!N$19:N$1013)*1)} -> -19572.01 | E38: {=SUM((Blotter!B$19:C$1013=C38)*(Blotter!R$19:R$1013)*1)} -> 20721.735 | F38: =IF(ISNUMBER(D38/E38),D38/E38,0) -> -0.94451599 | G38: {=IF(SUM((Blotter!C$19:C$1013=PLB!C38)*(Blotter!M$19:M$1013))=0,"C","O")} -> C | H38: =J37+D38 -> 2111432 | J38: =H38+I38 -> 2111432 | K38: =H38/J37-1 -> -0.0091844082 | L38: =(1+K38)*(1+L37)-1 -> 0.11600027 | M38: =O37-IF(G38="O",O37*1%,-D38) -> 2111432 | N38: =I38 -> 0 | O38: =M38+N38 -> 2111432 | P38: =M38/O37-1 -> -0.0091844082 | Q38: =(1+P38)*(1+Q37)-1 -> 0.11600027 | R38: =(1-1%)*(1+R37)-1 -> -0.29655231 | T38: =B38 -> 45264 | U38: =C38 -> 35 | V38: Long SAVE Call Spread | W38: JetBlue's acquisition of Spirit Airlines: end of the anti-trust trial to block the merger by US DoJ / market pricing a significant discount to bid price (ca. $29)
B39: =B38+7 -> 45271 | C39: =C38+1 -> 36 | D39: {=SUM((Blotter!C$19:C$1013=C39)*(Blotter!N$19:N$1013)*1)} -> 46083.36 | E39: {=SUM((Blotter!B$19:C$1013=C39)*(Blotter!R$19:R$1013)*1)} -> 18720 | F39: =IF(ISNUMBER(D39/E39),D39/E39,0) -> 2.4617179 | G39: {=IF(SUM((Blotter!C$19:C$1013=PLB!C39)*(Blotter!M$19:M$1013))=0,"C","O")} -> C | H39: =J38+D39 -> 2157515.3 | J39: =H39+I39 -> 2157515.3 | K39: =H39/J38-1 -> 0.021825643 | L39: =(1+K39)*(1+L38)-1 -> 0.14035769 | M39: =O38-IF(G39="O",O38*1%,-D39) -> 2157515.3 | N39: =I39 -> 0 | O39: =M39+N39 -> 2157515.3 | P39: =M39/O38-1 -> 0.021825643 | Q39: =(1+P39)*(1+Q38)-1 -> 0.14035769 | R39: =(1-1%)*(1+R38)-1 -> -0.30358678 | T39: =B39 -> 45271 | U39: =C39 -> 36 | V39: Long Natural Gas Futures | W39: Extreme bearish sentiment, mean reversion trade. Warmer weather forecasts and elevated production / delay of Golden Pass, much of the structural growth the market has been counting on has been pushed back further | X39: Extreme overbought after break-down below $3 / daily RSI = 21 / daily up trigger
B40: =B39+7 -> 45278 | C40: =C39+1 -> 37 | D40: {=SUM((Blotter!C$19:C$1013=C40)*(Blotter!N$19:N$1013)*1)} -> 30999.22 | E40: {=SUM((Blotter!B$19:C$1013=C40)*(Blotter!R$19:R$1013)*1)} -> 17700 | F40: =IF(ISNUMBER(D40/E40),D40/E40,0) -> 1.7513684 | G40: {=IF(SUM((Blotter!C$19:C$1013=PLB!C40)*(Blotter!M$19:M$1013))=0,"C","O")} -> C | H40: =J39+D40 -> 2188514.5 | J40: =H40+I40 -> 2188514.5 | K40: =H40/J39-1 -> 0.014368018 | L40: =(1+K40)*(1+L39)-1 -> 0.15674237 | M40: =O39-IF(G40="O",O39*1%,-D40) -> 2188514.5 | N40: =I40 -> 0 | O40: =M40+N40 -> 2188514.5 | P40: =M40/O39-1 -> 0.014368018 | Q40: =(1+P40)*(1+Q39)-1 -> 0.15674237 | R40: =(1-1%)*(1+R39)-1 -> -0.31055091 | T40: =B40 -> 45278 | U40: =C40 -> 37 | V40: Long Copper Futures | W40: Weaker dollar and lower rates headwind / China's stock market lowest valuation in a decade, potential oversold rebound (13D) | X40: Monthly bull flag / 3x weekly up / CTL trade + COT analysis
B41: =B40+7 -> 45285 | C41: =C40+1 -> 38 | D41: {=SUM((Blotter!C$19:C$1013=C41)*(Blotter!N$19:N$1013)*1)} -> 0 | E41: {=SUM((Blotter!B$19:C$1013=C41)*(Blotter!R$19:R$1013)*1)} -> 0 | F41: =IF(ISNUMBER(D41/E41),D41/E41,0) -> 0 | G41: {=IF(SUM((Blotter!C$19:C$1013=PLB!C41)*(Blotter!M$19:M$1013))=0,"C","O")} -> C | H41: =J40+D41 -> 2188514.5 | J41: =H41+I41 -> 2188514.5 | K41: =H41/J40-1 -> 0 | L41: =(1+K41)*(1+L40)-1 -> 0.15674237 | M41: =O40-IF(G41="O",O40*1%,-D41) -> 2188514.5 | N41: =I41 -> 0 | O41: =M41+N41 -> 2188514.5 | P41: =M41/O40-1 -> 0 | Q41: =(1+P41)*(1+Q40)-1 -> 0.15674237 | R41: =(1-1%)*(1+R40)-1 -> -0.3174454 | T41: =B41 -> 45285 | U41: =C41 -> 38
B42: =B41+7 -> 45292 | C42: =C41+1 -> 39 | D42: {=SUM((Blotter!C$19:C$1013=C42)*(Blotter!N$19:N$1013)*1)} -> 0 | E42: {=SUM((Blotter!B$19:C$1013=C42)*(Blotter!R$19:R$1013)*1)} -> 0 | F42: =IF(ISNUMBER(D42/E42),D42/E42,0) -> 0 | G42: {=IF(SUM((Blotter!C$19:C$1013=PLB!C42)*(Blotter!M$19:M$1013))=0,"C","O")} -> C | H42: =J41+D42 -> 2188514.5 | J42: =H42+I42 -> 2188514.5 | K42: =H42/J41-1 -> 0 | L42: =(1+K42)*(1+L41)-1 -> 0.15674237 | M42: =O41-IF(G42="O",O41*1%,-D42) -> 2188514.5 | N42: =I42 -> 0 | O42: =M42+N42 -> 2188514.5 | P42: =M42/O41-1 -> 0 | Q42: =(1+P42)*(1+Q41)-1 -> 0.15674237 | R42: =(1-1%)*(1+R41)-1 -> -0.32427095 | T42: =B42 -> 45292 | U42: =C42 -> 39
B43: =B42+7 -> 45299 | C43: =C42+1 -> 40 | D43: {=SUM((Blotter!C$19:C$1013=C43)*(Blotter!N$19:N$1013)*1)} -> -304302.67 | E43: {=SUM((Blotter!B$19:C$1013=C43)*(Blotter!R$19:R$1013)*1)} -> 21690 | F43: =IF(ISNUMBER(D43/E43),D43/E43,0) -> -14.02963 | G43: {=IF(SUM((Blotter!C$19:C$1013=PLB!C43)*(Blotter!M$19:M$1013))=0,"C","O")} -> C | H43: =J42+D43 -> 1884211.9 | J43: =H43+I43 -> 1884211.9 | K43: =H43/J42-1 -> -0.13904531 | L43: =(1+K43)*(1+L42)-1 -> -0.0040972223 | M43: =O42-IF(G43="O",O42*1%,-D43) -> 1884211.9 | N43: =I43 -> 0 | O43: =M43+N43 -> 1884211.9 | P43: =M43/O42-1 -> -0.13904531 | Q43: =(1+P43)*(1+Q42)-1 -> -0.0040972223 | R43: =(1-1%)*(1+R42)-1 -> -0.33102824 | T43: =B43 -> 45299 | U43: =C43 -> 40 | V43: Long CYTK Shares | W43: Novartis to acquire Cytokinetics in a deal that could value the company up to $140 per share. The auction includes AstraZeneca and J&J.
B44: =B43+7 -> 45306 | C44: =C43+1 -> 41 | D44: {=SUM((Blotter!C$19:C$1013=C44)*(Blotter!N$19:N$1013)*1)} -> 347.34 | E44: {=SUM((Blotter!B$19:C$1013=C44)*(Blotter!R$19:R$1013)*1)} -> 13000 | F44: =IF(ISNUMBER(D44/E44),D44/E44,0) -> 0.026718462 | G44: {=IF(SUM((Blotter!C$19:C$1013=PLB!C44)*(Blotter!M$19:M$1013))=0,"C","O")} -> C | H44: =J43+D44 -> 1884559.2 | J44: =H44+I44 -> 1884559.2 | K44: =H44/J43-1 -> 0.00018434233 | L44: =(1+K44)*(1+L43)-1 -> -0.0039136353 | M44: =O43-IF(G44="O",O43*1%,-D44) -> 1884559.2 | N44: =I44 -> 0 | O44: =M44+N44 -> 1884559.2 | P44: =M44/O43-1 -> 0.00018434233 | Q44: =(1+P44)*(1+Q43)-1 -> -0.0039136353 | R44: =(1-1%)*(1+R43)-1 -> -0.33771796 | T44: =B44 -> 45306 | U44: =C44 -> 41 | V44: Long WTI Futures | W44: Continued tensions in the Middle East, more tanker diversions from the Red Sea | X44: 5-week range $70-75 after retracement from $95 / anticipated 1/2 weekly up > $75.25
B45: =B44+7 -> 45313 | C45: =C44+1 -> 42 | D45: {=SUM((Blotter!C$19:C$1013=C45)*(Blotter!N$19:N$1013)*1)} -> 0 | E45: {=SUM((Blotter!B$19:C$1013=C45)*(Blotter!R$19:R$1013)*1)} -> 0 | F45: =IF(ISNUMBER(D45/E45),D45/E45,0) -> 0 | G45: {=IF(SUM((Blotter!C$19:C$1013=PLB!C45)*(Blotter!M$19:M$1013))=0,"C","O")} -> C | H45: =J44+D45 -> 1884559.2 | J45: =H45+I45 -> 1884559.2 | K45: =H45/J44-1 -> 0 | L45: =(1+K45)*(1+L44)-1 -> -0.0039136353 | M45: =O44-IF(G45="O",O44*1%,-D45) -> 1884559.2 | N45: =I45 -> 0 | O45: =M45+N45 -> 1884559.2 | P45: =M45/O44-1 -> 0 | Q45: =(1+P45)*(1+Q44)-1 -> -0.0039136353 | R45: =(1-1%)*(1+R44)-1 -> -0.34434078 | T45: =B45 -> 45313 | U45: =C45 -> 42
B46: =B45+7 -> 45320 | C46: =C45+1 -> 43 | D46: {=SUM((Blotter!C$19:C$1013=C46)*(Blotter!N$19:N$1013)*1)} -> 1014.16 | E46: {=SUM((Blotter!B$19:C$1013=C46)*(Blotter!R$19:R$1013)*1)} -> 18000 | F46: =IF(ISNUMBER(D46/E46),D46/E46,0) -> 0.056342222 | G46: {=IF(SUM((Blotter!C$19:C$1013=PLB!C46)*(Blotter!M$19:M$1013))=0,"C","O")} -> C | H46: =J45+D46 -> 1885573.4 | J46: =H46+I46 -> 1885573.4 | K46: =H46/J45-1 -> 0.00053814176 | L46: =(1+K46)*(1+L45)-1 -> -0.0033775996 | M46: =O45-IF(G46="O",O45*1%,-D46) -> 1885573.4 | N46: =I46 -> 0 | O46: =M46+N46 -> 1885573.4 | P46: =M46/O45-1 -> 0.00053814176 | Q46: =(1+P46)*(1+Q45)-1 -> -0.0033775996 | R46: =(1-1%)*(1+R45)-1 -> -0.35089737 | T46: =B46 -> 45320 | U46: =C46 -> 43 | V46: Long Wheat Futures | W46: Mean reversion trade, market expecting abundant crops and soft global demand | X46: Reverse H&S on weekly / weekly hammer - doji / weekly RSI positive divergence / CTL trade
B47: =B46+7 -> 45327 | C47: =C46+1 -> 44 | D47: {=SUM((Blotter!C$19:C$1013=C47)*(Blotter!N$19:N$1013)*1)} -> 0 | E47: {=SUM((Blotter!B$19:C$1013=C47)*(Blotter!R$19:R$1013)*1)} -> 0 | F47: =IF(ISNUMBER(D47/E47),D47/E47,0) -> 0 | G47: {=IF(SUM((Blotter!C$19:C$1013=PLB!C47)*(Blotter!M$19:M$1013))=0,"C","O")} -> C | H47: =J46+D47 -> 1885573.4 | J47: =H47+I47 -> 1885573.4 | K47: =H47/J46-1 -> 0 | L47: =(1+K47)*(1+L46)-1 -> -0.0033775996 | M47: =O46-IF(G47="O",O46*1%,-D47) -> 1885573.4 | N47: =I47 -> 0 | O47: =M47+N47 -> 1885573.4 | P47: =M47/O46-1 -> 0 | Q47: =(1+P47)*(1+Q46)-1 -> -0.0033775996 | R47: =(1-1%)*(1+R46)-1 -> -0.3573884 | T47: =B47 -> 45327 | U47: =C47 -> 44
B48: =B47+7 -> 45334 | C48: =C47+1 -> 45 | D48: {=SUM((Blotter!C$19:C$1013=C48)*(Blotter!N$19:N$1013)*1)} -> 0 | E48: {=SUM((Blotter!B$19:C$1013=C48)*(Blotter!R$19:R$1013)*1)} -> 0 | F48: =IF(ISNUMBER(D48/E48),D48/E48,0) -> 0 | G48: {=IF(SUM((Blotter!C$19:C$1013=PLB!C48)*(Blotter!M$19:M$1013))=0,"C","O")} -> C | H48: =J47+D48 -> 1885573.4 | J48: =H48+I48 -> 1885573.4 | K48: =H48/J47-1 -> 0 | L48: =(1+K48)*(1+L47)-1 -> -0.0033775996 | M48: =O47-IF(G48="O",O47*1%,-D48) -> 1885573.4 | N48: =I48 -> 0 | O48: =M48+N48 -> 1885573.4 | P48: =M48/O47-1 -> 0 | Q48: =(1+P48)*(1+Q47)-1 -> -0.0033775996 | R48: =(1-1%)*(1+R47)-1 -> -0.36381451 | T48: =B48 -> 45334 | U48: =C48 -> 45
B49: =B48+7 -> 45341 | C49: =C48+1 -> 46 | D49: {=SUM((Blotter!C$19:C$1013=C49)*(Blotter!N$19:N$1013)*1)} -> -404709.12 | E49: {=SUM((Blotter!B$19:C$1013=C49)*(Blotter!R$19:R$1013)*1)} -> 14960 | F49: =IF(ISNUMBER(D49/E49),D49/E49,0) -> -27.052749 | G49: {=IF(SUM((Blotter!C$19:C$1013=PLB!C49)*(Blotter!M$19:M$1013))=0,"C","O")} -> C | H49: =J48+D49 -> 1480864.2 | J49: =H49+I49 -> 1480864.2 | K49: =H49/J48-1 -> -0.21463451 | L49: =(1+K49)*(1+L48)-1 -> -0.21728716 | M49: =O48-IF(G49="O",O48*1%,-D49) -> 1480864.2 | N49: =I49 -> 0 | O49: =M49+N49 -> 1480864.2 | P49: =M49/O48-1 -> -0.21463451 | Q49: =(1+P49)*(1+Q48)-1 -> -0.21728716 | R49: =(1-1%)*(1+R48)-1 -> -0.37017637 | T49: =B49 -> 45341 | U49: =C49 -> 46 | V49: Long Cotton Futures | W49: Texas farmers plan to plant 5.3mm acres, down 5.1% from last year. U.S. farmers intend to plant 9.8mm acres this spring, down 3.7% from 2023 | X49: Break-out from multi-month (14) consolidation > 90 / daily retrace to 9SMA after 12 days rip | Y49: https://texasfarmbureau.org/u-s-texas-cotton-farmers-intend-to-plant-fewer-acres/
B50: =B49+7 -> 45348 | C50: =C49+1 -> 47 | D50: {=SUM((Blotter!C$19:C$1013=C50)*(Blotter!N$19:N$1013)*1)} -> 181.04 | E50: {=SUM((Blotter!B$19:C$1013=C50)*(Blotter!R$19:R$1013)*1)} -> 0 | F50: =IF(ISNUMBER(D50/E50),D50/E50,0) -> 0 | G50: {=IF(SUM((Blotter!C$19:C$1013=PLB!C50)*(Blotter!M$19:M$1013))=0,"C","O")} -> C | H50: =J49+D50 -> 1481045.3 | J50: =H50+I50 -> 1481045.3 | K50: =H50/J49-1 -> 0.00012225293 | L50: =(1+K50)*(1+L49)-1 -> -0.21719147 | M50: =O49-IF(G50="O",O49*1%,-D50) -> 1481045.3 | N50: =I50 -> 0 | O50: =M50+N50 -> 1481045.3 | P50: =M50/O49-1 -> 0.00012225293 | Q50: =(1+P50)*(1+Q49)-1 -> -0.21719147 | R50: =(1-1%)*(1+R49)-1 -> -0.37647461 | T50: =B50 -> 45348 | U50: =C50 -> 47 | V50: Long WTI Futures | W50: OPEC+ is extending its production cuts through at least the second quarter. The cartel could keep the cuts in place for the rest of the year. | X50: Monthly bull flag / monthly up > 79
B51: =B50+7 -> 45355 | C51: =C50+1 -> 48 | D51: {=SUM((Blotter!C$19:C$1013=C51)*(Blotter!N$19:N$1013)*1)} -> 47255.1 | E51: {=SUM((Blotter!B$19:C$1013=C51)*(Blotter!R$19:R$1013)*1)} -> 57903.4 | F51: =IF(ISNUMBER(D51/E51),D51/E51,0) -> 0.81610234 | G51: {=IF(SUM((Blotter!C$19:C$1013=PLB!C51)*(Blotter!M$19:M$1013))=0,"C","O")} -> C | H51: =J50+D51 -> 1528300.4 | J51: =H51+I51 -> 1528300.4 | K51: =H51/J50-1 -> 0.031906587 | L51: =(1+K51)*(1+L50)-1 -> -0.19221473 | M51: =O50-IF(G51="O",O50*1%,-D51) -> 1528300.4 | N51: =I51 -> 0 | O51: =M51+N51 -> 1528300.4 | P51: =M51/O50-1 -> 0.031906587 | Q51: =(1+P51)*(1+Q50)-1 -> -0.19221473 | R51: =(1-1%)*(1+R50)-1 -> -0.38270986 | T51: =B51 -> 45355 | U51: =C51 -> 48 | V51: Long ES Put Spread | W51: Hedge / mean reversion trade after a 19 weeks rally | X51: Weekly RSI = 75 / 19 weeks > 9SMA / multiple daily upper BB tags | Z51: Long Coffee Futures | AA51: 47% year-on-year increase in Vietnam’s coffee exports / excessive dry conditions in Brazil’s / ongoing Red Sea crisis impacting global trade routes | AB51: Weekly bull flag break-out / CTL trade
B52: =B51+7 -> 45362 | C52: =C51+1 -> 49 | D52: {=SUM((Blotter!C$19:C$1013=C52)*(Blotter!N$19:N$1013)*1)} -> -3523.5 | E52: {=SUM((Blotter!B$19:C$1013=C52)*(Blotter!R$19:R$1013)*1)} -> 20500 | F52: =IF(ISNUMBER(D52/E52),D52/E52,0) -> -0.17187805 | G52: {=IF(SUM((Blotter!C$19:C$1013=PLB!C52)*(Blotter!M$19:M$1013))=0,"C","O")} -> C | H52: =J51+D52 -> 1524776.9 | J52: =H52+I52 -> 1524776.9 | K52: =H52/J51-1 -> -0.0023055023 | L52: =(1+K52)*(1+L51)-1 -> -0.19407708 | M52: =O51-IF(G52="O",O51*1%,-D52) -> 1524776.9 | N52: =I52 -> 0 | O52: =M52+N52 -> 1524776.9 | P52: =M52/O51-1 -> -0.0023055023 | Q52: =(1+P52)*(1+Q51)-1 -> -0.19407708 | R52: =(1-1%)*(1+R51)-1 -> -0.38888276 | T52: =B52 -> 45362 | U52: =C52 -> 49 | V52: Long Soybean Futures | W52: USDA’s latest monthly report constructive for soybeans as lower supply pushed down global inventory estimates | X52: Monthly look below and reversal from daily RSI = 22 / weekly up (-2) > 1161 / daily bull flag + inside week
B53: =B52+7 -> 45369 | C53: =C52+1 -> 50 | D53: {=SUM((Blotter!C$19:C$1013=C53)*(Blotter!N$19:N$1013)*1)} -> 0 | E53: {=SUM((Blotter!B$19:C$1013=C53)*(Blotter!R$19:R$1013)*1)} -> 0 | F53: =IF(ISNUMBER(D53/E53),D53/E53,0) -> 0 | G53: {=IF(SUM((Blotter!C$19:C$1013=PLB!C53)*(Blotter!M$19:M$1013))=0,"C","O")} -> C | H53: =J52+D53 -> 1524776.9 | J53: =H53+I53 -> 1524776.9 | K53: =H53/J52-1 -> 0 | L53: =(1+K53)*(1+L52)-1 -> -0.19407708 | M53: =O52-IF(G53="O",O52*1%,-D53) -> 1524776.9 | N53: =I53 -> 0 | O53: =M53+N53 -> 1524776.9 | P53: =M53/O52-1 -> 0 | Q53: =(1+P53)*(1+Q52)-1 -> -0.19407708 | R53: =(1-1%)*(1+R52)-1 -> -0.39499393 | T53: =B53 -> 45369 | U53: =C53 -> 50
B54: =B53+7 -> 45376 | C54: =C53+1 -> 51 | D54: {=SUM((Blotter!C$19:C$1013=C54)*(Blotter!N$19:N$1013)*1)} -> 0 | E54: {=SUM((Blotter!B$19:C$1013=C54)*(Blotter!R$19:R$1013)*1)} -> 0 | F54: =IF(ISNUMBER(D54/E54),D54/E54,0) -> 0 | G54: {=IF(SUM((Blotter!C$19:C$1013=PLB!C54)*(Blotter!M$19:M$1013))=0,"C","O")} -> C | H54: =J53+D54 -> 1524776.9 | J54: =H54+I54 -> 1524776.9 | K54: =H54/J53-1 -> 0 | L54: =(1+K54)*(1+L53)-1 -> -0.19407708 | M54: =O53-IF(G54="O",O53*1%,-D54) -> 1524776.9 | N54: =I54 -> 0 | O54: =M54+N54 -> 1524776.9 | P54: =M54/O53-1 -> 0 | Q54: =(1+P54)*(1+Q53)-1 -> -0.19407708 | R54: =(1-1%)*(1+R53)-1 -> -0.40104399 | T54: =B54 -> 45376 | U54: =C54 -> 51
B55: =B54+7 -> 45383 | C55: =C54+1 -> 52 | D55: {=SUM((Blotter!C$19:C$1013=C55)*(Blotter!N$19:N$1013)*1)} -> 0 | E55: {=SUM((Blotter!B$19:C$1013=C55)*(Blotter!R$19:R$1013)*1)} -> 0 | F55: =IF(ISNUMBER(D55/E55),D55/E55,0) -> 0 | G55: {=IF(SUM((Blotter!C$19:C$1013=PLB!C55)*(Blotter!M$19:M$1013))=0,"C","O")} -> C | H55: =J54+D55 -> 1524776.9 | J55: =H55+I55 -> 1524776.9 | K55: =H55/J54-1 -> 0 | L55: =(1+K55)*(1+L54)-1 -> -0.19407708 | M55: =O54-IF(G55="O",O54*1%,-D55) -> 1524776.9 | N55: =I55 -> 0 | O55: =M55+N55 -> 1524776.9 | P55: =M55/O54-1 -> 0 | Q55: =(1+P55)*(1+Q54)-1 -> -0.19407708 | R55: =(1-1%)*(1+R54)-1 -> -0.40703355 | T55: =B55 -> 45383 | U55: =C55 -> 52
B56: =B55+7 -> 45390 | C56: =C55+1 -> 53 | D56: {=SUM((Blotter!C$19:C$1013=C56)*(Blotter!N$19:N$1013)*1)} -> 4446.6 | E56: {=SUM((Blotter!B$19:C$1013=C56)*(Blotter!R$19:R$1013)*1)} -> -14880 | F56: =IF(ISNUMBER(D56/E56),D56/E56,0) -> -0.29883065 | G56: {=IF(SUM((Blotter!C$19:C$1013=PLB!C56)*(Blotter!M$19:M$1013))=0,"C","O")} -> C | H56: =J55+D56 -> 1529223.5 | J56: =H56+I56 -> 1529223.5 | K56: =H56/J55-1 -> 0.0029162299 | L56: =(1+K56)*(1+L55)-1 -> -0.19172682 | M56: =O55-IF(G56="O",O55*1%,-D56) -> 1529223.5 | N56: =I56 -> 0 | O56: =M56+N56 -> 1529223.5 | P56: =M56/O55-1 -> 0.0029162299 | Q56: =(1+P56)*(1+Q55)-1 -> -0.19172682 | R56: =(1-1%)*(1+R55)-1 -> -0.41296322 | T56: =B56 -> 45390 | U56: =C56 -> 53 | V56: Short NDX Futures | W56: Rate cuts expectations adjustment to <2 / US10YR breaking out > 4.40% / Geopolical tensions, Iran ready to strike | X56: Potential distribution patterns / Inside month, potential first monthly down in 6 months
B57: =B56+7 -> 45397 | C57: =C56+1 -> 54 | D57: {=SUM((Blotter!C$19:C$1013=C57)*(Blotter!N$19:N$1013)*1)} -> 0 | E57: {=SUM((Blotter!B$19:C$1013=C57)*(Blotter!R$19:R$1013)*1)} -> 0 | F57: =IF(ISNUMBER(D57/E57),D57/E57,0) -> 0 | G57: {=IF(SUM((Blotter!C$19:C$1013=PLB!C57)*(Blotter!M$19:M$1013))=0,"C","O")} -> C | H57: =J56+D57 -> 1529223.5 | J57: =H57+I57 -> 1529223.5 | K57: =H57/J56-1 -> 0 | L57: =(1+K57)*(1+L56)-1 -> -0.19172682 | M57: =O56-IF(G57="O",O56*1%,-D57) -> 1529223.5 | N57: =I57 -> 0 | O57: =M57+N57 -> 1529223.5 | P57: =M57/O56-1 -> 0 | Q57: =(1+P57)*(1+Q56)-1 -> -0.19172682 | R57: =(1-1%)*(1+R56)-1 -> -0.41883359 | T57: =B57 -> 45397 | U57: =C57 -> 54
B58: =B57+7 -> 45404 | C58: =C57+1 -> 55 | D58: {=SUM((Blotter!C$19:C$1013=C58)*(Blotter!N$19:N$1013)*1)} -> 0 | E58: {=SUM((Blotter!B$19:C$1013=C58)*(Blotter!R$19:R$1013)*1)} -> 0 | F58: =IF(ISNUMBER(D58/E58),D58/E58,0) -> 0 | G58: {=IF(SUM((Blotter!C$19:C$1013=PLB!C58)*(Blotter!M$19:M$1013))=0,"C","O")} -> C | H58: =J57+D58 -> 1529223.5 | J58: =H58+I58 -> 1529223.5 | K58: =H58/J57-1 -> 0 | L58: =(1+K58)*(1+L57)-1 -> -0.19172682 | M58: =O57-IF(G58="O",O57*1%,-D58) -> 1529223.5 | N58: =I58 -> 0 | O58: =M58+N58 -> 1529223.5 | P58: =M58/O57-1 -> 0 | Q58: =(1+P58)*(1+Q57)-1 -> -0.19172682 | R58: =(1-1%)*(1+R57)-1 -> -0.42464525 | T58: =B58 -> 45404 | U58: =C58 -> 55
B59: =B58+7 -> 45411 | C59: =C58+1 -> 56 | D59: {=SUM((Blotter!C$19:C$1013=C59)*(Blotter!N$19:N$1013)*1)} -> -58467.3 | E59: {=SUM((Blotter!B$19:C$1013=C59)*(Blotter!R$19:R$1013)*1)} -> 20000 | F59: =IF(ISNUMBER(D59/E59),D59/E59,0) -> -2.923365 | G59: {=IF(SUM((Blotter!C$19:C$1013=PLB!C59)*(Blotter!M$19:M$1013))=0,"C","O")} -> C | H59: =J58+D59 -> 1470756.2 | J59: =H59+I59 -> 1470756.2 | K59: =H59/J58-1 -> -0.038233326 | L59: =(1+K59)*(1+L58)-1 -> -0.22262979 | M59: =O58-IF(G59="O",O58*1%,-D59) -> 1470756.2 | N59: =I59 -> 0 | O59: =M59+N59 -> 1470756.2 | P59: =M59/O58-1 -> -0.038233326 | Q59: =(1+P59)*(1+Q58)-1 -> -0.22262979 | R59: =(1-1%)*(1+R58)-1 -> -0.4303988 | T59: =B59 -> 45411 | U59: =C59 -> 56 | V59: Long Coca Futures | W59: Bad weather, aging cocoa trees and crop disease affect West Africa, or half of global output / supplies to fall short of demand for a third year | X59: 61.8% retracement

Sheet PLB_chart

Sheet Multiplier
B2: Ticker | C2: Multiplier | D2: ATR | E2: # ATR | F2: Capital $ | G2: % Risk Capital | H2: Sizing | I2: Max Sizing | J2: Price | K2: Sizing / Capital | L2: Max Sizing / Capital | N2: Capital Loc Crncy | O2: FX | P2: Capital $ | Q2: # ATR | R2: % Capital
B3: SPX | C3: 100 | D3: 42 | E3: =$Q$3 -> 1.5 | F3: =$P$3 -> 1000000 | G3: =$R$3 -> 0.01 | H3: =(F3*G3)/(C3*D3*E3) -> 1.5873016 | I3: =ROUND(H3*1.33,0) -> 2 | N3: 1000000 | O3: 1 | P3: =N3*O3 -> 1000000 | Q3: 1.5 | R3: 0.01
B4: ES | C4: 50 | D4: 50.57 | E4: =$Q$3 -> 1.5 | F4: =$P$3 -> 1000000 | G4: =$R$3 -> 0.01 | H4: =(F4*G4)/(C4*D4*E4) -> 2.6366093 | I4: =ROUND(H4*1.5,0) -> 4 | J4: 5237 | K4: =J4*H4*C4/$N$3 -> 0.69039615 | L4: =J4*I4*C4/$N$3 -> 1.0474
B5: NQ | C5: 20 | D5: 248 | E5: =$Q$3 -> 1.5 | F5: =$P$3 -> 1000000 | G5: =$R$3 -> 0.01 | H5: =(F5*G5)/(C5*D5*E5) -> 1.344086 | I5: =ROUND(H5*1.5,0) -> 2 | J5: 18320 | K5: =J5*H5*C5/$N$3 -> 0.49247312 | L5: =J5*I5*C5/$N$3 -> 0.7328
B6: RTY | C6: 50 | D6: 44.2 | E6: =$Q$3 -> 1.5 | F6: =$P$3 -> 1000000 | G6: =$R$3 -> 0.01 | H6: =(F6*G6)/(C6*D6*E6) -> 3.0165913 | I6: =ROUND(H6*1.5,0) -> 5
B7: CL | C7: 1000 | D7: 2.41 | E7: =$Q$3 -> 1.5 | F7: =$P$3 -> 1000000 | G7: =$R$3 -> 0.01 | H7: =(F7*G7)/(C7*D7*E7) -> 2.7662517 | I7: =ROUND(H7*1.5,0) -> 4 | J7: 82 | K7: =J7*H7*C7/$N$3 -> 0.22683264 | L7: =J7*I7*C7/$N$3 -> 0.328
B8: RB | C8: 42000 | D8: 0.0725 | E8: =$Q$3 -> 1.5 | F8: =$P$3 -> 1000000 | G8: =$R$3 -> 0.01 | H8: =(F8*G8)/(C8*D8*E8) -> 2.1893815 | I8: =ROUND(H8*1.5,0) -> 3
B9: NG | C9: 10000 | D9: 0.132 | E9: =$Q$3 -> 1.5 | F9: =$P$3 -> 1000000 | G9: =$R$3 -> 0.01 | H9: =(F9*G9)/(C9*D9*E9) -> 5.0505051 | I9: =ROUND(H9*1.5,0) -> 8
B10: HG | C10: 25000 | D10: 0.0708 | E10: =$Q$3 -> 1.5 | F10: =$P$3 -> 1000000 | G10: =$R$3 -> 0.01 | H10: =(F10*G10)/(C10*D10*E10) -> 3.7664783 | I10: =ROUND(H10*1.5,0) -> 6 | J10: 4.03 | K10: =J10*H10*C10/$N$3 -> 0.37947269 | L10: =J10*I10*C10/$N$3 -> 0.6045
B11: GC | C11: 100 | D11: 28.4 | E11: =$Q$3 -> 1.5 | F11: =$P$3 -> 1000000 | G11: =$R$3 -> 0.01 | H11: =(F11*G11)/(C11*D11*E11) -> 2.3474178 | I11: =ROUND(H11*1.5,0) -> 4
B12: SI | C12: 5000 | D12: 0.825 | E12: =$Q$3 -> 1.5 | F12: =$P$3 -> 1000000 | G12: =$R$3 -> 0.01 | H12: =(F12*G12)/(C12*D12*E12) -> 1.6161616 | I12: =ROUND(H12*1.5,0) -> 2 | J12: 25 | K12: =J12*H12*C12/$N$3 -> 0.2020202 | L12: =J12*I12*C12/$N$3 -> 0.25
B13: ZC | C13: 50 | D13: 8.25 | E13: =$Q$3 -> 1.5 | F13: =$P$3 -> 1000000 | G13: =$R$3 -> 0.01 | H13: =(F13*G13)/(C13*D13*E13) -> 16.161616 | I13: =ROUND(H13*1.5,0) -> 24
B14: ZW | C14: 50 | D14: 17.25 | E14: =$Q$3 -> 1.5 | F14: =$P$3 -> 1000000 | G14: =$R$3 -> 0.01 | H14: =(F14*G14)/(C14*D14*E14) -> 7.7294686 | I14: =ROUND(H14*1.5,0) -> 12 | J14: 550 | K14: =J14*H14*C14/$N$3 -> 0.21256039 | L14: =J14*I14*C14/$N$3 -> 0.33
B15: KE | C15: 50 | D15: 24.5 | E15: =$Q$3 -> 1.5 | F15: =$P$3 -> 1000000 | G15: =$R$3 -> 0.01 | H15: =(F15*G15)/(C15*D15*E15) -> 5.4421769 | I15: =ROUND(H15*1.5,0) -> 8
B16: ZS | C16: 50 | D16: 19.75 | E16: =$Q$3 -> 1.5 | F16: =$P$3 -> 1000000 | G16: =$R$3 -> 0.01 | H16: =(F16*G16)/(C16*D16*E16) -> 6.7510549 | I16: =ROUND(H16*1.5,0) -> 10 | J16: 1187 | K16: =J16*H16*C16/$N$3 -> 0.40067511 | L16: =J16*I16*C16/$N$3 -> 0.5935
B17: SB | C17: 1120 | D17: 0.89 | E17: =$Q$3 -> 1.5 | F17: =$P$3 -> 1000000 | G17: =$R$3 -> 0.01 | H17: =(F17*G17)/(C17*D17*E17) -> 6.6880685 | I17: =ROUND(H17*1.5,0) -> 10
B18: KC | C18: 375 | D18: 5.38 | E18: =$Q$3 -> 1.5 | F18: =$P$3 -> 1000000 | G18: =$R$3 -> 0.01 | H18: =(F18*G18)/(C18*D18*E18) -> 3.3044197 | I18: =ROUND(H18*1.5,0) -> 5 | J18: 184 | K18: =J18*H18*C18/$N$3 -> 0.22800496 | L18: =J18*I18*C18/$N$3 -> 0.345
B19: CC | C19: 10 | D19: 400 | E19: =$Q$3 -> 1.5 | F19: =$P$3 -> 1000000 | G19: =$R$3 -> 0.01 | H19: =(F19*G19)/(C19*D19*E19) -> 1.6666667 | I19: =ROUND(H19*1.5,0) -> 3 | J19: 8300 | K19: =J19*H19*C19/$N$3 -> 0.13833333 | L19: =J19*I19*C19/$N$3 -> 0.249
B20: CT | C20: 500 | D20: 3.01 | E20: =$Q$3 -> 1.5 | F20: =$P$3 -> 1000000 | G20: =$R$3 -> 0.01 | H20: =(F20*G20)/(C20*D20*E20) -> 4.4296788 | I20: =ROUND(H20*1.5,0) -> 7 | J20: 94 | K20: =J20*H20*C20/$N$3 -> 0.20819491 | L20: =J20*I20*C20/$N$3 -> 0.329
B21: LE | C21: 400 | D21: 1.055 | E21: =$Q$3 -> 1.5 | F21: =$P$3 -> 1000000 | G21: =$R$3 -> 0.01 | H21: =(F21*G21)/(C21*D21*E21) -> 15.797788 | I21: =ROUND(H21*1.5,0) -> 24
B22: GF | C22: 500 | D22: 1.939 | E22: =$Q$3 -> 1.5 | F22: =$P$3 -> 1000000 | G22: =$R$3 -> 0.01 | H22: =(F22*G22)/(C22*D22*E22) -> 6.8763968 | I22: =ROUND(H22*1.5,0) -> 10
B23: HE | C23: 400 | D23: 1.579 | E23: =$Q$3 -> 1.5 | F23: =$P$3 -> 1000000 | G23: =$R$3 -> 0.01 | H23: =(F23*G23)/(C23*D23*E23) -> 10.555204 | I23: =ROUND(H23*1.5,0) -> 16
B24: DX | C24: 1000 | D24: 0.849 | E24: =$Q$3 -> 1.5 | F24: =$P$3 -> 1000000 | G24: =$R$3 -> 0.01 | H24: =(F24*G24)/(C24*D24*E24) -> 7.8523753 | I24: =ROUND(H24*1.5,0) -> 12
B25: 6A | C25: 100000 | D25: 0.00914 | E25: =$Q$3 -> 1.5 | F25: =$P$3 -> 1000000 | G25: =$R$3 -> 0.01 | H25: =(F25*G25)/(C25*D25*E25) -> 7.293946 | I25: =ROUND(H25*1.5,0) -> 11
B26: 6B | C26: 62500 | D26: 0.0124 | E26: =$Q$3 -> 1.5 | F26: =$P$3 -> 1000000 | G26: =$R$3 -> 0.01 | H26: =(F26*G26)/(C26*D26*E26) -> 8.6021505 | I26: =ROUND(H26*1.5,0) -> 13
B27: 6C | C27: 100000 | D27: 0.00559 | E27: =$Q$3 -> 1.5 | F27: =$P$3 -> 1000000 | G27: =$R$3 -> 0.01 | H27: =(F27*G27)/(C27*D27*E27) -> 11.926058 | I27: =ROUND(H27*1.5,0) -> 18
B28: 6E | C28: 125000 | D28: 0.00956 | E28: =$Q$3 -> 1.5 | F28: =$P$3 -> 1000000 | G28: =$R$3 -> 0.01 | H28: =(F28*G28)/(C28*D28*E28) -> 5.5788006 | I28: =ROUND(H28*1.5,0) -> 8
B29: 6J | C29: 12500000 | D29: 0.0001022 | E29: =$Q$3 -> 1.5 | F29: =$P$3 -> 1000000 | G29: =$R$3 -> 0.01 | H29: =(F29*G29)/(C29*D29*E29) -> 5.2185258 | I29: =ROUND(H29*1.5,0) -> 8
B30: BTC | C30: 5 | D30: 908 | E30: =$Q$3 -> 1.5 | F30: =$P$3 -> 1000000 | G30: =$R$3 -> 0.01 | H30: =(F30*G30)/(C30*D30*E30) -> 1.4684288 | I30: =ROUND(H30*1.5,0) -> 2
B31: ETH | C31: 50 | D31: 140 | E31: =$Q$3 -> 1.5 | F31: =$P$3 -> 1000000 | G31: =$R$3 -> 0.01 | H31: =(F31*G31)/(C31*D31*E31) -> 0.95238095 | I31: =ROUND(H31*1.5,0) -> 1
B32: ZB | C32: 1000 | D32: =1+18/32 -> 1.5625 | E32: =$Q$3 -> 1.5 | F32: =$P$3 -> 1000000 | G32: =$R$3 -> 0.01 | H32: =(F32*G32)/(C32*D32*E32) -> 4.2666667 | I32: =ROUND(H32*1.5,0) -> 6
B33: BTP | C33: 1000 | D33: 1.57 | E33: =$Q$3 -> 1.5 | F33: =$P$3 -> 1000000 | G33: =$R$3 -> 0.01 | H33: =(F33*G33)/(C33*D33*E33) -> 4.2462845 | I33: =ROUND(H33*1.5,0) -> 6
B34: BABA | C34: 100 | D34: 4.15 | E34: =$Q$3 -> 1.5 | F34: =$P$3 -> 1000000 | G34: =$R$3 -> 0.01 | H34: =(F34*G34)/(C34*D34*E34) -> 16.064257 | I34: =ROUND(H34*1.5,0) -> 24
B35: NVDA | C35: 100 | D35: 9.29 | E35: =$Q$3 -> 1.5 | F35: =$P$3 -> 1000000 | G35: =$R$3 -> 0.01 | H35: =(F35*G35)/(C35*D35*E35) -> 7.1761751 | I35: =ROUND(H35*1.5,0) -> 11
B36: GOOG | C36: 100 | D36: 3.34 | E36: =$Q$3 -> 1.5 | F36: =$P$3 -> 1000000 | G36: =$R$3 -> 0.01 | H36: =(F36*G36)/(C36*D36*E36) -> 19.96008 | I36: =ROUND(H36*1.5,0) -> 30
B37: INDA | C37: 100 | D37: 0.3075 | E37: =$Q$3 -> 1.5 | F37: =$P$3 -> 1000000 | G37: =$R$3 -> 0.01 | H37: =(F37*G37)/(C37*D37*E37) -> 216.80217 | I37: =ROUND(H37*1.5,0) -> 325
B38: URA | C38: 100 | D38: 0.85 | E38: =$Q$3 -> 1.5 | F38: =$P$3 -> 1000000 | G38: =$R$3 -> 0.01 | H38: =(F38*G38)/(C38*D38*E38) -> 78.431373 | I38: =ROUND(H38*1.5,0) -> 118
B39: SAVE | C39: 100 | D39: 1.06 | E39: =$Q$3 -> 1.5 | F39: =$P$3 -> 1000000 | G39: =$R$3 -> 0.01 | H39: =(F39*G39)/(C39*D39*E39) -> 62.893082 | I39: =ROUND(H39*1.5,0) -> 94
B40: SAVE-S | C40: 1 | D40: 1.06 | E40: =$Q$3 -> 1.5 | F40: =$P$3 -> 1000000 | G40: =$R$3 -> 0.01 | H40: =(F40*G40)/(C40*D40*E40) -> 6289.3082 | I40: =ROUND(H40*1.5,0) -> 9434
B41: CYTK-S | C41: 1 | D41: 7.23 | E41: =$Q$3 -> 1.5 | F41: =$P$3 -> 1000000 | G41: =$R$3 -> 0.01 | H41: =(F41*G41)/(C41*D41*E41) -> 922.08391 | I41: =ROUND(H41*1.5,0) -> 1383 | J41: 68 | K41: =J41*H41*C41/$N$3 -> 0.062701706 | L41: =J41*I41*C41/$N$3 -> 0.094044
B42: IBB-S | C42: 1 | D42: 2.03 | E42: =$Q$3 -> 1.5 | F42: =$P$3 -> 1000000 | G42: =$R$3 -> 0.01 | H42: =(F42*G42)/(C42*D42*E42) -> 3284.0722 | I42: =ROUND(H42*1.5,0) -> 4926

Sheet Trades
A1: ClientAccountID | B1: CurrencyPrimary | C1: AssetClass | D1: Symbol | E1: Description | F1: ListingExchange | G1: UnderlyingSymbol | H1: Multiplier | I1: Strike | J1: Expiry | K1: Put/Call | L1: TradeDate | M1: Buy/Sell | N1: Quantity | O1: Price | P1: Amount | Q1: Commission | R1: CommissionCurrency | T1: Week | U1: Ticker | V1: Quantity | W1: Price | X1: Commission | Z1: (potential conflicting VLOOKUP if same instrument traded in different weeks)
A2: U11717501 | B2: USD | C2: OPT | D2: SPX 230616P03700000 | E2: SPX 16JUN23 3700 P | F2: CBOE | G2: SPX | H2: 100 | I2: 3700 | J2: 45093 | K2: P | L2: 45028 | M2: SELL | N2: -4 | O2: 24.5 | P2: -9800 | Q2: -5.4462 | R2: USD | T2: =IF(ISNUMBER(VLOOKUP(U2,Blotter!B:C,2,0)),VLOOKUP(U2,Blotter!B:C,2,0),"") -> 1 | U2: =D2 -> SPX 230616P03700000 | V2: =N2 -> -4 | W2: =O2 -> 24.5 | X2: =Q2 -> -5.4462 | Z2: (manually change "Week" if traded in multiple weeks)
A3: U11717501 | B3: USD | C3: OPT | D3: SPX 230616P03700000 | E3: SPX 16JUN23 3700 P | F3: CBOE | G3: SPX | H3: 100 | I3: 3700 | J3: 45093 | K3: P | L3: 45028 | M3: SELL | N3: -2 | O3: 24.5 | P3: -4900 | Q3: -2.7231 | R3: USD | T3: =IF(ISNUMBER(VLOOKUP(U3,Blotter!B:C,2,0)),VLOOKUP(U3,Blotter!B:C,2,0),"") -> 1 | U3: =D3 -> SPX 230616P03700000 | V3: =N3 -> -2 | W3: =O3 -> 24.5 | X3: =Q3 -> -2.7231
A4: U11717501 | B4: USD | C4: OPT | D4: SPX 230616P03850000 | E4: SPX 16JUN23 3850 P | F4: CBOE | G4: SPX | H4: 100 | I4: 3850 | J4: 45093 | K4: P | L4: 45028 | M4: BUY | N4: 6 | O4: 41 | P4: 24600 | Q4: -8.1693 | R4: USD | T4: =IF(ISNUMBER(VLOOKUP(U4,Blotter!B:C,2,0)),VLOOKUP(U4,Blotter!B:C,2,0),"") -> 1 | U4: =D4 -> SPX 230616P03850000 | V4: =N4 -> 6 | W4: =O4 -> 41 | X4: =Q4 -> -8.1693
A5: U11717501 | B5: USD | C5: BOND | D5: T 0 3/8 04/15/24 | E5: T 0 3/8 04/15/24 | H5: 1 | L5: 45028 | M5: BUY | N5: 1000000 | O5: 95.917 | P5: 959170 | Q5: -20 | R5: USD | T5: =IF(ISNUMBER(VLOOKUP(U5,Blotter!B:C,2,0)),VLOOKUP(U5,Blotter!B:C,2,0),"") | U5: =D5 -> T 0 3/8 04/15/24 | V5: =N5 -> 1000000 | W5: =O5 -> 95.917 | X5: =Q5 -> -20
A6: U11717501 | B6: USD | C6: FUT | D6: NGK3 | E6: NG MAY23 | F6: NYMEX | G6: NG | H6: 10000 | J6: 45042 | L6: 45036 | M6: BUY | N6: 1 | O6: 2.22 | P6: 22200 | Q6: -2.37 | R6: USD | T6: =IF(ISNUMBER(VLOOKUP(U6,Blotter!B:C,2,0)),VLOOKUP(U6,Blotter!B:C,2,0),"") -> 2 | U6: =D6 -> NGK3 | V6: =N6 -> 1 | W6: =O6 -> 2.22 | X6: =Q6 -> -2.37
A7: U11717501 | B7: USD | C7: FUT | D7: NGK3 | E7: NG MAY23 | F7: NYMEX | G7: NG | H7: 10000 | J7: 45042 | L7: 45036 | M7: BUY | N7: 1 | O7: 2.22 | P7: 22200 | Q7: -2.37 | R7: USD | T7: =IF(ISNUMBER(VLOOKUP(U7,Blotter!B:C,2,0)),VLOOKUP(U7,Blotter!B:C,2,0),"") -> 2 | U7: =D7 -> NGK3 | V7: =N7 -> 1 | W7: =O7 -> 2.22 | X7: =Q7 -> -2.37
A8: U11717501 | B8: USD | C8: FUT | D8: NGK3 | E8: NG MAY23 | F8: NYMEX | G8: NG | H8: 10000 | J8: 45042 | L8: 45036 | M8: BUY | N8: 1 | O8: 2.22 | P8: 22200 | Q8: -2.37 | R8: USD | T8: =IF(ISNUMBER(VLOOKUP(U8,Blotter!B:C,2,0)),VLOOKUP(U8,Blotter!B:C,2,0),"") -> 2 | U8: =D8 -> NGK3 | V8: =N8 -> 1 | W8: =O8 -> 2.22 | X8: =Q8 -> -2.37
A9: U11717501 | B9: USD | C9: FUT | D9: NGK3 | E9: NG MAY23 | F9: NYMEX | G9: NG | H9: 10000 | J9: 45042 | L9: 45036 | M9: BUY | N9: 2 | O9: 2.19 | P9: 43800 | Q9: -4.74 | R9: USD | T9: =IF(ISNUMBER(VLOOKUP(U9,Blotter!B:C,2,0)),VLOOKUP(U9,Blotter!B:C,2,0),"") -> 2 | U9: =D9 -> NGK3 | V9: =N9 -> 2 | W9: =O9 -> 2.19 | X9: =Q9 -> -4.74
A10: U11717501 | B10: USD | C10: FUT | D10: NGK3 | E10: NG MAY23 | F10: NYMEX | G10: NG | H10: 10000 | J10: 45042 | L10: 45040 | M10: SELL | N10: -5 | O10: 2.25 | P10: -112500 | Q10: -11.85 | R10: USD | T10: =IF(ISNUMBER(VLOOKUP(U10,Blotter!B:C,2,0)),VLOOKUP(U10,Blotter!B:C,2,0),"") -> 2 | U10: =D10 -> NGK3 | V10: =N10 -> -5 | W10: =O10 -> 2.25 | X10: =Q10 -> -11.85
A11: U11717501 | B11: USD | C11: FUT | D11: NGM3 | E11: NG JUN23 | F11: NYMEX | G11: NG | H11: 10000 | J11: 45072 | L11: 45040 | M11: BUY | N11: 1 | O11: 2.42 | P11: 24200 | Q11: -2.37 | R11: USD | T11: =IF(ISNUMBER(VLOOKUP(U11,Blotter!B:C,2,0)),VLOOKUP(U11,Blotter!B:C,2,0),"") -> 2 | U11: =D11 -> NGM3 | V11: =N11 -> 1 | W11: =O11 -> 2.42 | X11: =Q11 -> -2.37
A12: U11717501 | B12: USD | C12: FUT | D12: NGM3 | E12: NG JUN23 | F12: NYMEX | G12: NG | H12: 10000 | J12: 45072 | L12: 45040 | M12: BUY | N12: 3 | O12: 2.42 | P12: 72600 | Q12: -7.11 | R12: USD | T12: =IF(ISNUMBER(VLOOKUP(U12,Blotter!B:C,2,0)),VLOOKUP(U12,Blotter!B:C,2,0),"") -> 2 | U12: =D12 -> NGM3 | V12: =N12 -> 3 | W12: =O12 -> 2.42 | X12: =Q12 -> -7.11
A13: U11717501 | B13: USD | C13: FUT | D13: NGM3 | E13: NG JUN23 | F13: NYMEX | G13: NG | H13: 10000 | J13: 45072 | L13: 45040 | M13: BUY | N13: 1 | O13: 2.42 | P13: 24200 | Q13: -2.37 | R13: USD | T13: =IF(ISNUMBER(VLOOKUP(U13,Blotter!B:C,2,0)),VLOOKUP(U13,Blotter!B:C,2,0),"") -> 2 | U13: =D13 -> NGM3 | V13: =N13 -> 1 | W13: =O13 -> 2.42 | X13: =Q13 -> -2.37
A14: U11717501 | B14: USD | C14: FUT | D14: RBM3 | E14: RB JUN23 | F14: NYMEX | G14: RB | H14: 42000 | J14: 45077 | L14: 45041 | M14: BUY | N14: 1 | O14: 2.62 | P14: 110040 | Q14: -2.37 | R14: USD | T14: =IF(ISNUMBER(VLOOKUP(U14,Blotter!B:C,2,0)),VLOOKUP(U14,Blotter!B:C,2,0),"") -> 3 | U14: =D14 -> RBM3 | V14: =N14 -> 1 | W14: =O14 -> 2.62 | X14: =Q14 -> -2.37
A15: U11717501 | B15: USD | C15: FUT | D15: RBM3 | E15: RB JUN23 | F15: NYMEX | G15: RB | H15: 42000 | J15: 45077 | L15: 45041 | M15: BUY | N15: 1 | O15: 2.59 | P15: 108780 | Q15: -2.37 | R15: USD | T15: =IF(ISNUMBER(VLOOKUP(U15,Blotter!B:C,2,0)),VLOOKUP(U15,Blotter!B:C,2,0),"") -> 3 | U15: =D15 -> RBM3 | V15: =N15 -> 1 | W15: =O15 -> 2.59 | X15: =Q15 -> -2.37
A16: U11717501 | B16: USD | C16: FUT | D16: RBM3 | E16: RB JUN23 | F16: NYMEX | G16: RB | H16: 42000 | J16: 45077 | L16: 45042 | M16: SELL | N16: -1 | O16: 2.51 | P16: -105420 | Q16: -2.37 | R16: USD | T16: =IF(ISNUMBER(VLOOKUP(U16,Blotter!B:C,2,0)),VLOOKUP(U16,Blotter!B:C,2,0),"") -> 3 | U16: =D16 -> RBM3 | V16: =N16 -> -1 | W16: =O16 -> 2.51 | X16: =Q16 -> -2.37
A17: U11717501 | B17: USD | C17: FUT | D17: RBM3 | E17: RB JUN23 | F17: NYMEX | G17: RB | H17: 42000 | J17: 45077 | L17: 45042 | M17: SELL | N17: -1 | O17: 2.51 | P17: -105420 | Q17: -2.37 | R17: USD | T17: =IF(ISNUMBER(VLOOKUP(U17,Blotter!B:C,2,0)),VLOOKUP(U17,Blotter!B:C,2,0),"") -> 3 | U17: =D17 -> RBM3 | V17: =N17 -> -1 | W17: =O17 -> 2.51 | X17: =Q17 -> -2.37
... A20: U11717501 | B20: USD | C20: FUT | D20: NGM3 | E20: NG JUN23 | F20: NYMEX | G20: NG | H20: 10000 | J20: 45072 | L20: 45048 | M20: SELL | N20: -5 | O20: 2.215 | P20: -110750 | Q20: -11.85 | R20: USD | T20: =IF(ISNUMBER(VLOOKUP(U20,Blotter!B:C,2,0)),VLOOKUP(U20,Blotter!B:C,2,0),"") -> 2 | U20: =D20 -> NGM3 | V20: =N20 -> -5 | W20: =O20 -> 2.215 | X20: =Q20 -> -11.85
A21: U11717501 | B21: USD | C21: OPT | D21: SPX 230616P03850000 | E21: SPX 16JUN23 3850 P | F21: CBOE | G21: SPX | H21: 100 | I21: 3850 | J21: 45093 | K21: P | L21: 45051 | M21: SELL | N21: -6 | O21: 27 | P21: -16200 | Q21: -8.1693 | R21: USD | T21: =IF(ISNUMBER(VLOOKUP(U21,Blotter!B:C,2,0)),VLOOKUP(U21,Blotter!B:C,2,0),"") -> 1 | U21: =D21 -> SPX 230616P03850000 | V21: =N21 -> -6 | W21: =O21 -> 27 | X21: =Q21 -> -8.1693
A22: U11717501 | B22: USD | C22: FOP | D22: QNEM3 C13800 | E22: NQ 30JUN23 13800 C | F22: CME | G22: NQU3 | H22: 20 | I22: 13800 | J22: 45107 | K22: C | L22: 45054 | M22: BUY | N22: 1 | O22: 205 | P22: 4100 | Q22: -1.42 | R22: USD | T22: =IF(ISNUMBER(VLOOKUP(U22,Blotter!B:C,2,0)),VLOOKUP(U22,Blotter!B:C,2,0),"") -> 5 | U22: =D22 -> QNEM3 C13800 | V22: =N22 -> 1 | W22: =O22 -> 205 | X22: =Q22 -> -1.42
A23: U11717501 | B23: USD | C23: FUT | D23: NQM3 | E23: NQ 16JUN23 | F23: CME | G23: NQ | H23: 20 | J23: 45093 | L23: 45055 | M23: BUY | N23: 1 | O23: 13290 | P23: 265800 | Q23: -2.2 | R23: USD | T23: =IF(ISNUMBER(VLOOKUP(U23,Blotter!B:C,2,0)),VLOOKUP(U23,Blotter!B:C,2,0),"") -> 5 | U23: =D23 -> NQM3 | V23: =N23 -> 1 | W23: =O23 -> 13290 | X23: =Q23 -> -2.2
A24: U11717501 | B24: USD | C24: FUT | D24: SIN3 | E24: SI 27JUL23 | F24: COMEX | G24: SI | H24: 5000 | J24: 45134 | L24: 45061 | M24: BUY | N24: 1 | O24: 24.28 | P24: 121400 | Q24: -2.42 | R24: USD | T24: =IF(ISNUMBER(VLOOKUP(U24,Blotter!B:C,2,0)),VLOOKUP(U24,Blotter!B:C,2,0),"") -> 6 | U24: =D24 -> SIN3 | V24: =N24 -> 1 | W24: =O24 -> 24.28 | X24: =Q24 -> -2.42
A25: U11717501 | B25: USD | C25: FUT | D25: SIN3 | E25: SI 27JUL23 | F25: COMEX | G25: SI | H25: 5000 | J25: 45134 | L25: 45061 | M25: BUY | N25: 1 | O25: 24.2 | P25: 121000 | Q25: -2.42 | R25: USD | T25: =IF(ISNUMBER(VLOOKUP(U25,Blotter!B:C,2,0)),VLOOKUP(U25,Blotter!B:C,2,0),"") -> 6 | U25: =D25 -> SIN3 | V25: =N25 -> 1 | W25: =O25 -> 24.2 | X25: =Q25 -> -2.42
A26: U11717501 | B26: USD | C26: FOP | D26: QNEM3 C13800 | E26: NQ 30JUN23 13800 C | F26: CME | G26: NQU3 | H26: 20 | I26: 13800 | J26: 45107 | K26: C | L26: 45062 | M26: SELL | N26: -1 | O26: 275 | P26: -5500 | Q26: -1.42 | R26: USD | T26: =IF(ISNUMBER(VLOOKUP(U26,Blotter!B:C,2,0)),VLOOKUP(U26,Blotter!B:C,2,0),"") -> 5 | U26: =D26 -> QNEM3 C13800 | V26: =N26 -> -1 | W26: =O26 -> 275 | X26: =Q26 -> -1.42
A27: U11717501 | B27: USD | C27: FUT | D27: RBM3 | E27: RB JUN23 | F27: NYMEX | G27: RB | H27: 42000 | J27: 45077 | L27: 45063 | M27: SELL | N27: -1 | O27: 2.5487 | P27: -107045.4 | Q27: -2.37 | R27: USD | T27: =IF(ISNUMBER(VLOOKUP(U27,Blotter!B:C,2,0)),VLOOKUP(U27,Blotter!B:C,2,0),"") -> 3 | U27: =D27 -> RBM3 | V27: =N27 -> -1 | W27: =O27 -> 2.5487 | X27: =Q27 -> -2.37
A28: U11717501 | B28: USD | C28: FUT | D28: SIN3 | E28: SI 27JUL23 | F28: COMEX | G28: SI | H28: 5000 | J28: 45134 | L28: 45063 | M28: BUY | N28: 1 | O28: 23.78 | P28: 118900 | Q28: -2.42 | R28: USD | T28: =IF(ISNUMBER(VLOOKUP(U28,Blotter!B:C,2,0)),VLOOKUP(U28,Blotter!B:C,2,0),"") -> 6 | U28: =D28 -> SIN3 | V28: =N28 -> 1 | W28: =O28 -> 23.78 | X28: =Q28 -> -2.42
A29: U11717501 | B29: USD | C29: FUT | D29: NQM3 | E29: NQ 16JUN23 | F29: CME | G29: NQ | H29: 20 | J29: 45093 | L29: 45064 | M29: SELL | N29: -1 | O29: 13800 | P29: -276000 | Q29: -2.2 | R29: USD | T29: =IF(ISNUMBER(VLOOKUP(U29,Blotter!B:C,2,0)),VLOOKUP(U29,Blotter!B:C,2,0),"") -> 5 | U29: =D29 -> NQM3 | V29: =N29 -> -1 | W29: =O29 -> 13800 | X29: =Q29 -> -2.2
A30: U11717501 | B30: USD | C30: FUT | D30: RBM3 | E30: RB JUN23 | F30: NYMEX | G30: RB | H30: 42000 | J30: 45077 | L30: 45065 | M30: SELL | N30: -1 | O30: 2.6 | P30: -109200 | Q30: -2.37 | R30: USD | T30: =IF(ISNUMBER(VLOOKUP(U30,Blotter!B:C,2,0)),VLOOKUP(U30,Blotter!B:C,2,0),"") -> 3 | U30: =D30 -> RBM3 | V30: =N30 -> -1 | W30: =O30 -> 2.6 | X30: =Q30 -> -2.37
A31: U11717501 | B31: USD | C31: FUT | D31: NGN3 | E31: NG JUL23 | F31: NYMEX | G31: NG | H31: 10000 | J31: 45105 | L31: 45068 | M31: BUY | N31: 3 | O31: 2.61 | P31: 78300 | Q31: -7.11 | R31: USD | T31: =IF(ISNUMBER(VLOOKUP(U31,Blotter!B:C,2,0)),VLOOKUP(U31,Blotter!B:C,2,0),"") -> 2 | U31: =D31 -> NGN3 | V31: =N31 -> 3 | W31: =O31 -> 2.61 | X31: =Q31 -> -7.11
A32: U11717501 | B32: USD | C32: FUT | D32: NGN3 | E32: NG JUL23 | F32: NYMEX | G32: NG | H32: 10000 | J32: 45105 | L32: 45068 | M32: BUY | N32: 2 | O32: 2.61 | P32: 52200 | Q32: -4.74 | R32: USD | T32: =IF(ISNUMBER(VLOOKUP(U32,Blotter!B:C,2,0)),VLOOKUP(U32,Blotter!B:C,2,0),"") -> 2 | U32: =D32 -> NGN3 | V32: =N32 -> 2 | W32: =O32 -> 2.61 | X32: =Q32 -> -4.74
A33: U11717501 | B33: USD | C33: FUT | D33: NGM3 | E33: NG JUN23 | F33: NYMEX | G33: NG | H33: 10000 | J33: 45072 | L33: 45070 | M33: SELL | N33: -5 | O33: 2.4 | P33: -120000 | Q33: -11.85 | R33: USD | T33: =IF(ISNUMBER(VLOOKUP(U33,Blotter!B:C,2,0)),VLOOKUP(U33,Blotter!B:C,2,0),"") -> 2 | U33: =D33 -> NGM3 | V33: =N33 -> -5 | W33: =O33 -> 2.4 | X33: =Q33 -> -11.85
A34: U11717501 | B34: USD | C34: FUT | D34: NGN3 | E34: NG JUL23 | F34: NYMEX | G34: NG | H34: 10000 | J34: 45105 | L34: 45071 | M34: BUY | N34: 1 | O34: 2.51 | P34: 25100 | Q34: -2.37 | R34: USD | T34: =IF(ISNUMBER(VLOOKUP(U34,Blotter!B:C,2,0)),VLOOKUP(U34,Blotter!B:C,2,0),"") -> 2 | U34: =D34 -> NGN3 | V34: =N34 -> 1 | W34: =O34 -> 2.51 | X34: =Q34 -> -2.37
A35: U11717501 | B35: USD | C35: FUT | D35: NGN3 | E35: NG JUL23 | F35: NYMEX | G35: NG | H35: 10000 | J35: 45105 | L35: 45071 | M35: BUY | N35: 1 | O35: 2.51 | P35: 25100 | Q35: -2.37 | R35: USD | T35: =IF(ISNUMBER(VLOOKUP(U35,Blotter!B:C,2,0)),VLOOKUP(U35,Blotter!B:C,2,0),"") -> 2 | U35: =D35 -> NGN3 | V35: =N35 -> 1 | W35: =O35 -> 2.51 | X35: =Q35 -> -2.37
A36: U11717501 | B36: USD | C36: FUT | D36: NGN3 | E36: NG JUL23 | F36: NYMEX | G36: NG | H36: 10000 | J36: 45105 | L36: 45071 | M36: BUY | N36: 1 | O36: 2.51 | P36: 25100 | Q36: -2.37 | R36: USD | T36: =IF(ISNUMBER(VLOOKUP(U36,Blotter!B:C,2,0)),VLOOKUP(U36,Blotter!B:C,2,0),"") -> 2 | U36: =D36 -> NGN3 | V36: =N36 -> 1 | W36: =O36 -> 2.51 | X36: =Q36 -> -2.37
A37: U11717501 | B37: USD | C37: FUT | D37: NGN3 | E37: NG JUL23 | F37: NYMEX | G37: NG | H37: 10000 | J37: 45105 | L37: 45071 | M37: BUY | N37: 2 | O37: 2.51 | P37: 50200 | Q37: -4.74 | R37: USD | T37: =IF(ISNUMBER(VLOOKUP(U37,Blotter!B:C,2,0)),VLOOKUP(U37,Blotter!B:C,2,0),"") -> 2 | U37: =D37 -> NGN3 | V37: =N37 -> 2 | W37: =O37 -> 2.51 | X37: =Q37 -> -4.74
A38: U11717501 | B38: USD | C38: FUT | D38: SIN3 | E38: SI 27JUL23 | F38: COMEX | G38: SI | H38: 5000 | J38: 45134 | L38: 45071 | M38: BUY | N38: 1 | O38: 22.89 | P38: 114450 | Q38: -2.42 | R38: USD | T38: =IF(ISNUMBER(VLOOKUP(U38,Blotter!B:C,2,0)),VLOOKUP(U38,Blotter!B:C,2,0),"") -> 6 | U38: =D38 -> SIN3 | V38: =N38 -> 1 | W38: =O38 -> 22.89 | X38: =Q38 -> -2.42
... A54: U11717501 | B54: USD | C54: FUT | D54: NGN3 | E54: NG JUL23 | F54: NYMEX | G54: NG | H54: 10000 | J54: 45105 | L54: 45078 | M54: BUY | N54: 5 | O54: 2.159 | P54: 107950 | Q54: -11.85 | R54: USD | T54: =IF(ISNUMBER(VLOOKUP(U54,Blotter!B:C,2,0)),VLOOKUP(U54,Blotter!B:C,2,0),"") -> 2 | U54: =D54 -> NGN3 | V54: =N54 -> 5 | W54: =O54 -> 2.159 | X54: =Q54 -> -11.85
A55: U11717501 | B55: USD | C55: OPT | D55: INDA 231215C00044000 | E55: INDA 15DEC23 44 C | F55: CBOE | G55: INDA | H55: 100 | I55: 44 | J55: 45275 | K55: C | L55: 45082 | M55: BUY | N55: 16 | O55: 1.35 | P55: 2160 | Q55: 0.8152 | R55: USD | T55: =IF(ISNUMBER(VLOOKUP(U55,Blotter!B:C,2,0)),VLOOKUP(U55,Blotter!B:C,2,0),"") -> 9 | U55: =D55 -> INDA 231215C00044000 | V55: =N55 -> 16 | W55: =O55 -> 1.35 | X55: =Q55 -> 0.8152
A56: U11717501 | B56: USD | C56: FUT | D56: HGN3 | E56: HG 27JUL23 | F56: COMEX | G56: HG | H56: 25000 | J56: 45134 | L56: 45082 | M56: BUY | N56: 2 | O56: 3.71 | P56: 185500 | Q56: -4.84 | R56: USD | T56: =IF(ISNUMBER(VLOOKUP(U56,Blotter!B:C,2,0)),VLOOKUP(U56,Blotter!B:C,2,0),"") -> 8 | U56: =D56 -> HGN3 | V56: =N56 -> 2 | W56: =O56 -> 3.71 | X56: =Q56 -> -4.84
A57: U11717501 | B57: USD | C57: FUT | D57: NGN3 | E57: NG JUL23 | F57: NYMEX | G57: NG | H57: 10000 | J57: 45105 | L57: 45082 | M57: SELL | N57: -10 | O57: 2.26 | P57: -226000 | Q57: -23.7 | R57: USD | T57: =IF(ISNUMBER(VLOOKUP(U57,Blotter!B:C,2,0)),VLOOKUP(U57,Blotter!B:C,2,0),"") -> 2 | U57: =D57 -> NGN3 | V57: =N57 -> -10 | W57: =O57 -> 2.26 | X57: =Q57 -> -23.7
A58: U11717501 | B58: USD | C58: OPT | D58: INDA 231215C00044000 | E58: INDA 15DEC23 44 C | F58: CBOE | G58: INDA | H58: 100 | I58: 44 | J58: 45275 | K58: C | L58: 45083 | M58: BUY | N58: 10 | O58: 1.4 | P58: 1400 | Q58: 0.5095 | R58: USD | T58: =IF(ISNUMBER(VLOOKUP(U58,Blotter!B:C,2,0)),VLOOKUP(U58,Blotter!B:C,2,0),"") -> 9 | U58: =D58 -> INDA 231215C00044000 | V58: =N58 -> 10 | W58: =O58 -> 1.4 | X58: =Q58 -> 0.5095
A59: U11717501 | B59: USD | C59: OPT | D59: INDA 231215C00044000 | E59: INDA 15DEC23 44 C | F59: CBOE | G59: INDA | H59: 100 | I59: 44 | J59: 45275 | K59: C | L59: 45083 | M59: BUY | N59: 10 | O59: 1.4 | P59: 1400 | Q59: 0.5095 | R59: USD | T59: =IF(ISNUMBER(VLOOKUP(U59,Blotter!B:C,2,0)),VLOOKUP(U59,Blotter!B:C,2,0),"") -> 9 | U59: =D59 -> INDA 231215C00044000 | V59: =N59 -> 10 | W59: =O59 -> 1.4 | X59: =Q59 -> 0.5095
A60: U11717501 | B60: USD | C60: OPT | D60: INDA 231215C00044000 | E60: INDA 15DEC23 44 C | F60: CBOE | G60: INDA | H60: 100 | I60: 44 | J60: 45275 | K60: C | L60: 45083 | M60: BUY | N60: 14 | O60: 1.45 | P60: 2030 | Q60: 0.7133 | R60: USD | T60: =IF(ISNUMBER(VLOOKUP(U60,Blotter!B:C,2,0)),VLOOKUP(U60,Blotter!B:C,2,0),"") -> 9 | U60: =D60 -> INDA 231215C00044000 | V60: =N60 -> 14 | W60: =O60 -> 1.45 | X60: =Q60 -> 0.7133
A61: U11717501 | B61: USD | C61: FUT | D61: NGN3 | E61: NG JUL23 | F61: NYMEX | G61: NG | H61: 10000 | J61: 45105 | L61: 45083 | M61: BUY | N61: 1 | O61: 2.21 | P61: 22100 | Q61: -2.37 | R61: USD | T61: =IF(ISNUMBER(VLOOKUP(U61,Blotter!B:C,2,0)),VLOOKUP(U61,Blotter!B:C,2,0),"") -> 2 | U61: =D61 -> NGN3 | V61: =N61 -> 1 | W61: =O61 -> 2.21 | X61: =Q61 -> -2.37
A62: U11717501 | B62: USD | C62: FUT | D62: NGN3 | E62: NG JUL23 | F62: NYMEX | G62: NG | H62: 10000 | J62: 45105 | L62: 45083 | M62: BUY | N62: 1 | O62: 2.21 | P62: 22100 | Q62: -2.37 | R62: USD | T62: =IF(ISNUMBER(VLOOKUP(U62,Blotter!B:C,2,0)),VLOOKUP(U62,Blotter!B:C,2,0),"") -> 2 | U62: =D62 -> NGN3 | V62: =N62 -> 1 | W62: =O62 -> 2.21 | X62: =Q62 -> -2.37
